Workbook
Name COVERAGE: Tables!$T$3:$U$17
Name ITEMS: 'Item Builder'!$A$4:$FH$251
Name LAYERS: Tables!$AB$3:$AC$13
Name MATERIAL: Tables!$B$3:$N$36
Name MWS: Tables!$W$3:$Z$8

Sheet Standard Suits
C1: HMK page 113 | L1: HMK page 114 | U1: HMK page 115 | AD1: HMK page 116
B2: Suit Name: | C2: Light Clothing | K2: Suit Name: | L2: Kûrbúl Cuirass | T2: Suit Name: | U2: Gambeson | AC2: Suit Name: | AD2: Mail Hauberk
B3: Item List | C3: Suit is NOT LEGAL!! | K3: Item List | T3: Item List | AC3: Item List
A4: 0 | B4: Buckram Vest | C4: Price | D4: ENC | E4: PER | F4: Area | G4: LB | J4: 0 | K4: Plate Helm | L4: Price | M4: ENC | N4: PER | O4: Area | P4: LB | S4: 0 | T4: Plate Helm | U4: Price | V4: ENC | W4: PER | X4: Area | Y4: LB | AB4: 0 | AC4: Mail Cowl | AD4: Price | AE4: ENC | AF4: PER | AG4: Area | AH4: LB
A5: 0 | B5: Buckram Tunic | C5: 115 | D5: 0 | E5: 0 | F5: 1 | G5: 5.75 | J5: 0 | K5: Padded Cap | L5: 487 | M5: 5 | N5: 0 | O5: 4 | P5: 25.65 | S5: 0 | T5: Padded Cap | U5: 811 | V5: 10 | W5: 0 | X5: 5 | Y5: 30.69 | AB5: 0 | AC5: Padded Cowl | AD5: 2014 | AE5: 25 | AF5: 10 | AG5: 6 | AH5: 62.08
A6: 0 | B6: Buckram Breeches | J6: 0 | K6: Kûrbúl Spaulders | S6: 0 | T6: Gambeson Coat | AB6: 0 | AC6: Plate Coudes
A7: 0 | B7: Buckram Swaddle | C7: Loc | D7: B | E7: E | F7: P | G7: F | J7: 0 | K7: Kûrbúl Rerebraces | L7: Loc | M7: B | N7: E | O7: P | P7: F | S7: 0 | T7: Buckram Vest | U7: Loc | V7: B | W7: E | X7: P | Y7: F | AB7: 0 | AC7: Mail Mittens | AD7: Loc | AE7: B | AF7: E | AG7: P | AH7: F
A8: 0 | C8: Sk | D8: 0 | E8: 0 | F8: 0 | G8: 0 | H8: 0 | J8: 0 | K8: Kûrbúl Cuirass | L8: Sk | M8: 8 | N8: 13 | O8: 10 | P8: 7 | Q8: 4 | S8: 0 | T8: Kûrbúl Kneecops | U8: Sk | V8: 8 | W8: 13 | X8: 10 | Y8: 7 | Z8: 4 | AB8: 0 | AC8: Padded Mittens | AD8: Sk | AE8: 4 | AF8: 10 | AG8: 8 | AH8: 5 | AI8: 3
A9: 0 | C9: Fa | D9: 0 | E9: 0 | F9: 0 | G9: 0 | H9: 0 | J9: 0 | K9: Padded Tunic, Sleeved | L9: Fa | M9: 0 | N9: 0 | O9: 0 | P9: 0 | Q9: 0 | S9: 0 | T9: Padded Cuisses | U9: Fa | V9: 0 | W9: 0 | X9: 0 | Y9: 0 | Z9: 0 | AB9: 0 | AC9: Mail Hauberk | AD9: Fa | AE9: 0 | AF9: 0 | AG9: 0 | AH9: 0 | AI9: 0
A10: 0 | C10: Nk | D10: 0 | E10: 0 | F10: 0 | G10: 0 | H10: 0 | J10: 0 | K10: Buckram Trousers | L10: Nk | M10: 0 | N10: 0 | O10: 0 | P10: 0 | Q10: 0 | S10: 0 | T10: Buckram Breeches | U10: Nk | V10: 6 | W10: 5 | X10: 4 | Y10: 5 | Z10: 1 | AB10: 0 | AC10: Padded Coat | AD10: Nk | AE10: 4 | AF10: 10 | AG10: 8 | AH10: 5 | AI10: 3
A11: 0 | C11: Sh | D11: 0 | E11: 1 | F11: 0 | G11: 1 | H11: 0 | J11: 0 | K11: Buckram Swaddle | L11: Sh | M11: 6 | N11: 8 | O11: 6 | P11: 6 | Q11: 2 | S11: 0 | T11: Buckram Swaddle | U11: Sh | V11: 6 | W11: 5 | X11: 4 | Y11: 5 | Z11: 1 | AB11: 0 | AC11: Buckram Breeches | AD11: Sh | AE11: 4 | AF11: 10 | AG11: 8 | AH11: 5 | AI11: 3
A12: 0 | C12: Ua | D12: 0 | E12: 1 | F12: 0 | G12: 1 | H12: 0 | J12: 0 | K12: Leather Boots | L12: Ua | M12: 6 | N12: 8 | O12: 6 | P12: 6 | Q12: 2 | S12: 0 | T12: Leather Boots | U12: Ua | V12: 6 | W12: 5 | X12: 4 | Y12: 5 | Z12: 1 | AB12: 0 | AC12: Plate Kneecops | AD12: Ua | AE12: 4 | AF12: 10 | AG12: 8 | AH12: 5 | AI12: 3
A13: 0 | C13: El | D13: 0 | E13: 1 | F13: 0 | G13: 1 | H13: 0 | J13: 0 | L13: El | M13: 2 | N13: 2 | O13: 1 | P13: 2 | Q13: 0 | S13: 0 | U13: El | V13: 6 | W13: 5 | X13: 4 | Y13: 5 | Z13: 1 | AB13: 0 | AC13: Mail Leggings | AD13: El | AE13: 10 | AF13: 21 | AG13: 17 | AH13: 10 | AI13: 4
A14: 0 | C14: Fo | D14: 0 | E14: 0 | F14: 0 | G14: 0 | H14: 0 | J14: 0 | L14: Fo | M14: 2 | N14: 2 | O14: 1 | P14: 2 | Q14: 0 | S14: 0 | U14: Fo | V14: 6 | W14: 5 | X14: 4 | Y14: 5 | Z14: 1 | AB14: 0 | AC14: Padded Leggings | AD14: Fo | AE14: 4 | AF14: 10 | AG14: 8 | AH14: 5 | AI14: 3
A15: 0 | C15: Ha | D15: 0 | E15: 0 | F15: 0 | G15: 0 | H15: 0 | J15: 0 | L15: Ha | M15: 0 | N15: 0 | O15: 0 | P15: 0 | Q15: 0 | S15: 0 | U15: Ha | V15: 0 | W15: 0 | X15: 0 | Y15: 0 | Z15: 0 | AB15: 0 | AD15: Ha | AE15: 4 | AF15: 10 | AG15: 8 | AH15: 5 | AI15: 3
A16: 0 | C16: Tx | D16: 0 | E16: 2 | F16: 0 | G16: 2 | H16: 0 | J16: 0 | L16: Tx | M16: 6 | N16: 8 | O16: 6 | P16: 6 | Q16: 2 | S16: 0 | U16: Tx | V16: 6 | W16: 6 | X16: 4 | Y16: 6 | Z16: 1 | AB16: 0 | AD16: Tx | AE16: 4 | AF16: 10 | AG16: 8 | AH16: 5 | AI16: 3
A17: 0 | C17: Ab | D17: 0 | E17: 2 | F17: 0 | G17: 2 | H17: 0 | J17: 0 | L17: Ab | M17: 6 | N17: 8 | O17: 6 | P17: 6 | Q17: 2 | S17: 0 | U17: Ab | V17: 6 | W17: 6 | X17: 4 | Y17: 6 | Z17: 1 | AB17: 0 | AD17: Ab | AE17: 4 | AF17: 10 | AG17: 8 | AH17: 5 | AI17: 3
A18: 0 | C18: Pv | D18: 0 | E18: 2 | F18: 0 | G18: 2 | H18: 0 | J18: 0 | L18: Pv | M18: 2 | N18: 3 | O18: 1 | P18: 3 | Q18: 0 | S18: 0 | U18: Pv | V18: 6 | W18: 6 | X18: 4 | Y18: 6 | Z18: 1 | AB18: 0 | AD18: Pv | AE18: 4 | AF18: 11 | AG18: 8 | AH18: 6 | AI18: 3
A19: 0 | C19: Th | D19: 0 | E19: 1 | F19: 0 | G19: 1 | H19: 0 | J19: 0 | L19: Th | M19: 0 | N19: 1 | O19: 0 | P19: 1 | Q19: 0 | S19: 0 | U19: Th | V19: 8 | W19: 8 | X19: 5 | Y19: 8 | Z19: 1 | AB19: 0 | AD19: Th | AE19: 8 | AF19: 21 | AG19: 16 | AH19: 11 | AI19: 3
A20: 0 | C20: Kn | D20: 0 | E20: 1 | F20: 0 | G20: 1 | H20: 0 | J20: 0 | L20: Kn | M20: 0 | N20: 1 | O20: 0 | P20: 1 | Q20: 0 | S20: 0 | U20: Kn | V20: 6 | W20: 9 | X20: 6 | Y20: 7 | Z20: 2 | AB20: 0 | AD20: Kn | AE20: 10 | AF20: 22 | AG20: 17 | AH20: 11 | AI20: 4
A21: 0 | C21: Cf | D21: 0 | E21: 1 | F21: 0 | G21: 1 | H21: 0 | J21: 0 | L21: Cf | M21: 1 | N21: 4 | O21: 1 | P21: 5 | Q21: 0 | S21: 0 | U21: Cf | V21: 1 | W21: 3 | X21: 1 | Y21: 4 | Z21: 0 | AB21: 0 | AD21: Cf | AE21: 4 | AF21: 10 | AG21: 8 | AH21: 5 | AI21: 3
A22: 0 | C22: Ft | D22: 0 | E22: 1 | F22: 0 | G22: 1 | H22: 0 | J22: 0 | L22: Ft | M22: 1 | N22: 3 | O22: 1 | P22: 4 | Q22: 0 | S22: 0 | U22: Ft | V22: 1 | W22: 3 | X22: 1 | Y22: 4 | Z22: 0 | AB22: 0 | AD22: Ft | AE22: 4 | AF22: 10 | AG22: 8 | AH22: 5 | AI22: 3
A23: 0 | J23: 0 | S23: 0 | AB23: 0
A24: 0 | D24: Bulk Penalty: | J24: 0 | M24: Bulk Penalty: | S24: 0 | V24: Bulk Penalty: | AB24: 0 | AE24: Bulk Penalty:
A25: 0 | D25: Head | E25: 0 | J25: 0 | M25: Head | N25: 0 | S25: 0 | V25: Head | W25: 0 | AB25: 0 | AE25: Head | AF25: 0
A26: 0 | D26: Arms | E26: 0 | J26: 0 | M26: Arms | N26: 0 | S26: 0 | V26: Arms | W26: 0 | AB26: 0 | AE26: Arms | AF26: 0
A27: 0 | D27: Torso | E27: 0 | J27: 0 | M27: Torso | N27: 0 | S27: 0 | V27: Torso | W27: 0 | AB27: 0 | AE27: Torso | AF27: 0
A28: 0 | D28: Legs | E28: 0 | J28: 0 | M28: Legs | N28: 0 | S28: 0 | V28: Legs | W28: 0 | AB28: 0 | AE28: Legs | AF28: 0
A29: 0 | J29: 0 | S29: 0 | AB29: 0
A30: 0 | J30: 0 | S30: 0 | AB30: 0
A31: 0 | J31: 0 | S31: 0 | AB31: 0
B35: Suit Name: | C35: Heavy Clothing | K35: Suit Name: | L35: Scale Byrnie | T35: Suit Name: | U35: Scale Habergeoun | AC35: Suit Name: | AD35: Kûrbúl & Mail
B36: Item List | K36: Item List | T36: Item List | AC36: Item List
A37: 0 | B37: Leather Cap | C37: Price | D37: ENC | E37: PER | F37: Area | G37: LB | J37: 0 | K37: Plate Helm | L37: Price | M37: ENC | N37: PER | O37: Area | P37: LB | S37: 0 | T37: Plate 3/4-Helm | U37: Price | V37: ENC | W37: PER | X37: Area | Y37: LB | AB37: 0 | AC37: Plate 3/4-Helm | AD37: Price | AE37: ENC | AF37: PER | AG37: Area | AH37: LB
A38: 0 | B38: Padded Shirt | C38: 260 | D38: 0 | E38: 0 | F38: 2 | G38: 11.79 | J38: 0 | K38: Padded Cap | L38: 680 | M38: 10 | N38: 0 | O38: 4 | P38: 32.38 | S38: 0 | T38: Padded Cap | U38: 961 | V38: 15 | W38: 5 | X38: 6 | Y38: 46.38 | AB38: 0 | AC38: Mail Cowl | AD38: 2484 | AE38: 40 | AF38: 15 | AG38: 8 | AH38: 84.5
A39: 0 | B39: Buckram Tunic, Sleeved | J39: 0 | K39: Scale Byrnie | S39: 0 | T39: Kûrbúl Spaulders | AB39: 0 | AC39: Padded Cowl
A40: 0 | B40: Buckram Surcoat | C40: Loc | D40: B | E40: E | F40: P | G40: F | J40: 0 | K40: Padded Coat | L40: Loc | M40: B | N40: E | O40: P | P40: F | S40: 0 | T40: Kûrbúl Coudes | U40: Loc | V40: B | W40: E | X40: P | Y40: F | AB40: 0 | AC40: Kûrbúl Spaulders | AD40: Loc | AE40: B | AF40: E | AG40: P | AH40: F
A41: 0 | B41: Buckram Breeches | C41: Sk | D41: 1 | E41: 2 | F41: 1 | G41: 3 | H41: 2 | J41: 0 | K41: Buckram Trousers | L41: Sk | M41: 8 | N41: 13 | O41: 10 | P41: 7 | Q41: 4 | S41: 0 | T41: Leather Gauntlets | U41: Sk | V41: 8 | W41: 13 | X41: 10 | Y41: 7 | Z41: 4 | AB41: 0 | AC41: Kûrbúl Rerebraces | AD41: Sk | AE41: 10 | AF41: 21 | AG41: 17 | AH41: 10 | AI41: 3
A42: 0 | B42: Buckram Swaddle | C42: Fa | D42: 0 | E42: 0 | F42: 0 | G42: 0 | H42: 0 | J42: 0 | K42: Buckram Swaddle | L42: Fa | M42: 0 | N42: 0 | O42: 0 | P42: 0 | Q42: 0 | S42: 0 | T42: Scale Habergeoun | U42: Fa | V42: 6 | W42: 11 | X42: 9 | Y42: 5 | Z42: 0 | AB42: 0 | AC42: Kûrbúl Coudes | AD42: Fa | AE42: 6 | AF42: 11 | AG42: 9 | AH42: 5 | AI42: 0
A43: 0 | B43: Leather Shoes | C43: Nk | D43: 0 | E43: 0 | F43: 0 | G43: 0 | H43: 0 | J43: 0 | K43: Leather Boots | L43: Nk | M43: 0 | N43: 0 | O43: 0 | P43: 0 | Q43: 0 | S43: 0 | T43: Padded Coat | U43: Nk | V43: 0 | W43: 0 | X43: 0 | Y43: 0 | Z43: 0 | AB43: 0 | AC43: Mail Mittens | AD43: Nk | AE43: 4 | AF43: 10 | AG43: 8 | AH43: 5 | AI43: 3
A44: 0 | C44: Sh | D44: 2 | E44: 4 | F44: 1 | G44: 4 | H44: 0 | J44: 0 | L44: Sh | M44: 6 | N44: 10 | O44: 6 | P44: 7 | Q44: 3 | S44: 0 | T44: Buckram Breeches | U44: Sh | V44: 10 | W44: 16 | X44: 11 | Y44: 11 | Z44: 3 | AB44: 0 | AC44: Padded Mittens | AD44: Sh | AE44: 8 | AF44: 16 | AG44: 13 | AH44: 9 | AI44: 3
A45: 0 | C45: Ua | D45: 2 | E45: 3 | F45: 1 | G45: 3 | H45: 0 | J45: 0 | L45: Ua | M45: 6 | N45: 10 | O45: 6 | P45: 7 | Q45: 3 | S45: 0 | T45: Kûrbúl Kneecops | U45: Ua | V45: 6 | W45: 10 | X45: 6 | Y45: 7 | Z45: 3 | AB45: 0 | AC45: Kûrbúl Cuirass | AD45: Ua | AE45: 8 | AF45: 16 | AG45: 13 | AH45: 9 | AI45: 3
A46: 0 | C46: El | D46: 0 | E46: 1 | F46: 0 | G46: 1 | H46: 0 | J46: 0 | L46: El | M46: 2 | N46: 2 | O46: 1 | P46: 2 | Q46: 0 | S46: 0 | T46: Padded Leggings | U46: El | V46: 10 | W46: 16 | X46: 11 | Y46: 11 | Z46: 0 | AB46: 0 | AC46: Mail Hauberk | AD46: El | AE46: 8 | AF46: 16 | AG46: 13 | AH46: 9 | AI46: 4
A47: 0 | C47: Fo | D47: 0 | E47: 1 | F47: 0 | G47: 1 | H47: 0 | J47: 0 | L47: Fo | M47: 2 | N47: 2 | O47: 1 | P47: 2 | Q47: 0 | S47: 0 | T47: Leather Boots | U47: Fo | V47: 2 | W47: 2 | X47: 1 | Y47: 2 | Z47: 0 | AB47: 0 | AC47: Padded Coat | AD47: Fo | AE47: 4 | AF47: 10 | AG47: 8 | AH47: 5 | AI47: 3
A48: 0 | C48: Ha | D48: 0 | E48: 0 | F48: 0 | G48: 0 | H48: 0 | J48: 0 | L48: Ha | M48: 0 | N48: 0 | O48: 0 | P48: 0 | Q48: 0 | S48: 0 | U48: Ha | V48: 1 | W48: 2 | X48: 1 | Y48: 3 | Z48: 0 | AB48: 0 | AC48: Buckram Breeches | AD48: Ha | AE48: 4 | AF48: 10 | AG48: 8 | AH48: 5 | AI48: 3
A49: 0 | C49: Tx | D49: 2 | E49: 4 | F49: 1 | G49: 4 | H49: 0 | J49: 0 | L49: Tx | M49: 6 | N49: 10 | O49: 6 | P49: 7 | Q49: 3 | S49: 0 | U49: Tx | V49: 6 | W49: 10 | X49: 6 | Y49: 7 | Z49: 3 | AB49: 0 | AC49: Kûrbúl Kneecops | AD49: Tx | AE49: 8 | AF49: 16 | AG49: 13 | AH49: 9 | AI49: 3
A50: 0 | C50: Ab | D50: 2 | E50: 4 | F50: 1 | G50: 4 | H50: 0 | J50: 0 | L50: Ab | M50: 6 | N50: 10 | O50: 6 | P50: 7 | Q50: 3 | S50: 0 | U50: Ab | V50: 6 | W50: 10 | X50: 6 | Y50: 7 | Z50: 3 | AB50: 0 | AC50: Plate Greaves | AD50: Ab | AE50: 8 | AF50: 16 | AG50: 13 | AH50: 9 | AI50: 3
A51: 0 | C51: Pv | D51: 0 | E51: 3 | F51: 0 | G51: 3 | H51: 0 | J51: 0 | L51: Pv | M51: 2 | N51: 3 | O51: 1 | P51: 3 | Q51: 0 | S51: 0 | U51: Pv | V51: 6 | W51: 11 | X51: 6 | Y51: 8 | Z51: 0 | AB51: 0 | AC51: Mail Leggings | AD51: Pv | AE51: 4 | AF51: 11 | AG51: 8 | AH51: 6 | AI51: 3
A52: 0 | C52: Th | D52: 0 | E52: 2 | F52: 0 | G52: 2 | H52: 0 | J52: 0 | L52: Th | M52: 2 | N52: 3 | O52: 1 | P52: 3 | Q52: 0 | S52: 0 | U52: Th | V52: 4 | W52: 5 | X52: 2 | Y52: 5 | Z52: 0 | AB52: 0 | AC52: Padded Leggings | AD52: Th | AE52: 8 | AF52: 21 | AG52: 16 | AH52: 11 | AI52: 3
A53: 0 | C53: Kn | D53: 0 | E53: 2 | F53: 0 | G53: 2 | H53: 0 | J53: 0 | L53: Kn | M53: 0 | N53: 1 | O53: 0 | P53: 1 | Q53: 0 | S53: 0 | U53: Kn | V53: 6 | W53: 9 | X53: 6 | Y53: 7 | Z53: 0 | AB53: 0 | AD53: Kn | AE53: 8 | AF53: 17 | AG53: 13 | AH53: 10 | AI53: 4
A54: 0 | C54: Cf | D54: 0 | E54: 1 | F54: 0 | G54: 1 | H54: 0 | J54: 0 | L54: Cf | M54: 1 | N54: 4 | O54: 1 | P54: 5 | Q54: 0 | S54: 0 | U54: Cf | V54: 3 | W54: 4 | X54: 2 | Y54: 5 | Z54: 0 | AB54: 0 | AD54: Cf | AE54: 10 | AF54: 21 | AG54: 17 | AH54: 10 | AI54: 3
A55: 0 | C55: Ft | D55: 1 | E55: 3 | F55: 1 | G55: 4 | H55: 0 | J55: 0 | L55: Ft | M55: 1 | N55: 3 | O55: 1 | P55: 4 | Q55: 0 | S55: 0 | U55: Ft | V55: 3 | W55: 4 | X55: 2 | Y55: 5 | Z55: 0 | AB55: 0 | AD55: Ft | AE55: 4 | AF55: 10 | AG55: 8 | AH55: 5 | AI55: 3
A56: 0 | J56: 0 | S56: 0 | AB56: 0
A57: 0 | D57: Bulk Penalty: | J57: 0 | M57: Bulk Penalty: | S57: 0 | V57: Bulk Penalty: | AB57: 0 | AE57: Bulk Penalty:
A58: 0 | D58: Head | E58: 0 | J58: 0 | M58: Head | N58: 0 | S58: 0 | V58: Head | W58: 0 | AB58: 0 | AE58: Head | AF58: 0
A59: 0 | D59: Arms | E59: 0 | J59: 0 | M59: Arms | N59: 0 | S59: 0 | V59: Arms | W59: 0 | AB59: 0 | AE59: Arms | AF59: 0
A60: 0 | D60: Torso | E60: 0 | J60: 0 | M60: Torso | N60: 0 | S60: 0 | V60: Torso | W60: 0 | AB60: 0 | AE60: Torso | AF60: 0
A61: 0 | D61: Legs | E61: 0 | J61: 0 | M61: Legs | N61: 0 | S61: 0 | V61: Legs | W61: 0 | AB61: 0 | AE61: Legs | AF61: 0
A62: 0 | J62: 0 | S62: 0 | AB62: 0
A63: 0 | J63: 0 | S63: 0 | AB63: 0
A64: 0 | J64: 0 | S64: 0 | AB64: 0
B68: Suit Name: | C68: Quilted Coat | K68: Suit Name: | L68: Mail Byrnie | T68: Suit Name: | U68: Mail Habergeoun | AC68: Suit Name: | AD68: Plate & Mail
B69: Item List | K69: Item List | T69: Item List | AC69: Item List
A70: 0 | B70: Kûrbúl Helm | C70: Price | D70: ENC | E70: PER | F70: Area | G70: LB | J70: 0 | K70: Plate Helm | L70: Price | M70: ENC | N70: PER | O70: Area | P70: LB | S70: 0 | T70: Plate Helm | U70: Price | V70: ENC | W70: PER | X70: Area | Y70: LB | AB70: 0 | AC70: Plate Greathelm | AD70: Price | AE70: ENC | AF70: PER | AG70: Area | AH70: LB
A71: 0 | B71: Padded Cap | C71: 420 | D71: 5 | E71: 0 | F71: 3 | G71: 21.33 | J71: 0 | K71: Padded Cap | L71: 807 | M71: 5 | N71: 0 | O71: 3 | P71: 27.56 | S71: 0 | T71: Padded Cap | U71: 1081 | V71: 10 | W71: 0 | X71: 5 | Y71: 36.95 | AB71: 0 | AC71: Mail Cowl | AD71: 3194 | AE71: 40 | AF71: 20 | AG71: 9 | AH71: 87.92
A72: 0 | B72: Quilted Coat | J72: 0 | K72: Mail Byrnie | S72: 0 | T72: Mail Habergeoun | AB72: 0 | AC72: Padded Cowl
A73: 0 | B73: Buckram Tunic | C73: Loc | D73: B | E73: E | F73: P | G73: F | J73: 0 | K73: Padded Tunic | L73: Loc | M73: B | N73: E | O73: P | P73: F | S73: 0 | T73: Padded Coat | U73: Loc | V73: B | W73: E | X73: P | Y73: F | AB73: 0 | AC73: Plate Spaulders | AD73: Loc | AE73: B | AF73: E | AG73: P | AH73: F
A74: 0 | B74: Buckram Breeches | C74: Sk | D74: 6 | E74: 8 | F74: 6 | G74: 6 | H74: 4 | J74: 0 | K74: Buckram Trousers | L74: Sk | M74: 8 | N74: 13 | O74: 10 | P74: 7 | Q74: 4 | S74: 0 | T74: Buckram Breeches | U74: Sk | V74: 8 | W74: 13 | X74: 10 | Y74: 7 | Z74: 4 | AB74: 0 | AC74: Plate Rerebraces | AD74: Sk | AE74: 10 | AF74: 21 | AG74: 17 | AH74: 10 | AI74: 4
A75: 0 | B75: Buckram Leggings | C75: Fa | D75: 0 | E75: 0 | F75: 0 | G75: 0 | H75: 0 | J75: 0 | K75: Buckram Swaddle | L75: Fa | M75: 0 | N75: 0 | O75: 0 | P75: 0 | Q75: 0 | S75: 0 | T75: Kûrbúl Kneecops | U75: Fa | V75: 0 | W75: 0 | X75: 0 | Y75: 0 | Z75: 0 | AB75: 0 | AC75: Plate Coudes | AD75: Fa | AE75: 6 | AF75: 11 | AG75: 9 | AH75: 5 | AI75: 4
A76: 0 | B76: Leather Shoes | C76: Nk | D76: 0 | E76: 0 | F76: 0 | G76: 0 | H76: 1 | J76: 0 | K76: Leather Boots | L76: Nk | M76: 0 | N76: 0 | O76: 0 | P76: 0 | Q76: 0 | S76: 0 | T76: Padded Leggings | U76: Nk | V76: 0 | W76: 0 | X76: 0 | Y76: 0 | Z76: 0 | AB76: 0 | AC76: Plate Vambraces | AD76: Nk | AE76: 10 | AF76: 21 | AG76: 17 | AH76: 10 | AI76: 4
A77: 0 | C77: Sh | D77: 4 | E77: 4 | F77: 2 | G77: 4 | H77: 1 | J77: 0 | L77: Sh | M77: 4 | N77: 10 | O77: 8 | P77: 5 | Q77: 3 | S77: 0 | T77: Leather Boots | U77: Sh | V77: 4 | W77: 10 | X77: 8 | Y77: 5 | Z77: 3 | AB77: 0 | AC77: Mail Mittens | AD77: Sh | AE77: 10 | AF77: 21 | AG77: 17 | AH77: 10 | AI77: 4
A78: 0 | C78: Ua | D78: 4 | E78: 4 | F78: 2 | G78: 4 | H78: 1 | J78: 0 | L78: Ua | M78: 4 | N78: 10 | O78: 8 | P78: 5 | Q78: 3 | S78: 0 | U78: Ua | V78: 4 | W78: 10 | X78: 8 | Y78: 5 | Z78: 3 | AB78: 0 | AC78: Padded Mittens | AD78: Ua | AE78: 10 | AF78: 21 | AG78: 17 | AH78: 10 | AI78: 4
A79: 0 | C79: El | D79: 4 | E79: 4 | F79: 2 | G79: 4 | H79: 1 | J79: 0 | L79: El | M79: 2 | N79: 2 | O79: 1 | P79: 2 | Q79: 0 | S79: 0 | U79: El | V79: 4 | W79: 10 | X79: 8 | Y79: 5 | Z79: 3 | AB79: 0 | AC79: Plate Cuirass | AD79: El | AE79: 10 | AF79: 21 | AG79: 17 | AH79: 10 | AI79: 4
A80: 0 | C80: Fo | D80: 4 | E80: 3 | F80: 2 | G80: 3 | H80: 1 | J80: 0 | L80: Fo | M80: 0 | N80: 0 | O80: 0 | P80: 0 | Q80: 0 | S80: 0 | U80: Fo | V80: 2 | W80: 2 | X80: 1 | Y80: 2 | Z80: 0 | AB80: 0 | AC80: Mail Hauberk | AD80: Fo | AE80: 10 | AF80: 21 | AG80: 17 | AH80: 10 | AI80: 4
A81: 0 | C81: Ha | D81: 0 | E81: 0 | F81: 0 | G81: 0 | H81: 0 | J81: 0 | L81: Ha | M81: 0 | N81: 0 | O81: 0 | P81: 0 | Q81: 0 | S81: 0 | U81: Ha | V81: 0 | W81: 0 | X81: 0 | Y81: 0 | Z81: 0 | AB81: 0 | AC81: Padded Coat | AD81: Ha | AE81: 4 | AF81: 10 | AG81: 8 | AH81: 5 | AI81: 3
A82: 0 | C82: Tx | D82: 4 | E82: 4 | F82: 2 | G82: 4 | H82: 1 | J82: 0 | L82: Tx | M82: 4 | N82: 10 | O82: 8 | P82: 5 | Q82: 3 | S82: 0 | U82: Tx | V82: 4 | W82: 10 | X82: 8 | Y82: 5 | Z82: 3 | AB82: 0 | AC82: Buckram Breeches | AD82: Tx | AE82: 10 | AF82: 21 | AG82: 17 | AH82: 10 | AI82: 4
A83: 0 | C83: Ab | D83: 4 | E83: 4 | F83: 2 | G83: 4 | H83: 1 | J83: 0 | L83: Ab | M83: 4 | N83: 10 | O83: 8 | P83: 5 | Q83: 3 | S83: 0 | U83: Ab | V83: 4 | W83: 10 | X83: 8 | Y83: 5 | Z83: 3 | AB83: 0 | AC83: Plate Kneecops | AD83: Ab | AE83: 10 | AF83: 21 | AG83: 17 | AH83: 10 | AI83: 4
A84: 0 | C84: Pv | D84: 4 | E84: 5 | F84: 2 | G84: 5 | H84: 1 | J84: 0 | L84: Pv | M84: 2 | N84: 3 | O84: 1 | P84: 3 | Q84: 0 | S84: 0 | U84: Pv | V84: 4 | W84: 11 | X84: 8 | Y84: 6 | Z84: 3 | AB84: 0 | AC84: Plate Greaves | AD84: Pv | AE84: 4 | AF84: 11 | AG84: 8 | AH84: 6 | AI84: 3
A85: 0 | C85: Th | D85: 4 | E85: 5 | F85: 2 | G85: 5 | H85: 1 | J85: 0 | L85: Th | M85: 0 | N85: 1 | O85: 0 | P85: 1 | Q85: 0 | S85: 0 | U85: Th | V85: 4 | W85: 5 | X85: 2 | Y85: 5 | Z85: 0 | AB85: 0 | AC85: Mail Leggings | AD85: Th | AE85: 8 | AF85: 21 | AG85: 16 | AH85: 11 | AI85: 3
A86: 0 | C86: Kn | D86: 0 | E86: 2 | F86: 0 | G86: 2 | H86: 2 | J86: 0 | L86: Kn | M86: 0 | N86: 1 | O86: 0 | P86: 1 | Q86: 0 | S86: 0 | U86: Kn | V86: 6 | W86: 9 | X86: 6 | Y86: 7 | Z86: 2 | AB86: 0 | AC86: Padded Leggings | AD86: Kn | AE86: 10 | AF86: 22 | AG86: 17 | AH86: 11 | AI86: 4
A87: 0 | C87: Cf | D87: 0 | E87: 1 | F87: 0 | G87: 1 | H87: 0 | J87: 0 | L87: Cf | M87: 1 | N87: 4 | O87: 1 | P87: 5 | Q87: 0 | S87: 0 | U87: Cf | V87: 3 | W87: 4 | X87: 2 | Y87: 5 | Z87: 0 | AB87: 0 | AD87: Cf | AE87: 10 | AF87: 21 | AG87: 17 | AH87: 10 | AI87: 4
A88: 0 | C88: Ft | D88: 1 | E88: 3 | F88: 1 | G88: 4 | H88: 0 | J88: 0 | L88: Ft | M88: 1 | N88: 3 | O88: 1 | P88: 4 | Q88: 0 | S88: 0 | U88: Ft | V88: 3 | W88: 4 | X88: 2 | Y88: 5 | Z88: 0 | AB88: 0 | AD88: Ft | AE88: 4 | AF88: 10 | AG88: 8 | AH88: 5 | AI88: 3
A89: 0 | J89: 0 | S89: 0 | AB89: 0
A90: 0 | D90: Bulk Penalty: | J90: 0 | M90: Bulk Penalty: | S90: 0 | V90: Bulk Penalty: | AB90: 0 | AE90: Bulk Penalty:
A91: 0 | D91: Head | E91: 0 | J91: 0 | M91: Head | N91: 0 | S91: 0 | V91: Head | W91: 0 | AB91: 0 | AE91: Head | AF91: 0
A92: 0 | D92: Arms | E92: 0 | J92: 0 | M92: Arms | N92: 0 | S92: 0 | V92: Arms | W92: 0 | AB92: 0 | AE92: Arms | AF92: 0
A93: 0 | D93: Torso | E93: 0 | J93: 0 | M93: Torso | N93: 0 | S93: 0 | V93: Torso | W93: 0 | AB93: 0 | AE93: Torso | AF93: 0
A94: 0 | D94: Legs | E94: 0 | J94: 0 | M94: Legs | N94: 0 | S94: 0 | V94: Legs | W94: 0 | AB94: 0 | AE94: Legs | AF94: 0
A95: 0 | J95: 0 | S95: 0 | AB95: 0
A96: 0 | J96: 0 | S96: 0 | AB96: 0
A97: 0 | J97: 0 | S97: 0 | AB97: 0

Sheet Suit Builder
A1: HârnMaster Kèthîra Armour Calculator | Y1: =SUM(Y5:Y32) -> 486 | Z1: =SUM(Z5:Z32) -> 24.63 | AA1: =SUM(AA5:AA32)+IF(EA30>2,5,0) -> 5 | AB1: =SUM(AB5:AB32) -> 0 | AC1: =SUM(AC5:AC32) -> 6 | AD1: =SUM(AD5:AD32) -> 0 | AE1: =SUM(AE5:AE32) -> 0 | AF1: =SUM(AF5:AF32) -> 4 | AG1: =SUM(AG5:AG32) -> 4 | AH1: =SUM(AH5:AH32) -> 4 | AI1: =SUM(AI5:AI32) -> 4 | ... CJ1: =SUM(CJ5:CJ32) -> 4 | CK1: 0.04 | CL1: 0.03 | CM1: 0.02 | CN1: 0.03 | CO1: 0.06 | CP1: 0.02 | CQ1: 0.05 | CR1: 0.05 | CS1: 0.12 | CT1: 0.12 | CU1: 0.1 | CV1: 0.14 | CW1: 0.03 | CX1: 0.12 | CY1: 0.07
J2: 2 | K2: 3 | L2: 4 | M2: 5 | N2: 6 | O2: 7 | P2: 8 | Q2: 9 | R2: 10 | S2: 11 | T2: 12 | U2: 13 | V2: 14 | W2: 15 | X2: 16 | AC2: B | AR2: E | BG2: P | BV2: F | CK2: Layers | CZ2: Types | DO2: Layers by Type | EF2: Rigidity | EU2: 149
B3: Suit Name: | C3: Test Suit | J3: Head | M3: Arms | R3: Torso | U3: Legs | AC3: Head | AF3: Arms | AK3: Torso | AN3: Legs | AR3: Head | AU3: Arms | AZ3: Torso | BC3: Legs | BG3: Head | BJ3: Arms | BO3: Torso | BR3: Legs | BV3: Head | BY3: Arms | CD3: Torso | CG3: Legs | CK3: Head | CN3: Arms | CS3: Torso | CV3: Legs | CZ3: Head | DC3: Arms | DH3: Torso | DK3: Legs | DO3: Head | DR3: Arms | DW3: Torso | DZ3: Legs | EF3: Head | EI3: Arms | EN3: Torso | EQ3: Legs | EX3: Green areas may be edited to create new armour suits.
B4: Item List | C4: Suit is NOT LEGAL!! | J4: Sk | K4: Fa | L4: Nk | M4: Sh | N4: Ua | O4: El | P4: Fo | Q4: Ha | R4: Tx | S4: Ab | T4: Pv | U4: Th | V4: Kn | W4: Cf | X4: Ft | Y4: Price | Z4: Weight | AA4: ENC | AB4: PER | AC4: Sk | AD4: Fa | AE4: Nk | AF4: Sh | AG4: Ua | AH4: El | AI4: Fo | AJ4: Ha | AK4: Tx | AL4: Ab | AM4: Pv | AN4: Th | AO4: Kn | AP4: Cf | AQ4: Ft | AR4: Sk | AS4: Fa | AT4: Nk | AU4: Sh | AV4: Ua | AW4: El | AX4: Fo | AY4: Ha | AZ4: Tx | BA4: Ab | BB4: Pv | BC4: Th | BD4: Kn | BE4: Cf | BF4: Ft | BG4: Sk | BH4: Fa | BI4: Nk | BJ4: Sh | BK4: Ua | BL4: El | BM4: Fo | BN4: Ha | BO4: Tx | BP4: Ab | BQ4: Pv | BR4: Th | BS4: Kn | BT4: Cf | BU4: Ft | BV4: Sk | BW4: Fa | BX4: Nk | BY4: Sh | BZ4: Ua | CA4: El | CB4: Fo | CC4: Ha | CD4: Tx | CE4: Ab | CF4: Pv | CG4: Th | CH4: Kn | CI4: Cf | CJ4: Ft | CK4: Sk | CL4: Fa | CM4: Nk | CN4: Sh | CO4: Ua | CP4: El | CQ4: Fo | CR4: Ha | CS4: Tx | CT4: Ab | CU4: Pv | CV4: Th | CW4: Kn | CX4: Cf | CY4: Ft | CZ4: Sk | DA4: Fa | DB4: Nk | DC4: Sh | DD4: Ua | DE4: El | DF4: Fo | DG4: Ha | DH4: Tx | DI4: Ab | DJ4: Pv | DK4: Th | DL4: Kn | DM4: Cf | DN4: Ft | DO4: Sk | DP4: Fa | DQ4: Nk | DR4: Sh | DS4: Ua | DT4: El | DU4: Fo | DV4: Ha | DW4: Tx | DX4: Ab | DY4: Pv | DZ4: Th | EA4: Kn | EB4: Cf | EC4: Ft | EF4: Sk | EG4: Fa | EH4: Nk | EI4: Sh | EJ4: Ua | EK4: El | EL4: Fo | EM4: Ha | EN4: Tx | EO4: Ab | EP4: Pv | EQ4: Th | ER4: Kn | ES4: Cf | ET4: Ft | EU4: MWS | EV4: AQ | EW4: AV | EX4: The item list is limited to items in the Item Builder sheet,; a drop-down is provided for convenience.
A5: =EV5 -> 0 | B5: Kûrbúl Helm | C5: Price | D5: ENC | E5: PER | F5: Area | G5: LB | J5: =IF($B5="",0,VLOOKUP($B5,ITEMS,J$2,FALSE())) -> K | K5: =IF($B5="",0,VLOOKUP($B5,ITEMS,K$2,FALSE())) -> 0 | L5: =IF($B5="",0,VLOOKUP($B5,ITEMS,L$2,FALSE())) -> 0 | M5: =IF($B5="",0,VLOOKUP($B5,ITEMS,M$2,FALSE())) -> 0 | N5: =IF($B5="",0,VLOOKUP($B5,ITEMS,N$2,FALSE())) -> 0 | O5: =IF($B5="",0,VLOOKUP($B5,ITEMS,O$2,FALSE())) -> 0 | P5: =IF($B5="",0,VLOOKUP($B5,ITEMS,P$2,FALSE())) -> 0 | Q5: =IF($B5="",0,VLOOKUP($B5,ITEMS,Q$2,FALSE())) -> 0 | ... X5: =IF($B5="",0,VLOOKUP($B5,ITEMS,X$2,FALSE())) -> 0 | Y5: =IF($B5="",0,VLOOKUP($B5,ITEMS,17,FALSE())) -> 20 | Z5: =IF($B5="",0,VLOOKUP($B5,ITEMS,18,FALSE())) -> 3.04 | AA5: =IF($B5="",0,VLOOKUP($B5,ITEMS,19,FALSE())) -> 0 | AB5: =IF($B5="",0,VLOOKUP($B5,ITEMS,20,FALSE())) -> 0 | AC5: =VLOOKUP(J5,MATERIAL,5,FALSE())+IF(J5=0,0,$EW5) -> 4 | AD5: =VLOOKUP(K5,MATERIAL,5,FALSE())+IF(K5=0,0,$EW5) -> 0 | AE5: =VLOOKUP(L5,MATERIAL,5,FALSE())+IF(L5=0,0,$EW5) -> 0 | AF5: =VLOOKUP(M5,MATERIAL,5,FALSE())+IF(M5=0,0,$EW5) -> 0 | AG5: =VLOOKUP(N5,MATERIAL,5,FALSE())+IF(N5=0,0,$EW5) -> 0 | AH5: =VLOOKUP(O5,MATERIAL,5,FALSE())+IF(O5=0,0,$EW5) -> 0 | AI5: =VLOOKUP(P5,MATERIAL,5,FALSE())+IF(P5=0,0,$EW5) -> 0 | AJ5: =VLOOKUP(Q5,MATERIAL,5,FALSE())+IF(Q5=0,0,$EW5) -> 0 | ... AQ5: =VLOOKUP(X5,MATERIAL,5,FALSE())+IF(X5=0,0,$EW5) -> 0 | AR5: =VLOOKUP(J5,MATERIAL,6,FALSE())+IF(J5=0,0,$EW5) -> 6 | AS5: =VLOOKUP(K5,MATERIAL,6,FALSE())+IF(K5=0,0,$EW5) -> 0 | AT5: =VLOOKUP(L5,MATERIAL,6,FALSE())+IF(L5=0,0,$EW5) -> 0 | AU5: =VLOOKUP(M5,MATERIAL,6,FALSE())+IF(M5=0,0,$EW5) -> 0 | AV5: =VLOOKUP(N5,MATERIAL,6,FALSE())+IF(N5=0,0,$EW5) -> 0 | AW5: =VLOOKUP(O5,MATERIAL,6,FALSE())+IF(O5=0,0,$EW5) -> 0 | AX5: =VLOOKUP(P5,MATERIAL,6,FALSE())+IF(P5=0,0,$EW5) -> 0 | AY5: =VLOOKUP(Q5,MATERIAL,6,FALSE())+IF(Q5=0,0,$EW5) -> 0 | ... BF5: =VLOOKUP(X5,MATERIAL,6,FALSE())+IF(X5=0,0,$EW5) -> 0 | BG5: =VLOOKUP(J5,MATERIAL,7,FALSE())+IF(J5=0,0,$EW5) -> 5 | BH5: =VLOOKUP(K5,MATERIAL,7,FALSE())+IF(K5=0,0,$EW5) -> 0 | BI5: =VLOOKUP(L5,MATERIAL,7,FALSE())+IF(L5=0,0,$EW5) -> 0 | BJ5: =VLOOKUP(M5,MATERIAL,7,FALSE())+IF(M5=0,0,$EW5) -> 0 | BK5: =VLOOKUP(N5,MATERIAL,7,FALSE())+IF(N5=0,0,$EW5) -> 0 | BL5: =VLOOKUP(O5,MATERIAL,7,FALSE())+IF(O5=0,0,$EW5) -> 0 | BM5: =VLOOKUP(P5,MATERIAL,7,FALSE())+IF(P5=0,0,$EW5) -> 0 | BN5: =VLOOKUP(Q5,MATERIAL,7,FALSE())+IF(Q5=0,0,$EW5) -> 0 | ... BU5: =VLOOKUP(X5,MATERIAL,7,FALSE())+IF(X5=0,0,$EW5) -> 0 | BV5: =VLOOKUP(J5,MATERIAL,8,FALSE())+IF(J5=0,0,$EW5) -> 4 | BW5: =VLOOKUP(K5,MATERIAL,8,FALSE())+IF(K5=0,0,$EW5) -> 0 | BX5: =VLOOKUP(L5,MATERIAL,8,FALSE())+IF(L5=0,0,$EW5) -> 0 | BY5: =VLOOKUP(M5,MATERIAL,8,FALSE())+IF(M5=0,0,$EW5) -> 0 | BZ5: =VLOOKUP(N5,MATERIAL,8,FALSE())+IF(N5=0,0,$EW5) -> 0 | CA5: =VLOOKUP(O5,MATERIAL,8,FALSE())+IF(O5=0,0,$EW5) -> 0 | CB5: =VLOOKUP(P5,MATERIAL,8,FALSE())+IF(P5=0,0,$EW5) -> 0 | CC5: =VLOOKUP(Q5,MATERIAL,8,FALSE())+IF(Q5=0,0,$EW5) -> 0 | ... CJ5: =VLOOKUP(X5,MATERIAL,8,FALSE())+IF(X5=0,0,$EW5) -> 0 | CK5: =VLOOKUP(J5,MATERIAL,4,FALSE()) -> 1 | CL5: =VLOOKUP(K5,MATERIAL,4,FALSE()) -> 0 | CM5: =VLOOKUP(L5,MATERIAL,4,FALSE()) -> 0 | CN5: =VLOOKUP(M5,MATERIAL,4,FALSE()) -> 0 | CO5: =VLOOKUP(N5,MATERIAL,4,FALSE()) -> 0 | CP5: =VLOOKUP(O5,MATERIAL,4,FALSE()) -> 0 | CQ5: =VLOOKUP(P5,MATERIAL,4,FALSE()) -> 0 | CR5: =VLOOKUP(Q5,MATERIAL,4,FALSE()) -> 0 | ... CY5: =VLOOKUP(X5,MATERIAL,4,FALSE()) -> 0 | CZ5: =IF(J5=0,0,LEFT(J5,1)) -> K | DA5: =IF(K5=0,0,LEFT(K5,1)) -> 0 | DB5: =IF(L5=0,0,LEFT(L5,1)) -> 0 | DC5: =IF(M5=0,0,LEFT(M5,1)) -> 0 | DD5: =IF(N5=0,0,LEFT(N5,1)) -> 0 | DE5: =IF(O5=0,0,LEFT(O5,1)) -> 0 | DF5: =IF(P5=0,0,LEFT(P5,1)) -> 0 | DG5: =IF(Q5=0,0,LEFT(Q5,1)) -> 0 | ... DN5: =IF(X5=0,0,LEFT(X5,1)) -> 0 | DO5: =SUMIF(CZ$5:CZ$32,$ED5,CK$5:CK$32) -> 1.5 | DP5: =SUMIF(DA$5:DA$32,$ED5,CL$5:CL$32) -> 0 | DQ5: =SUMIF(DB$5:DB$32,$ED5,CM$5:CM$32) -> 0 | DR5: =SUMIF(DC$5:DC$32,$ED5,CN$5:CN$32) -> 0 | DS5: =SUMIF(DD$5:DD$32,$ED5,CO$5:CO$32) -> 0 | DT5: =SUMIF(DE$5:DE$32,$ED5,CP$5:CP$32) -> 0 | DU5: =SUMIF(DF$5:DF$32,$ED5,CQ$5:CQ$32) -> 0 | DV5: =SUMIF(DG$5:DG$32,$ED5,CR$5:CR$32) -> 0 | ... EC5: =SUMIF(DN$5:DN$32,$ED5,CY$5:CY$32) -> 0 | ED5: D | EF5: =VLOOKUP(J5,MATERIAL,9,FALSE()) -> 2 | EG5: =VLOOKUP(K5,MATERIAL,9,FALSE()) -> 0 | EH5: =VLOOKUP(L5,MATERIAL,9,FALSE()) -> 0 | EI5: =VLOOKUP(M5,MATERIAL,9,FALSE()) -> 0 | EJ5: =VLOOKUP(N5,MATERIAL,9,FALSE()) -> 0 | EK5: =VLOOKUP(O5,MATERIAL,9,FALSE()) -> 0 | EL5: =VLOOKUP(P5,MATERIAL,9,FALSE()) -> 0 | EM5: =VLOOKUP(Q5,MATERIAL,9,FALSE()) -> 0 | ... ET5: =VLOOKUP(X5,MATERIAL,9,FALSE()) -> 0 | EU5: =IF($B5="",0,VLOOKUP($B5,ITEMS,EU$2,FALSE())) -> 0 | EV5: =VLOOKUP(EU5,MWS,2) -> 0 | EW5: =VLOOKUP(EU5,MWS,3) -> 0 | EX5: The suit name may be entered freely.
A6: =EV6 -> 0 | B6: Padded Cap | C6: =Y1 -> 486 | D6: =AA1 -> 5 | E6: =AB1 -> 0 | F6: =ROUND(SUMPRODUCT(BV1:CJ1,CK1:CY1)+0.2,0) -> 4 | G6: =Z1 -> 24.63 | J6: =IF($B6="",0,VLOOKUP($B6,ITEMS,J$2,FALSE())) -> D | K6: =IF($B6="",0,VLOOKUP($B6,ITEMS,K$2,FALSE())) -> 0 | L6: =IF($B6="",0,VLOOKUP($B6,ITEMS,L$2,FALSE())) -> 0 | M6: =IF($B6="",0,VLOOKUP($B6,ITEMS,M$2,FALSE())) -> 0 | N6: =IF($B6="",0,VLOOKUP($B6,ITEMS,N$2,FALSE())) -> 0 | O6: =IF($B6="",0,VLOOKUP($B6,ITEMS,O$2,FALSE())) -> 0 | P6: =IF($B6="",0,VLOOKUP($B6,ITEMS,P$2,FALSE())) -> 0 | Q6: =IF($B6="",0,VLOOKUP($B6,ITEMS,Q$2,FALSE())) -> 0 | ... X6: =IF($B6="",0,VLOOKUP($B6,ITEMS,X$2,FALSE())) -> 0 | Y6: =IF($B6="",0,VLOOKUP($B6,ITEMS,17,FALSE())) -> 8 | Z6: =IF($B6="",0,VLOOKUP($B6,ITEMS,18,FALSE())) -> 0.32 | AA6: =IF($B6="",0,VLOOKUP($B6,ITEMS,19,FALSE())) -> 0 | AB6: =IF($B6="",0,VLOOKUP($B6,ITEMS,20,FALSE())) -> 0 | AC6: =VLOOKUP(J6,MATERIAL,5,FALSE())+IF(J6=0,0,$EW6) -> 2 | AD6: =VLOOKUP(K6,MATERIAL,5,FALSE())+IF(K6=0,0,$EW6) -> 0 | AE6: =VLOOKUP(L6,MATERIAL,5,FALSE())+IF(L6=0,0,$EW6) -> 0 | AF6: =VLOOKUP(M6,MATERIAL,5,FALSE())+IF(M6=0,0,$EW6) -> 0 | AG6: =VLOOKUP(N6,MATERIAL,5,FALSE())+IF(N6=0,0,$EW6) -> 0 | AH6: =VLOOKUP(O6,MATERIAL,5,FALSE())+IF(O6=0,0,$EW6) -> 0 | AI6: =VLOOKUP(P6,MATERIAL,5,FALSE())+IF(P6=0,0,$EW6) -> 0 | AJ6: =VLOOKUP(Q6,MATERIAL,5,FALSE())+IF(Q6=0,0,$EW6) -> 0 | ... AQ6: =VLOOKUP(X6,MATERIAL,5,FALSE())+IF(X6=0,0,$EW6) -> 0 | AR6: =VLOOKUP(J6,MATERIAL,6,FALSE())+IF(J6=0,0,$EW6) -> 2 | AS6: =VLOOKUP(K6,MATERIAL,6,FALSE())+IF(K6=0,0,$EW6) -> 0 | AT6: =VLOOKUP(L6,MATERIAL,6,FALSE())+IF(L6=0,0,$EW6) -> 0 | AU6: =VLOOKUP(M6,MATERIAL,6,FALSE())+IF(M6=0,0,$EW6) -> 0 | AV6: =VLOOKUP(N6,MATERIAL,6,FALSE())+IF(N6=0,0,$EW6) -> 0 | AW6: =VLOOKUP(O6,MATERIAL,6,FALSE())+IF(O6=0,0,$EW6) -> 0 | AX6: =VLOOKUP(P6,MATERIAL,6,FALSE())+IF(P6=0,0,$EW6) -> 0 | AY6: =VLOOKUP(Q6,MATERIAL,6,FALSE())+IF(Q6=0,0,$EW6) -> 0 | ... BF6: =VLOOKUP(X6,MATERIAL,6,FALSE())+IF(X6=0,0,$EW6) -> 0 | BG6: =VLOOKUP(J6,MATERIAL,7,FALSE())+IF(J6=0,0,$EW6) -> 1 | BH6: =VLOOKUP(K6,MATERIAL,7,FALSE())+IF(K6=0,0,$EW6) -> 0 | BI6: =VLOOKUP(L6,MATERIAL,7,FALSE())+IF(L6=0,0,$EW6) -> 0 | BJ6: =VLOOKUP(M6,MATERIAL,7,FALSE())+IF(M6=0,0,$EW6) -> 0 | BK6: =VLOOKUP(N6,MATERIAL,7,FALSE())+IF(N6=0,0,$EW6) -> 0 | BL6: =VLOOKUP(O6,MATERIAL,7,FALSE())+IF(O6=0,0,$EW6) -> 0 | BM6: =VLOOKUP(P6,MATERIAL,7,FALSE())+IF(P6=0,0,$EW6) -> 0 | BN6: =VLOOKUP(Q6,MATERIAL,7,FALSE())+IF(Q6=0,0,$EW6) -> 0 | ... BU6: =VLOOKUP(X6,MATERIAL,7,FALSE())+IF(X6=0,0,$EW6) -> 0 | BV6: =VLOOKUP(J6,MATERIAL,8,FALSE())+IF(J6=0,0,$EW6) -> 2 | BW6: =VLOOKUP(K6,MATERIAL,8,FALSE())+IF(K6=0,0,$EW6) -> 0 | BX6: =VLOOKUP(L6,MATERIAL,8,FALSE())+IF(L6=0,0,$EW6) -> 0 | BY6: =VLOOKUP(M6,MATERIAL,8,FALSE())+IF(M6=0,0,$EW6) -> 0 | BZ6: =VLOOKUP(N6,MATERIAL,8,FALSE())+IF(N6=0,0,$EW6) -> 0 | CA6: =VLOOKUP(O6,MATERIAL,8,FALSE())+IF(O6=0,0,$EW6) -> 0 | CB6: =VLOOKUP(P6,MATERIAL,8,FALSE())+IF(P6=0,0,$EW6) -> 0 | CC6: =VLOOKUP(Q6,MATERIAL,8,FALSE())+IF(Q6=0,0,$EW6) -> 0 | ... CJ6: =VLOOKUP(X6,MATERIAL,8,FALSE())+IF(X6=0,0,$EW6) -> 0 | CK6: =VLOOKUP(J6,MATERIAL,4,FALSE()) -> 1.5 | CL6: =VLOOKUP(K6,MATERIAL,4,FALSE()) -> 0 | CM6: =VLOOKUP(L6,MATERIAL,4,FALSE()) -> 0 | CN6: =VLOOKUP(M6,MATERIAL,4,FALSE()) -> 0 | CO6: =VLOOKUP(N6,MATERIAL,4,FALSE()) -> 0 | CP6: =VLOOKUP(O6,MATERIAL,4,FALSE()) -> 0 | CQ6: =VLOOKUP(P6,MATERIAL,4,FALSE()) -> 0 | CR6: =VLOOKUP(Q6,MATERIAL,4,FALSE()) -> 0 | ... CY6: =VLOOKUP(X6,MATERIAL,4,FALSE()) -> 0 | CZ6: =IF(J6=0,0,LEFT(J6,1)) -> D | DA6: =IF(K6=0,0,LEFT(K6,1)) -> 0 | DB6: =IF(L6=0,0,LEFT(L6,1)) -> 0 | DC6: =IF(M6=0,0,LEFT(M6,1)) -> 0 | DD6: =IF(N6=0,0,LEFT(N6,1)) -> 0 | DE6: =IF(O6=0,0,LEFT(O6,1)) -> 0 | DF6: =IF(P6=0,0,LEFT(P6,1)) -> 0 | DG6: =IF(Q6=0,0,LEFT(Q6,1)) -> 0 | ... DN6: =IF(X6=0,0,LEFT(X6,1)) -> 0 | DO6: =SUMIF(CZ$5:CZ$32,$ED6,CK$5:CK$32) -> 0 | DP6: =SUMIF(DA$5:DA$32,$ED6,CL$5:CL$32) -> 0 | DQ6: =SUMIF(DB$5:DB$32,$ED6,CM$5:CM$32) -> 0 | DR6: =SUMIF(DC$5:DC$32,$ED6,CN$5:CN$32) -> 2 | DS6: =SUMIF(DD$5:DD$32,$ED6,CO$5:CO$32) -> 2 | DT6: =SUMIF(DE$5:DE$32,$ED6,CP$5:CP$32) -> 2 | DU6: =SUMIF(DF$5:DF$32,$ED6,CQ$5:CQ$32) -> 2 | DV6: =SUMIF(DG$5:DG$32,$ED6,CR$5:CR$32) -> 0 | ... EC6: =SUMIF(DN$5:DN$32,$ED6,CY$5:CY$32) -> 0 | ED6: Q | EF6: =VLOOKUP(J6,MATERIAL,9,FALSE()) -> 0 | EG6: =VLOOKUP(K6,MATERIAL,9,FALSE()) -> 0 | EH6: =VLOOKUP(L6,MATERIAL,9,FALSE()) -> 0 | EI6: =VLOOKUP(M6,MATERIAL,9,FALSE()) -> 0 | EJ6: =VLOOKUP(N6,MATERIAL,9,FALSE()) -> 0 | EK6: =VLOOKUP(O6,MATERIAL,9,FALSE()) -> 0 | EL6: =VLOOKUP(P6,MATERIAL,9,FALSE()) -> 0 | EM6: =VLOOKUP(Q6,MATERIAL,9,FALSE()) -> 0 | ... ET6: =VLOOKUP(X6,MATERIAL,9,FALSE()) -> 0 | EU6: =IF($B6="",0,VLOOKUP($B6,ITEMS,EU$2,FALSE())) -> 0 | EV6: =VLOOKUP(EU6,MWS,2) -> 0 | EW6: =VLOOKUP(EU6,MWS,3) -> 0
A7: =EV7 -> 0 | B7: Quilted Coat | J7: =IF($B7="",0,VLOOKUP($B7,ITEMS,J$2,FALSE())) -> 0 | K7: =IF($B7="",0,VLOOKUP($B7,ITEMS,K$2,FALSE())) -> 0 | L7: =IF($B7="",0,VLOOKUP($B7,ITEMS,L$2,FALSE())) -> 0 | M7: =IF($B7="",0,VLOOKUP($B7,ITEMS,M$2,FALSE())) -> Q | N7: =IF($B7="",0,VLOOKUP($B7,ITEMS,N$2,FALSE())) -> Q | O7: =IF($B7="",0,VLOOKUP($B7,ITEMS,O$2,FALSE())) -> Q | P7: =IF($B7="",0,VLOOKUP($B7,ITEMS,P$2,FALSE())) -> Q | Q7: =IF($B7="",0,VLOOKUP($B7,ITEMS,Q$2,FALSE())) -> 0 | ... X7: =IF($B7="",0,VLOOKUP($B7,ITEMS,X$2,FALSE())) -> 0 | Y7: =IF($B7="",0,VLOOKUP($B7,ITEMS,17,FALSE())) -> 256 | Z7: =IF($B7="",0,VLOOKUP($B7,ITEMS,18,FALSE())) -> 11.52 | AA7: =IF($B7="",0,VLOOKUP($B7,ITEMS,19,FALSE())) -> 5 | AB7: =IF($B7="",0,VLOOKUP($B7,ITEMS,20,FALSE())) -> 0 | AC7: =VLOOKUP(J7,MATERIAL,5,FALSE())+IF(J7=0,0,$EW7) -> 0 | AD7: =VLOOKUP(K7,MATERIAL,5,FALSE())+IF(K7=0,0,$EW7) -> 0 | AE7: =VLOOKUP(L7,MATERIAL,5,FALSE())+IF(L7=0,0,$EW7) -> 0 | AF7: =VLOOKUP(M7,MATERIAL,5,FALSE())+IF(M7=0,0,$EW7) -> 4 | AG7: =VLOOKUP(N7,MATERIAL,5,FALSE())+IF(N7=0,0,$EW7) -> 4 | AH7: =VLOOKUP(O7,MATERIAL,5,FALSE())+IF(O7=0,0,$EW7) -> 4 | AI7: =VLOOKUP(P7,MATERIAL,5,FALSE())+IF(P7=0,0,$EW7) -> 4 | AJ7: =VLOOKUP(Q7,MATERIAL,5,FALSE())+IF(Q7=0,0,$EW7) -> 0 | ... AQ7: =VLOOKUP(X7,MATERIAL,5,FALSE())+IF(X7=0,0,$EW7) -> 0 | AR7: =VLOOKUP(J7,MATERIAL,6,FALSE())+IF(J7=0,0,$EW7) -> 0 | AS7: =VLOOKUP(K7,MATERIAL,6,FALSE())+IF(K7=0,0,$EW7) -> 0 | AT7: =VLOOKUP(L7,MATERIAL,6,FALSE())+IF(L7=0,0,$EW7) -> 0 | AU7: =VLOOKUP(M7,MATERIAL,6,FALSE())+IF(M7=0,0,$EW7) -> 3 | AV7: =VLOOKUP(N7,MATERIAL,6,FALSE())+IF(N7=0,0,$EW7) -> 3 | AW7: =VLOOKUP(O7,MATERIAL,6,FALSE())+IF(O7=0,0,$EW7) -> 3 | AX7: =VLOOKUP(P7,MATERIAL,6,FALSE())+IF(P7=0,0,$EW7) -> 3 | AY7: =VLOOKUP(Q7,MATERIAL,6,FALSE())+IF(Q7=0,0,$EW7) -> 0 | ... BF7: =VLOOKUP(X7,MATERIAL,6,FALSE())+IF(X7=0,0,$EW7) -> 0 | BG7: =VLOOKUP(J7,MATERIAL,7,FALSE())+IF(J7=0,0,$EW7) -> 0 | BH7: =VLOOKUP(K7,MATERIAL,7,FALSE())+IF(K7=0,0,$EW7) -> 0 | BI7: =VLOOKUP(L7,MATERIAL,7,FALSE())+IF(L7=0,0,$EW7) -> 0 | BJ7: =VLOOKUP(M7,MATERIAL,7,FALSE())+IF(M7=0,0,$EW7) -> 2 | BK7: =VLOOKUP(N7,MATERIAL,7,FALSE())+IF(N7=0,0,$EW7) -> 2 | BL7: =VLOOKUP(O7,MATERIAL,7,FALSE())+IF(O7=0,0,$EW7) -> 2 | BM7: =VLOOKUP(P7,MATERIAL,7,FALSE())+IF(P7=0,0,$EW7) -> 2 | BN7: =VLOOKUP(Q7,MATERIAL,7,FALSE())+IF(Q7=0,0,$EW7) -> 0 | ... BU7: =VLOOKUP(X7,MATERIAL,7,FALSE())+IF(X7=0,0,$EW7) -> 0 | BV7: =VLOOKUP(J7,MATERIAL,8,FALSE())+IF(J7=0,0,$EW7) -> 0 | BW7: =VLOOKUP(K7,MATERIAL,8,FALSE())+IF(K7=0,0,$EW7) -> 0 | BX7: =VLOOKUP(L7,MATERIAL,8,FALSE())+IF(L7=0,0,$EW7) -> 0 | BY7: =VLOOKUP(M7,MATERIAL,8,FALSE())+IF(M7=0,0,$EW7) -> 3 | BZ7: =VLOOKUP(N7,MATERIAL,8,FALSE())+IF(N7=0,0,$EW7) -> 3 | CA7: =VLOOKUP(O7,MATERIAL,8,FALSE())+IF(O7=0,0,$EW7) -> 3 | CB7: =VLOOKUP(P7,MATERIAL,8,FALSE())+IF(P7=0,0,$EW7) -> 3 | CC7: =VLOOKUP(Q7,MATERIAL,8,FALSE())+IF(Q7=0,0,$EW7) -> 0 | ... CJ7: =VLOOKUP(X7,MATERIAL,8,FALSE())+IF(X7=0,0,$EW7) -> 0 | CK7: =VLOOKUP(J7,MATERIAL,4,FALSE()) -> 0 | CL7: =VLOOKUP(K7,MATERIAL,4,FALSE()) -> 0 | CM7: =VLOOKUP(L7,MATERIAL,4,FALSE()) -> 0 | CN7: =VLOOKUP(M7,MATERIAL,4,FALSE()) -> 2 | CO7: =VLOOKUP(N7,MATERIAL,4,FALSE()) -> 2 | CP7: =VLOOKUP(O7,MATERIAL,4,FALSE()) -> 2 | CQ7: =VLOOKUP(P7,MATERIAL,4,FALSE()) -> 2 | CR7: =VLOOKUP(Q7,MATERIAL,4,FALSE()) -> 0 | ... CY7: =VLOOKUP(X7,MATERIAL,4,FALSE()) -> 0 | CZ7: =IF(J7=0,0,LEFT(J7,1)) -> 0 | DA7: =IF(K7=0,0,LEFT(K7,1)) -> 0 | DB7: =IF(L7=0,0,LEFT(L7,1)) -> 0 | DC7: =IF(M7=0,0,LEFT(M7,1)) -> Q | DD7: =IF(N7=0,0,LEFT(N7,1)) -> Q | DE7: =IF(O7=0,0,LEFT(O7,1)) -> Q | DF7: =IF(P7=0,0,LEFT(P7,1)) -> Q | DG7: =IF(Q7=0,0,LEFT(Q7,1)) -> 0 | ... DN7: =IF(X7=0,0,LEFT(X7,1)) -> 0 | DO7: =SUMIF(CZ$5:CZ$32,$ED7,CK$5:CK$32) -> 0 | DP7: =SUMIF(DA$5:DA$32,$ED7,CL$5:CL$32) -> 0 | DQ7: =SUMIF(DB$5:DB$32,$ED7,CM$5:CM$32) -> 0 | DR7: =SUMIF(DC$5:DC$32,$ED7,CN$5:CN$32) -> 0 | DS7: =SUMIF(DD$5:DD$32,$ED7,CO$5:CO$32) -> 0 | DT7: =SUMIF(DE$5:DE$32,$ED7,CP$5:CP$32) -> 0 | DU7: =SUMIF(DF$5:DF$32,$ED7,CQ$5:CQ$32) -> 0 | DV7: =SUMIF(DG$5:DG$32,$ED7,CR$5:CR$32) -> 0 | ... EC7: =SUMIF(DN$5:DN$32,$ED7,CY$5:CY$32) -> 0 | ED7: G | EF7: =VLOOKUP(J7,MATERIAL,9,FALSE()) -> 0 | EG7: =VLOOKUP(K7,MATERIAL,9,FALSE()) -> 0 | EH7: =VLOOKUP(L7,MATERIAL,9,FALSE()) -> 0 | EI7: =VLOOKUP(M7,MATERIAL,9,FALSE()) -> 0 | EJ7: =VLOOKUP(N7,MATERIAL,9,FALSE()) -> 0 | EK7: =VLOOKUP(O7,MATERIAL,9,FALSE()) -> 0 | EL7: =VLOOKUP(P7,MATERIAL,9,FALSE()) -> 0 | EM7: =VLOOKUP(Q7,MATERIAL,9,FALSE()) -> 0 | ... ET7: =VLOOKUP(X7,MATERIAL,9,FALSE()) -> 0 | EU7: =IF($B7="",0,VLOOKUP($B7,ITEMS,EU$2,FALSE())) -> 0 | EV7: =VLOOKUP(EU7,MWS,2) -> 0 | EW7: =VLOOKUP(EU7,MWS,3) -> 0
A8: =EV8 -> 0 | B8: Buckram Tunic | C8: Loc | D8: B | E8: E | F8: P | G8: F | J8: =IF($B8="",0,VLOOKUP($B8,ITEMS,J$2,FALSE())) -> 0 | K8: =IF($B8="",0,VLOOKUP($B8,ITEMS,K$2,FALSE())) -> 0 | L8: =IF($B8="",0,VLOOKUP($B8,ITEMS,L$2,FALSE())) -> 0 | M8: =IF($B8="",0,VLOOKUP($B8,ITEMS,M$2,FALSE())) -> C | N8: =IF($B8="",0,VLOOKUP($B8,ITEMS,N$2,FALSE())) -> C | O8: =IF($B8="",0,VLOOKUP($B8,ITEMS,O$2,FALSE())) -> C | P8: =IF($B8="",0,VLOOKUP($B8,ITEMS,P$2,FALSE())) -> 0 | Q8: =IF($B8="",0,VLOOKUP($B8,ITEMS,Q$2,FALSE())) -> 0 | ... X8: =IF($B8="",0,VLOOKUP($B8,ITEMS,X$2,FALSE())) -> 0 | Y8: =IF($B8="",0,VLOOKUP($B8,ITEMS,17,FALSE())) -> 45 | Z8: =IF($B8="",0,VLOOKUP($B8,ITEMS,18,FALSE())) -> 2.25 | AA8: =IF($B8="",0,VLOOKUP($B8,ITEMS,19,FALSE())) -> 0 | AB8: =IF($B8="",0,VLOOKUP($B8,ITEMS,20,FALSE())) -> 0 | AC8: =VLOOKUP(J8,MATERIAL,5,FALSE())+IF(J8=0,0,$EW8) -> 0 | AD8: =VLOOKUP(K8,MATERIAL,5,FALSE())+IF(K8=0,0,$EW8) -> 0 | AE8: =VLOOKUP(L8,MATERIAL,5,FALSE())+IF(L8=0,0,$EW8) -> 0 | AF8: =VLOOKUP(M8,MATERIAL,5,FALSE())+IF(M8=0,0,$EW8) -> 0 | AG8: =VLOOKUP(N8,MATERIAL,5,FALSE())+IF(N8=0,0,$EW8) -> 0 | AH8: =VLOOKUP(O8,MATERIAL,5,FALSE())+IF(O8=0,0,$EW8) -> 0 | AI8: =VLOOKUP(P8,MATERIAL,5,FALSE())+IF(P8=0,0,$EW8) -> 0 | AJ8: =VLOOKUP(Q8,MATERIAL,5,FALSE())+IF(Q8=0,0,$EW8) -> 0 | ... AQ8: =VLOOKUP(X8,MATERIAL,5,FALSE())+IF(X8=0,0,$EW8) -> 0 | AR8: =VLOOKUP(J8,MATERIAL,6,FALSE())+IF(J8=0,0,$EW8) -> 0 | AS8: =VLOOKUP(K8,MATERIAL,6,FALSE())+IF(K8=0,0,$EW8) -> 0 | AT8: =VLOOKUP(L8,MATERIAL,6,FALSE())+IF(L8=0,0,$EW8) -> 0 | AU8: =VLOOKUP(M8,MATERIAL,6,FALSE())+IF(M8=0,0,$EW8) -> 1 | AV8: =VLOOKUP(N8,MATERIAL,6,FALSE())+IF(N8=0,0,$EW8) -> 1 | AW8: =VLOOKUP(O8,MATERIAL,6,FALSE())+IF(O8=0,0,$EW8) -> 1 | AX8: =VLOOKUP(P8,MATERIAL,6,FALSE())+IF(P8=0,0,$EW8) -> 0 | AY8: =VLOOKUP(Q8,MATERIAL,6,FALSE())+IF(Q8=0,0,$EW8) -> 0 | ... BF8: =VLOOKUP(X8,MATERIAL,6,FALSE())+IF(X8=0,0,$EW8) -> 0 | BG8: =VLOOKUP(J8,MATERIAL,7,FALSE())+IF(J8=0,0,$EW8) -> 0 | BH8: =VLOOKUP(K8,MATERIAL,7,FALSE())+IF(K8=0,0,$EW8) -> 0 | BI8: =VLOOKUP(L8,MATERIAL,7,FALSE())+IF(L8=0,0,$EW8) -> 0 | BJ8: =VLOOKUP(M8,MATERIAL,7,FALSE())+IF(M8=0,0,$EW8) -> 0 | BK8: =VLOOKUP(N8,MATERIAL,7,FALSE())+IF(N8=0,0,$EW8) -> 0 | BL8: =VLOOKUP(O8,MATERIAL,7,FALSE())+IF(O8=0,0,$EW8) -> 0 | BM8: =VLOOKUP(P8,MATERIAL,7,FALSE())+IF(P8=0,0,$EW8) -> 0 | BN8: =VLOOKUP(Q8,MATERIAL,7,FALSE())+IF(Q8=0,0,$EW8) -> 0 | ... BU8: =VLOOKUP(X8,MATERIAL,7,FALSE())+IF(X8=0,0,$EW8) -> 0 | BV8: =VLOOKUP(J8,MATERIAL,8,FALSE())+IF(J8=0,0,$EW8) -> 0 | BW8: =VLOOKUP(K8,MATERIAL,8,FALSE())+IF(K8=0,0,$EW8) -> 0 | BX8: =VLOOKUP(L8,MATERIAL,8,FALSE())+IF(L8=0,0,$EW8) -> 0 | BY8: =VLOOKUP(M8,MATERIAL,8,FALSE())+IF(M8=0,0,$EW8) -> 1 | BZ8: =VLOOKUP(N8,MATERIAL,8,FALSE())+IF(N8=0,0,$EW8) -> 1 | CA8: =VLOOKUP(O8,MATERIAL,8,FALSE())+IF(O8=0,0,$EW8) -> 1 | CB8: =VLOOKUP(P8,MATERIAL,8,FALSE())+IF(P8=0,0,$EW8) -> 0 | CC8: =VLOOKUP(Q8,MATERIAL,8,FALSE())+IF(Q8=0,0,$EW8) -> 0 | ... CJ8: =VLOOKUP(X8,MATERIAL,8,FALSE())+IF(X8=0,0,$EW8) -> 0 | CK8: =VLOOKUP(J8,MATERIAL,4,FALSE()) -> 0 | CL8: =VLOOKUP(K8,MATERIAL,4,FALSE()) -> 0 | CM8: =VLOOKUP(L8,MATERIAL,4,FALSE()) -> 0 | CN8: =VLOOKUP(M8,MATERIAL,4,FALSE()) -> 1 | CO8: =VLOOKUP(N8,MATERIAL,4,FALSE()) -> 1 | CP8: =VLOOKUP(O8,MATERIAL,4,FALSE()) -> 1 | CQ8: =VLOOKUP(P8,MATERIAL,4,FALSE()) -> 0 | CR8: =VLOOKUP(Q8,MATERIAL,4,FALSE()) -> 0 | ... CY8: =VLOOKUP(X8,MATERIAL,4,FALSE()) -> 0 | CZ8: =IF(J8=0,0,LEFT(J8,1)) -> 0 | DA8: =IF(K8=0,0,LEFT(K8,1)) -> 0 | DB8: =IF(L8=0,0,LEFT(L8,1)) -> 0 | DC8: =IF(M8=0,0,LEFT(M8,1)) -> C | DD8: =IF(N8=0,0,LEFT(N8,1)) -> C | DE8: =IF(O8=0,0,LEFT(O8,1)) -> C | DF8: =IF(P8=0,0,LEFT(P8,1)) -> 0 | DG8: =IF(Q8=0,0,LEFT(Q8,1)) -> 0 | ... DN8: =IF(X8=0,0,LEFT(X8,1)) -> 0 | DO8: =SUMIF(CZ$5:CZ$32,$ED8,CK$5:CK$32) -> 0 | DP8: =SUMIF(DA$5:DA$32,$ED8,CL$5:CL$32) -> 0 | DQ8: =SUMIF(DB$5:DB$32,$ED8,CM$5:CM$32) -> 0 | DR8: =SUMIF(DC$5:DC$32,$ED8,CN$5:CN$32) -> 0 | DS8: =SUMIF(DD$5:DD$32,$ED8,CO$5:CO$32) -> 0 | DT8: =SUMIF(DE$5:DE$32,$ED8,CP$5:CP$32) -> 0 | DU8: =SUMIF(DF$5:DF$32,$ED8,CQ$5:CQ$32) -> 0 | DV8: =SUMIF(DG$5:DG$32,$ED8,CR$5:CR$32) -> 0 | ... EC8: =SUMIF(DN$5:DN$32,$ED8,CY$5:CY$32) -> 1 | ED8: L | EF8: =VLOOKUP(J8,MATERIAL,9,FALSE()) -> 0 | EG8: =VLOOKUP(K8,MATERIAL,9,FALSE()) -> 0 | EH8: =VLOOKUP(L8,MATERIAL,9,FALSE()) -> 0 | EI8: =VLOOKUP(M8,MATERIAL,9,FALSE()) -> 0 | EJ8: =VLOOKUP(N8,MATERIAL,9,FALSE()) -> 0 | EK8: =VLOOKUP(O8,MATERIAL,9,FALSE()) -> 0 | EL8: =VLOOKUP(P8,MATERIAL,9,FALSE()) -> 0 | EM8: =VLOOKUP(Q8,MATERIAL,9,FALSE()) -> 0 | ... ET8: =VLOOKUP(X8,MATERIAL,9,FALSE()) -> 0 | EU8: =IF($B8="",0,VLOOKUP($B8,ITEMS,EU$2,FALSE())) -> 0 | EV8: =VLOOKUP(EU8,MWS,2) -> 0 | EW8: =VLOOKUP(EU8,MWS,3) -> 0
A9: =EV9 -> 0 | B9: Buckram Breeches | C9: Sk | D9: =AC1 -> 6 | E9: =AR1 -> 8 | F9: =BG1 -> 6 | G9: =BV1 -> 6 | H9: =MAX(EF5:EF32) -> 2 | J9: =IF($B9="",0,VLOOKUP($B9,ITEMS,J$2,FALSE())) -> 0 | K9: =IF($B9="",0,VLOOKUP($B9,ITEMS,K$2,FALSE())) -> 0 | L9: =IF($B9="",0,VLOOKUP($B9,ITEMS,L$2,FALSE())) -> 0 | M9: =IF($B9="",0,VLOOKUP($B9,ITEMS,M$2,FALSE())) -> 0 | N9: =IF($B9="",0,VLOOKUP($B9,ITEMS,N$2,FALSE())) -> 0 | O9: =IF($B9="",0,VLOOKUP($B9,ITEMS,O$2,FALSE())) -> 0 | P9: =IF($B9="",0,VLOOKUP($B9,ITEMS,P$2,FALSE())) -> 0 | Q9: =IF($B9="",0,VLOOKUP($B9,ITEMS,Q$2,FALSE())) -> 0 | ... X9: =IF($B9="",0,VLOOKUP($B9,ITEMS,X$2,FALSE())) -> 0 | Y9: =IF($B9="",0,VLOOKUP($B9,ITEMS,17,FALSE())) -> 27 | Z9: =IF($B9="",0,VLOOKUP($B9,ITEMS,18,FALSE())) -> 1.35 | AA9: =IF($B9="",0,VLOOKUP($B9,ITEMS,19,FALSE())) -> 0 | AB9: =IF($B9="",0,VLOOKUP($B9,ITEMS,20,FALSE())) -> 0 | AC9: =VLOOKUP(J9,MATERIAL,5,FALSE())+IF(J9=0,0,$EW9) -> 0 | AD9: =VLOOKUP(K9,MATERIAL,5,FALSE())+IF(K9=0,0,$EW9) -> 0 | AE9: =VLOOKUP(L9,MATERIAL,5,FALSE())+IF(L9=0,0,$EW9) -> 0 | AF9: =VLOOKUP(M9,MATERIAL,5,FALSE())+IF(M9=0,0,$EW9) -> 0 | AG9: =VLOOKUP(N9,MATERIAL,5,FALSE())+IF(N9=0,0,$EW9) -> 0 | AH9: =VLOOKUP(O9,MATERIAL,5,FALSE())+IF(O9=0,0,$EW9) -> 0 | AI9: =VLOOKUP(P9,MATERIAL,5,FALSE())+IF(P9=0,0,$EW9) -> 0 | AJ9: =VLOOKUP(Q9,MATERIAL,5,FALSE())+IF(Q9=0,0,$EW9) -> 0 | ... AQ9: =VLOOKUP(X9,MATERIAL,5,FALSE())+IF(X9=0,0,$EW9) -> 0 | AR9: =VLOOKUP(J9,MATERIAL,6,FALSE())+IF(J9=0,0,$EW9) -> 0 | AS9: =VLOOKUP(K9,MATERIAL,6,FALSE())+IF(K9=0,0,$EW9) -> 0 | AT9: =VLOOKUP(L9,MATERIAL,6,FALSE())+IF(L9=0,0,$EW9) -> 0 | AU9: =VLOOKUP(M9,MATERIAL,6,FALSE())+IF(M9=0,0,$EW9) -> 0 | AV9: =VLOOKUP(N9,MATERIAL,6,FALSE())+IF(N9=0,0,$EW9) -> 0 | AW9: =VLOOKUP(O9,MATERIAL,6,FALSE())+IF(O9=0,0,$EW9) -> 0 | AX9: =VLOOKUP(P9,MATERIAL,6,FALSE())+IF(P9=0,0,$EW9) -> 0 | AY9: =VLOOKUP(Q9,MATERIAL,6,FALSE())+IF(Q9=0,0,$EW9) -> 0 | ... BF9: =VLOOKUP(X9,MATERIAL,6,FALSE())+IF(X9=0,0,$EW9) -> 0 | BG9: =VLOOKUP(J9,MATERIAL,7,FALSE())+IF(J9=0,0,$EW9) -> 0 | BH9: =VLOOKUP(K9,MATERIAL,7,FALSE())+IF(K9=0,0,$EW9) -> 0 | BI9: =VLOOKUP(L9,MATERIAL,7,FALSE())+IF(L9=0,0,$EW9) -> 0 | BJ9: =VLOOKUP(M9,MATERIAL,7,FALSE())+IF(M9=0,0,$EW9) -> 0 | BK9: =VLOOKUP(N9,MATERIAL,7,FALSE())+IF(N9=0,0,$EW9) -> 0 | BL9: =VLOOKUP(O9,MATERIAL,7,FALSE())+IF(O9=0,0,$EW9) -> 0 | BM9: =VLOOKUP(P9,MATERIAL,7,FALSE())+IF(P9=0,0,$EW9) -> 0 | BN9: =VLOOKUP(Q9,MATERIAL,7,FALSE())+IF(Q9=0,0,$EW9) -> 0 | ... BU9: =VLOOKUP(X9,MATERIAL,7,FALSE())+IF(X9=0,0,$EW9) -> 0 | BV9: =VLOOKUP(J9,MATERIAL,8,FALSE())+IF(J9=0,0,$EW9) -> 0 | BW9: =VLOOKUP(K9,MATERIAL,8,FALSE())+IF(K9=0,0,$EW9) -> 0 | BX9: =VLOOKUP(L9,MATERIAL,8,FALSE())+IF(L9=0,0,$EW9) -> 0 | BY9: =VLOOKUP(M9,MATERIAL,8,FALSE())+IF(M9=0,0,$EW9) -> 0 | BZ9: =VLOOKUP(N9,MATERIAL,8,FALSE())+IF(N9=0,0,$EW9) -> 0 | CA9: =VLOOKUP(O9,MATERIAL,8,FALSE())+IF(O9=0,0,$EW9) -> 0 | CB9: =VLOOKUP(P9,MATERIAL,8,FALSE())+IF(P9=0,0,$EW9) -> 0 | CC9: =VLOOKUP(Q9,MATERIAL,8,FALSE())+IF(Q9=0,0,$EW9) -> 0 | ... CJ9: =VLOOKUP(X9,MATERIAL,8,FALSE())+IF(X9=0,0,$EW9) -> 0 | CK9: =VLOOKUP(J9,MATERIAL,4,FALSE()) -> 0 | CL9: =VLOOKUP(K9,MATERIAL,4,FALSE()) -> 0 | CM9: =VLOOKUP(L9,MATERIAL,4,FALSE()) -> 0 | CN9: =VLOOKUP(M9,MATERIAL,4,FALSE()) -> 0 | CO9: =VLOOKUP(N9,MATERIAL,4,FALSE()) -> 0 | CP9: =VLOOKUP(O9,MATERIAL,4,FALSE()) -> 0 | CQ9: =VLOOKUP(P9,MATERIAL,4,FALSE()) -> 0 | CR9: =VLOOKUP(Q9,MATERIAL,4,FALSE()) -> 0 | ... CY9: =VLOOKUP(X9,MATERIAL,4,FALSE()) -> 0 | CZ9: =IF(J9=0,0,LEFT(J9,1)) -> 0 | DA9: =IF(K9=0,0,LEFT(K9,1)) -> 0 | DB9: =IF(L9=0,0,LEFT(L9,1)) -> 0 | DC9: =IF(M9=0,0,LEFT(M9,1)) -> 0 | DD9: =IF(N9=0,0,LEFT(N9,1)) -> 0 | DE9: =IF(O9=0,0,LEFT(O9,1)) -> 0 | DF9: =IF(P9=0,0,LEFT(P9,1)) -> 0 | DG9: =IF(Q9=0,0,LEFT(Q9,1)) -> 0 | ... DN9: =IF(X9=0,0,LEFT(X9,1)) -> 0 | DO9: =SUMIF(CZ$5:CZ$32,$ED9,CK$5:CK$32) -> 1 | DP9: =SUMIF(DA$5:DA$32,$ED9,CL$5:CL$32) -> 0 | DQ9: =SUMIF(DB$5:DB$32,$ED9,CM$5:CM$32) -> 0 | DR9: =SUMIF(DC$5:DC$32,$ED9,CN$5:CN$32) -> 0 | DS9: =SUMIF(DD$5:DD$32,$ED9,CO$5:CO$32) -> 0 | DT9: =SUMIF(DE$5:DE$32,$ED9,CP$5:CP$32) -> 0 | DU9: =SUMIF(DF$5:DF$32,$ED9,CQ$5:CQ$32) -> 0 | DV9: =SUMIF(DG$5:DG$32,$ED9,CR$5:CR$32) -> 0 | ... EC9: =SUMIF(DN$5:DN$32,$ED9,CY$5:CY$32) -> 0 | ED9: K | EF9: =VLOOKUP(J9,MATERIAL,9,FALSE()) -> 0 | EG9: =VLOOKUP(K9,MATERIAL,9,FALSE()) -> 0 | EH9: =VLOOKUP(L9,MATERIAL,9,FALSE()) -> 0 | EI9: =VLOOKUP(M9,MATERIAL,9,FALSE()) -> 0 | EJ9: =VLOOKUP(N9,MATERIAL,9,FALSE()) -> 0 | EK9: =VLOOKUP(O9,MATERIAL,9,FALSE()) -> 0 | EL9: =VLOOKUP(P9,MATERIAL,9,FALSE()) -> 0 | EM9: =VLOOKUP(Q9,MATERIAL,9,FALSE()) -> 0 | ... ET9: =VLOOKUP(X9,MATERIAL,9,FALSE()) -> 0 | EU9: =IF($B9="",0,VLOOKUP($B9,ITEMS,EU$2,FALSE())) -> 0 | EV9: =VLOOKUP(EU9,MWS,2) -> 0 | EW9: =VLOOKUP(EU9,MWS,3) -> 0
A10: =EV10 -> 0 | B10: Buckram Leggings | C10: Fa | D10: =AD1 -> 0 | E10: =AS1 -> 0 | F10: =BH1 -> 0 | G10: =BW1 -> 0 | H10: =MAX(EG5:EG32) -> 0 | J10: =IF($B10="",0,VLOOKUP($B10,ITEMS,J$2,FALSE())) -> 0 | K10: =IF($B10="",0,VLOOKUP($B10,ITEMS,K$2,FALSE())) -> 0 | L10: =IF($B10="",0,VLOOKUP($B10,ITEMS,L$2,FALSE())) -> 0 | M10: =IF($B10="",0,VLOOKUP($B10,ITEMS,M$2,FALSE())) -> 0 | N10: =IF($B10="",0,VLOOKUP($B10,ITEMS,N$2,FALSE())) -> 0 | O10: =IF($B10="",0,VLOOKUP($B10,ITEMS,O$2,FALSE())) -> 0 | P10: =IF($B10="",0,VLOOKUP($B10,ITEMS,P$2,FALSE())) -> 0 | Q10: =IF($B10="",0,VLOOKUP($B10,ITEMS,Q$2,FALSE())) -> 0 | ... X10: =IF($B10="",0,VLOOKUP($B10,ITEMS,X$2,FALSE())) -> C | Y10: =IF($B10="",0,VLOOKUP($B10,ITEMS,17,FALSE())) -> 36 | Z10: =IF($B10="",0,VLOOKUP($B10,ITEMS,18,FALSE())) -> 1.8 | AA10: =IF($B10="",0,VLOOKUP($B10,ITEMS,19,FALSE())) -> 0 | AB10: =IF($B10="",0,VLOOKUP($B10,ITEMS,20,FALSE())) -> 0 | AC10: =VLOOKUP(J10,MATERIAL,5,FALSE())+IF(J10=0,0,$EW10) -> 0 | AD10: =VLOOKUP(K10,MATERIAL,5,FALSE())+IF(K10=0,0,$EW10) -> 0 | AE10: =VLOOKUP(L10,MATERIAL,5,FALSE())+IF(L10=0,0,$EW10) -> 0 | AF10: =VLOOKUP(M10,MATERIAL,5,FALSE())+IF(M10=0,0,$EW10) -> 0 | AG10: =VLOOKUP(N10,MATERIAL,5,FALSE())+IF(N10=0,0,$EW10) -> 0 | AH10: =VLOOKUP(O10,MATERIAL,5,FALSE())+IF(O10=0,0,$EW10) -> 0 | AI10: =VLOOKUP(P10,MATERIAL,5,FALSE())+IF(P10=0,0,$EW10) -> 0 | AJ10: =VLOOKUP(Q10,MATERIAL,5,FALSE())+IF(Q10=0,0,$EW10) -> 0 | ... AQ10: =VLOOKUP(X10,MATERIAL,5,FALSE())+IF(X10=0,0,$EW10) -> 0 | AR10: =VLOOKUP(J10,MATERIAL,6,FALSE())+IF(J10=0,0,$EW10) -> 0 | AS10: =VLOOKUP(K10,MATERIAL,6,FALSE())+IF(K10=0,0,$EW10) -> 0 | AT10: =VLOOKUP(L10,MATERIAL,6,FALSE())+IF(L10=0,0,$EW10) -> 0 | AU10: =VLOOKUP(M10,MATERIAL,6,FALSE())+IF(M10=0,0,$EW10) -> 0 | AV10: =VLOOKUP(N10,MATERIAL,6,FALSE())+IF(N10=0,0,$EW10) -> 0 | AW10: =VLOOKUP(O10,MATERIAL,6,FALSE())+IF(O10=0,0,$EW10) -> 0 | AX10: =VLOOKUP(P10,MATERIAL,6,FALSE())+IF(P10=0,0,$EW10) -> 0 | AY10: =VLOOKUP(Q10,MATERIAL,6,FALSE())+IF(Q10=0,0,$EW10) -> 0 | ... BF10: =VLOOKUP(X10,MATERIAL,6,FALSE())+IF(X10=0,0,$EW10) -> 1 | BG10: =VLOOKUP(J10,MATERIAL,7,FALSE())+IF(J10=0,0,$EW10) -> 0 | BH10: =VLOOKUP(K10,MATERIAL,7,FALSE())+IF(K10=0,0,$EW10) -> 0 | BI10: =VLOOKUP(L10,MATERIAL,7,FALSE())+IF(L10=0,0,$EW10) -> 0 | BJ10: =VLOOKUP(M10,MATERIAL,7,FALSE())+IF(M10=0,0,$EW10) -> 0 | BK10: =VLOOKUP(N10,MATERIAL,7,FALSE())+IF(N10=0,0,$EW10) -> 0 | BL10: =VLOOKUP(O10,MATERIAL,7,FALSE())+IF(O10=0,0,$EW10) -> 0 | BM10: =VLOOKUP(P10,MATERIAL,7,FALSE())+IF(P10=0,0,$EW10) -> 0 | BN10: =VLOOKUP(Q10,MATERIAL,7,FALSE())+IF(Q10=0,0,$EW10) -> 0 | ... BU10: =VLOOKUP(X10,MATERIAL,7,FALSE())+IF(X10=0,0,$EW10) -> 0 | BV10: =VLOOKUP(J10,MATERIAL,8,FALSE())+IF(J10=0,0,$EW10) -> 0 | BW10: =VLOOKUP(K10,MATERIAL,8,FALSE())+IF(K10=0,0,$EW10) -> 0 | BX10: =VLOOKUP(L10,MATERIAL,8,FALSE())+IF(L10=0,0,$EW10) -> 0 | BY10: =VLOOKUP(M10,MATERIAL,8,FALSE())+IF(M10=0,0,$EW10) -> 0 | BZ10: =VLOOKUP(N10,MATERIAL,8,FALSE())+IF(N10=0,0,$EW10) -> 0 | CA10: =VLOOKUP(O10,MATERIAL,8,FALSE())+IF(O10=0,0,$EW10) -> 0 | CB10: =VLOOKUP(P10,MATERIAL,8,FALSE())+IF(P10=0,0,$EW10) -> 0 | CC10: =VLOOKUP(Q10,MATERIAL,8,FALSE())+IF(Q10=0,0,$EW10) -> 0 | ... CJ10: =VLOOKUP(X10,MATERIAL,8,FALSE())+IF(X10=0,0,$EW10) -> 1 | CK10: =VLOOKUP(J10,MATERIAL,4,FALSE()) -> 0 | CL10: =VLOOKUP(K10,MATERIAL,4,FALSE()) -> 0 | CM10: =VLOOKUP(L10,MATERIAL,4,FALSE()) -> 0 | CN10: =VLOOKUP(M10,MATERIAL,4,FALSE()) -> 0 | CO10: =VLOOKUP(N10,MATERIAL,4,FALSE()) -> 0 | CP10: =VLOOKUP(O10,MATERIAL,4,FALSE()) -> 0 | CQ10: =VLOOKUP(P10,MATERIAL,4,FALSE()) -> 0 | CR10: =VLOOKUP(Q10,MATERIAL,4,FALSE()) -> 0 | ... CY10: =VLOOKUP(X10,MATERIAL,4,FALSE()) -> 1 | CZ10: =IF(J10=0,0,LEFT(J10,1)) -> 0 | DA10: =IF(K10=0,0,LEFT(K10,1)) -> 0 | DB10: =IF(L10=0,0,LEFT(L10,1)) -> 0 | DC10: =IF(M10=0,0,LEFT(M10,1)) -> 0 | DD10: =IF(N10=0,0,LEFT(N10,1)) -> 0 | DE10: =IF(O10=0,0,LEFT(O10,1)) -> 0 | DF10: =IF(P10=0,0,LEFT(P10,1)) -> 0 | DG10: =IF(Q10=0,0,LEFT(Q10,1)) -> 0 | ... DN10: =IF(X10=0,0,LEFT(X10,1)) -> C | DO10: =SUMIF(CZ$5:CZ$32,$ED10,CK$5:CK$32) -> 0 | DP10: =SUMIF(DA$5:DA$32,$ED10,CL$5:CL$32) -> 0 | DQ10: =SUMIF(DB$5:DB$32,$ED10,CM$5:CM$32) -> 0 | DR10: =SUMIF(DC$5:DC$32,$ED10,CN$5:CN$32) -> 0 | DS10: =SUMIF(DD$5:DD$32,$ED10,CO$5:CO$32) -> 0 | DT10: =SUMIF(DE$5:DE$32,$ED10,CP$5:CP$32) -> 0 | DU10: =SUMIF(DF$5:DF$32,$ED10,CQ$5:CQ$32) -> 0 | DV10: =SUMIF(DG$5:DG$32,$ED10,CR$5:CR$32) -> 0 | ... EC10: =SUMIF(DN$5:DN$32,$ED10,CY$5:CY$32) -> 0 | ED10: S | EF10: =VLOOKUP(J10,MATERIAL,9,FALSE()) -> 0 | EG10: =VLOOKUP(K10,MATERIAL,9,FALSE()) -> 0 | EH10: =VLOOKUP(L10,MATERIAL,9,FALSE()) -> 0 | EI10: =VLOOKUP(M10,MATERIAL,9,FALSE()) -> 0 | EJ10: =VLOOKUP(N10,MATERIAL,9,FALSE()) -> 0 | EK10: =VLOOKUP(O10,MATERIAL,9,FALSE()) -> 0 | EL10: =VLOOKUP(P10,MATERIAL,9,FALSE()) -> 0 | EM10: =VLOOKUP(Q10,MATERIAL,9,FALSE()) -> 0 | ... ET10: =VLOOKUP(X10,MATERIAL,9,FALSE()) -> 0 | EU10: =IF($B10="",0,VLOOKUP($B10,ITEMS,EU$2,FALSE())) -> 0 | EV10: =VLOOKUP(EU10,MWS,2) -> 0 | EW10: =VLOOKUP(EU10,MWS,3) -> 0
A11: =EV11 -> 0 | B11: Leather Shoes | C11: Nk | D11: =AE1 -> 0 | E11: =AT1 -> 0 | F11: =BI1 -> 0 | G11: =BX1 -> 0 | H11: =MAX(EH5:EH32) -> 0 | J11: =IF($B11="",0,VLOOKUP($B11,ITEMS,J$2,FALSE())) -> 0 | K11: =IF($B11="",0,VLOOKUP($B11,ITEMS,K$2,FALSE())) -> 0 | L11: =IF($B11="",0,VLOOKUP($B11,ITEMS,L$2,FALSE())) -> 0 | M11: =IF($B11="",0,VLOOKUP($B11,ITEMS,M$2,FALSE())) -> 0 | N11: =IF($B11="",0,VLOOKUP($B11,ITEMS,N$2,FALSE())) -> 0 | O11: =IF($B11="",0,VLOOKUP($B11,ITEMS,O$2,FALSE())) -> 0 | P11: =IF($B11="",0,VLOOKUP($B11,ITEMS,P$2,FALSE())) -> 0 | Q11: =IF($B11="",0,VLOOKUP($B11,ITEMS,Q$2,FALSE())) -> 0 | ... X11: =IF($B11="",0,VLOOKUP($B11,ITEMS,X$2,FALSE())) -> L | Y11: =IF($B11="",0,VLOOKUP($B11,ITEMS,17,FALSE())) -> 28 | Z11: =IF($B11="",0,VLOOKUP($B11,ITEMS,18,FALSE())) -> 1.05 | AA11: =IF($B11="",0,VLOOKUP($B11,ITEMS,19,FALSE())) -> 0 | AB11: =IF($B11="",0,VLOOKUP($B11,ITEMS,20,FALSE())) -> 0 | AC11: =VLOOKUP(J11,MATERIAL,5,FALSE())+IF(J11=0,0,$EW11) -> 0 | AD11: =VLOOKUP(K11,MATERIAL,5,FALSE())+IF(K11=0,0,$EW11) -> 0 | AE11: =VLOOKUP(L11,MATERIAL,5,FALSE())+IF(L11=0,0,$EW11) -> 0 | AF11: =VLOOKUP(M11,MATERIAL,5,FALSE())+IF(M11=0,0,$EW11) -> 0 | AG11: =VLOOKUP(N11,MATERIAL,5,FALSE())+IF(N11=0,0,$EW11) -> 0 | AH11: =VLOOKUP(O11,MATERIAL,5,FALSE())+IF(O11=0,0,$EW11) -> 0 | AI11: =VLOOKUP(P11,MATERIAL,5,FALSE())+IF(P11=0,0,$EW11) -> 0 | AJ11: =VLOOKUP(Q11,MATERIAL,5,FALSE())+IF(Q11=0,0,$EW11) -> 0 | ... AQ11: =VLOOKUP(X11,MATERIAL,5,FALSE())+IF(X11=0,0,$EW11) -> 1 | AR11: =VLOOKUP(J11,MATERIAL,6,FALSE())+IF(J11=0,0,$EW11) -> 0 | AS11: =VLOOKUP(K11,MATERIAL,6,FALSE())+IF(K11=0,0,$EW11) -> 0 | AT11: =VLOOKUP(L11,MATERIAL,6,FALSE())+IF(L11=0,0,$EW11) -> 0 | AU11: =VLOOKUP(M11,MATERIAL,6,FALSE())+IF(M11=0,0,$EW11) -> 0 | AV11: =VLOOKUP(N11,MATERIAL,6,FALSE())+IF(N11=0,0,$EW11) -> 0 | AW11: =VLOOKUP(O11,MATERIAL,6,FALSE())+IF(O11=0,0,$EW11) -> 0 | AX11: =VLOOKUP(P11,MATERIAL,6,FALSE())+IF(P11=0,0,$EW11) -> 0 | AY11: =VLOOKUP(Q11,MATERIAL,6,FALSE())+IF(Q11=0,0,$EW11) -> 0 | ... BF11: =VLOOKUP(X11,MATERIAL,6,FALSE())+IF(X11=0,0,$EW11) -> 2 | BG11: =VLOOKUP(J11,MATERIAL,7,FALSE())+IF(J11=0,0,$EW11) -> 0 | BH11: =VLOOKUP(K11,MATERIAL,7,FALSE())+IF(K11=0,0,$EW11) -> 0 | BI11: =VLOOKUP(L11,MATERIAL,7,FALSE())+IF(L11=0,0,$EW11) -> 0 | BJ11: =VLOOKUP(M11,MATERIAL,7,FALSE())+IF(M11=0,0,$EW11) -> 0 | BK11: =VLOOKUP(N11,MATERIAL,7,FALSE())+IF(N11=0,0,$EW11) -> 0 | BL11: =VLOOKUP(O11,MATERIAL,7,FALSE())+IF(O11=0,0,$EW11) -> 0 | BM11: =VLOOKUP(P11,MATERIAL,7,FALSE())+IF(P11=0,0,$EW11) -> 0 | BN11: =VLOOKUP(Q11,MATERIAL,7,FALSE())+IF(Q11=0,0,$EW11) -> 0 | ... BU11: =VLOOKUP(X11,MATERIAL,7,FALSE())+IF(X11=0,0,$EW11) -> 1 | BV11: =VLOOKUP(J11,MATERIAL,8,FALSE())+IF(J11=0,0,$EW11) -> 0 | BW11: =VLOOKUP(K11,MATERIAL,8,FALSE())+IF(K11=0,0,$EW11) -> 0 | BX11: =VLOOKUP(L11,MATERIAL,8,FALSE())+IF(L11=0,0,$EW11) -> 0 | BY11: =VLOOKUP(M11,MATERIAL,8,FALSE())+IF(M11=0,0,$EW11) -> 0 | BZ11: =VLOOKUP(N11,MATERIAL,8,FALSE())+IF(N11=0,0,$EW11) -> 0 | CA11: =VLOOKUP(O11,MATERIAL,8,FALSE())+IF(O11=0,0,$EW11) -> 0 | CB11: =VLOOKUP(P11,MATERIAL,8,FALSE())+IF(P11=0,0,$EW11) -> 0 | CC11: =VLOOKUP(Q11,MATERIAL,8,FALSE())+IF(Q11=0,0,$EW11) -> 0 | ... CJ11: =VLOOKUP(X11,MATERIAL,8,FALSE())+IF(X11=0,0,$EW11) -> 3 | CK11: =VLOOKUP(J11,MATERIAL,4,FALSE()) -> 0 | CL11: =VLOOKUP(K11,MATERIAL,4,FALSE()) -> 0 | CM11: =VLOOKUP(L11,MATERIAL,4,FALSE()) -> 0 | CN11: =VLOOKUP(M11,MATERIAL,4,FALSE()) -> 0 | CO11: =VLOOKUP(N11,MATERIAL,4,FALSE()) -> 0 | CP11: =VLOOKUP(O11,MATERIAL,4,FALSE()) -> 0 | CQ11: =VLOOKUP(P11,MATERIAL,4,FALSE()) -> 0 | CR11: =VLOOKUP(Q11,MATERIAL,4,FALSE()) -> 0 | ... CY11: =VLOOKUP(X11,MATERIAL,4,FALSE()) -> 1 | CZ11: =IF(J11=0,0,LEFT(J11,1)) -> 0 | DA11: =IF(K11=0,0,LEFT(K11,1)) -> 0 | DB11: =IF(L11=0,0,LEFT(L11,1)) -> 0 | DC11: =IF(M11=0,0,LEFT(M11,1)) -> 0 | DD11: =IF(N11=0,0,LEFT(N11,1)) -> 0 | DE11: =IF(O11=0,0,LEFT(O11,1)) -> 0 | DF11: =IF(P11=0,0,LEFT(P11,1)) -> 0 | DG11: =IF(Q11=0,0,LEFT(Q11,1)) -> 0 | ... DN11: =IF(X11=0,0,LEFT(X11,1)) -> L | DO11: =SUMIF(CZ$5:CZ$32,$ED11,CK$5:CK$32) -> 0 | DP11: =SUMIF(DA$5:DA$32,$ED11,CL$5:CL$32) -> 0 | DQ11: =SUMIF(DB$5:DB$32,$ED11,CM$5:CM$32) -> 0 | DR11: =SUMIF(DC$5:DC$32,$ED11,CN$5:CN$32) -> 0 | DS11: =SUMIF(DD$5:DD$32,$ED11,CO$5:CO$32) -> 0 | DT11: =SUMIF(DE$5:DE$32,$ED11,CP$5:CP$32) -> 0 | DU11: =SUMIF(DF$5:DF$32,$ED11,CQ$5:CQ$32) -> 0 | DV11: =SUMIF(DG$5:DG$32,$ED11,CR$5:CR$32) -> 0 | ... EC11: =SUMIF(DN$5:DN$32,$ED11,CY$5:CY$32) -> 0 | ED11: M | EF11: =VLOOKUP(J11,MATERIAL,9,FALSE()) -> 0 | EG11: =VLOOKUP(K11,MATERIAL,9,FALSE()) -> 0 | EH11: =VLOOKUP(L11,MATERIAL,9,FALSE()) -> 0 | EI11: =VLOOKUP(M11,MATERIAL,9,FALSE()) -> 0 | EJ11: =VLOOKUP(N11,MATERIAL,9,FALSE()) -> 0 | EK11: =VLOOKUP(O11,MATERIAL,9,FALSE()) -> 0 | EL11: =VLOOKUP(P11,MATERIAL,9,FALSE()) -> 0 | EM11: =VLOOKUP(Q11,MATERIAL,9,FALSE()) -> 0 | ... ET11: =VLOOKUP(X11,MATERIAL,9,FALSE()) -> 0 | EU11: =IF($B11="",0,VLOOKUP($B11,ITEMS,EU$2,FALSE())) -> 0 | EV11: =VLOOKUP(EU11,MWS,2) -> 0 | EW11: =VLOOKUP(EU11,MWS,3) -> 0
A12: =EV12 -> 0 | B12: Buckram Cloak | C12: Sh | D12: =AF1 -> 4 | E12: =AU1 -> 4 | F12: =BJ1 -> 2 | G12: =BY1 -> 5 | H12: =MAX(EI5:EI32) -> 0 | J12: =IF($B12="",0,VLOOKUP($B12,ITEMS,J$2,FALSE())) -> 0 | K12: =IF($B12="",0,VLOOKUP($B12,ITEMS,K$2,FALSE())) -> 0 | L12: =IF($B12="",0,VLOOKUP($B12,ITEMS,L$2,FALSE())) -> 0 | M12: =IF($B12="",0,VLOOKUP($B12,ITEMS,M$2,FALSE())) -> Cb | N12: =IF($B12="",0,VLOOKUP($B12,ITEMS,N$2,FALSE())) -> 0 | O12: =IF($B12="",0,VLOOKUP($B12,ITEMS,O$2,FALSE())) -> 0 | P12: =IF($B12="",0,VLOOKUP($B12,ITEMS,P$2,FALSE())) -> 0 | Q12: =IF($B12="",0,VLOOKUP($B12,ITEMS,Q$2,FALSE())) -> 0 | ... X12: =IF($B12="",0,VLOOKUP($B12,ITEMS,X$2,FALSE())) -> 0 | Y12: =IF($B12="",0,VLOOKUP($B12,ITEMS,17,FALSE())) -> 66 | Z12: =IF($B12="",0,VLOOKUP($B12,ITEMS,18,FALSE())) -> 3.3 | AA12: =IF($B12="",0,VLOOKUP($B12,ITEMS,19,FALSE())) -> 0 | AB12: =IF($B12="",0,VLOOKUP($B12,ITEMS,20,FALSE())) -> 0 | AC12: =VLOOKUP(J12,MATERIAL,5,FALSE())+IF(J12=0,0,$EW12) -> 0 | AD12: =VLOOKUP(K12,MATERIAL,5,FALSE())+IF(K12=0,0,$EW12) -> 0 | AE12: =VLOOKUP(L12,MATERIAL,5,FALSE())+IF(L12=0,0,$EW12) -> 0 | AF12: =VLOOKUP(M12,MATERIAL,5,FALSE())+IF(M12=0,0,$EW12) -> 0 | AG12: =VLOOKUP(N12,MATERIAL,5,FALSE())+IF(N12=0,0,$EW12) -> 0 | AH12: =VLOOKUP(O12,MATERIAL,5,FALSE())+IF(O12=0,0,$EW12) -> 0 | AI12: =VLOOKUP(P12,MATERIAL,5,FALSE())+IF(P12=0,0,$EW12) -> 0 | AJ12: =VLOOKUP(Q12,MATERIAL,5,FALSE())+IF(Q12=0,0,$EW12) -> 0 | ... AQ12: =VLOOKUP(X12,MATERIAL,5,FALSE())+IF(X12=0,0,$EW12) -> 0 | AR12: =VLOOKUP(J12,MATERIAL,6,FALSE())+IF(J12=0,0,$EW12) -> 0 | AS12: =VLOOKUP(K12,MATERIAL,6,FALSE())+IF(K12=0,0,$EW12) -> 0 | AT12: =VLOOKUP(L12,MATERIAL,6,FALSE())+IF(L12=0,0,$EW12) -> 0 | AU12: =VLOOKUP(M12,MATERIAL,6,FALSE())+IF(M12=0,0,$EW12) -> 0 | AV12: =VLOOKUP(N12,MATERIAL,6,FALSE())+IF(N12=0,0,$EW12) -> 0 | AW12: =VLOOKUP(O12,MATERIAL,6,FALSE())+IF(O12=0,0,$EW12) -> 0 | AX12: =VLOOKUP(P12,MATERIAL,6,FALSE())+IF(P12=0,0,$EW12) -> 0 | AY12: =VLOOKUP(Q12,MATERIAL,6,FALSE())+IF(Q12=0,0,$EW12) -> 0 | ... BF12: =VLOOKUP(X12,MATERIAL,6,FALSE())+IF(X12=0,0,$EW12) -> 0 | BG12: =VLOOKUP(J12,MATERIAL,7,FALSE())+IF(J12=0,0,$EW12) -> 0 | BH12: =VLOOKUP(K12,MATERIAL,7,FALSE())+IF(K12=0,0,$EW12) -> 0 | BI12: =VLOOKUP(L12,MATERIAL,7,FALSE())+IF(L12=0,0,$EW12) -> 0 | BJ12: =VLOOKUP(M12,MATERIAL,7,FALSE())+IF(M12=0,0,$EW12) -> 0 | BK12: =VLOOKUP(N12,MATERIAL,7,FALSE())+IF(N12=0,0,$EW12) -> 0 | BL12: =VLOOKUP(O12,MATERIAL,7,FALSE())+IF(O12=0,0,$EW12) -> 0 | BM12: =VLOOKUP(P12,MATERIAL,7,FALSE())+IF(P12=0,0,$EW12) -> 0 | BN12: =VLOOKUP(Q12,MATERIAL,7,FALSE())+IF(Q12=0,0,$EW12) -> 0 | ... BU12: =VLOOKUP(X12,MATERIAL,7,FALSE())+IF(X12=0,0,$EW12) -> 0 | BV12: =VLOOKUP(J12,MATERIAL,8,FALSE())+IF(J12=0,0,$EW12) -> 0 | BW12: =VLOOKUP(K12,MATERIAL,8,FALSE())+IF(K12=0,0,$EW12) -> 0 | BX12: =VLOOKUP(L12,MATERIAL,8,FALSE())+IF(L12=0,0,$EW12) -> 0 | BY12: =VLOOKUP(M12,MATERIAL,8,FALSE())+IF(M12=0,0,$EW12) -> 1 | BZ12: =VLOOKUP(N12,MATERIAL,8,FALSE())+IF(N12=0,0,$EW12) -> 0 | CA12: =VLOOKUP(O12,MATERIAL,8,FALSE())+IF(O12=0,0,$EW12) -> 0 | CB12: =VLOOKUP(P12,MATERIAL,8,FALSE())+IF(P12=0,0,$EW12) -> 0 | CC12: =VLOOKUP(Q12,MATERIAL,8,FALSE())+IF(Q12=0,0,$EW12) -> 0 | ... CJ12: =VLOOKUP(X12,MATERIAL,8,FALSE())+IF(X12=0,0,$EW12) -> 0 | CK12: =VLOOKUP(J12,MATERIAL,4,FALSE()) -> 0 | CL12: =VLOOKUP(K12,MATERIAL,4,FALSE()) -> 0 | CM12: =VLOOKUP(L12,MATERIAL,4,FALSE()) -> 0 | CN12: =VLOOKUP(M12,MATERIAL,4,FALSE()) -> 0.5 | CO12: =VLOOKUP(N12,MATERIAL,4,FALSE()) -> 0 | CP12: =VLOOKUP(O12,MATERIAL,4,FALSE()) -> 0 | CQ12: =VLOOKUP(P12,MATERIAL,4,FALSE()) -> 0 | CR12: =VLOOKUP(Q12,MATERIAL,4,FALSE()) -> 0 | ... CY12: =VLOOKUP(X12,MATERIAL,4,FALSE()) -> 0 | CZ12: =IF(J12=0,0,LEFT(J12,1)) -> 0 | DA12: =IF(K12=0,0,LEFT(K12,1)) -> 0 | DB12: =IF(L12=0,0,LEFT(L12,1)) -> 0 | DC12: =IF(M12=0,0,LEFT(M12,1)) -> C | DD12: =IF(N12=0,0,LEFT(N12,1)) -> 0 | DE12: =IF(O12=0,0,LEFT(O12,1)) -> 0 | DF12: =IF(P12=0,0,LEFT(P12,1)) -> 0 | DG12: =IF(Q12=0,0,LEFT(Q12,1)) -> 0 | ... DN12: =IF(X12=0,0,LEFT(X12,1)) -> 0 | DO12: =SUMIF(CZ$5:CZ$32,$ED12,CK$5:CK$32) -> 0 | DP12: =SUMIF(DA$5:DA$32,$ED12,CL$5:CL$32) -> 0 | DQ12: =SUMIF(DB$5:DB$32,$ED12,CM$5:CM$32) -> 0 | DR12: =SUMIF(DC$5:DC$32,$ED12,CN$5:CN$32) -> 0 | DS12: =SUMIF(DD$5:DD$32,$ED12,CO$5:CO$32) -> 0 | DT12: =SUMIF(DE$5:DE$32,$ED12,CP$5:CP$32) -> 0 | DU12: =SUMIF(DF$5:DF$32,$ED12,CQ$5:CQ$32) -> 0 | DV12: =SUMIF(DG$5:DG$32,$ED12,CR$5:CR$32) -> 0 | ... EC12: =SUMIF(DN$5:DN$32,$ED12,CY$5:CY$32) -> 0 | ED12: P | EF12: =VLOOKUP(J12,MATERIAL,9,FALSE()) -> 0 | EG12: =VLOOKUP(K12,MATERIAL,9,FALSE()) -> 0 | EH12: =VLOOKUP(L12,MATERIAL,9,FALSE()) -> 0 | EI12: =VLOOKUP(M12,MATERIAL,9,FALSE()) -> 0 | EJ12: =VLOOKUP(N12,MATERIAL,9,FALSE()) -> 0 | EK12: =VLOOKUP(O12,MATERIAL,9,FALSE()) -> 0 | EL12: =VLOOKUP(P12,MATERIAL,9,FALSE()) -> 0 | EM12: =VLOOKUP(Q12,MATERIAL,9,FALSE()) -> 0 | ... ET12: =VLOOKUP(X12,MATERIAL,9,FALSE()) -> 0 | EU12: =IF($B12="",0,VLOOKUP($B12,ITEMS,EU$2,FALSE())) -> 0 | EV12: =VLOOKUP(EU12,MWS,2) -> 0 | EW12: =VLOOKUP(EU12,MWS,3) -> 0
A13: =EV13 -> 0 | C13: Ua | D13: =AG1 -> 4 | E13: =AV1 -> 4 | F13: =BK1 -> 2 | G13: =BZ1 -> 4 | H13: =MAX(EJ5:EJ32) -> 0 | J13: =IF($B13="",0,VLOOKUP($B13,ITEMS,J$2,FALSE())) -> 0 | K13: =IF($B13="",0,VLOOKUP($B13,ITEMS,K$2,FALSE())) -> 0 | L13: =IF($B13="",0,VLOOKUP($B13,ITEMS,L$2,FALSE())) -> 0 | M13: =IF($B13="",0,VLOOKUP($B13,ITEMS,M$2,FALSE())) -> 0 | N13: =IF($B13="",0,VLOOKUP($B13,ITEMS,N$2,FALSE())) -> 0 | O13: =IF($B13="",0,VLOOKUP($B13,ITEMS,O$2,FALSE())) -> 0 | P13: =IF($B13="",0,VLOOKUP($B13,ITEMS,P$2,FALSE())) -> 0 | Q13: =IF($B13="",0,VLOOKUP($B13,ITEMS,Q$2,FALSE())) -> 0 | ... X13: =IF($B13="",0,VLOOKUP($B13,ITEMS,X$2,FALSE())) -> 0 | Y13: =IF($B13="",0,VLOOKUP($B13,ITEMS,17,FALSE())) -> 0 | Z13: =IF($B13="",0,VLOOKUP($B13,ITEMS,18,FALSE())) -> 0 | AA13: =IF($B13="",0,VLOOKUP($B13,ITEMS,19,FALSE())) -> 0 | AB13: =IF($B13="",0,VLOOKUP($B13,ITEMS,20,FALSE())) -> 0 | AC13: =VLOOKUP(J13,MATERIAL,5,FALSE())+IF(J13=0,0,$EW13) -> 0 | AD13: =VLOOKUP(K13,MATERIAL,5,FALSE())+IF(K13=0,0,$EW13) -> 0 | AE13: =VLOOKUP(L13,MATERIAL,5,FALSE())+IF(L13=0,0,$EW13) -> 0 | AF13: =VLOOKUP(M13,MATERIAL,5,FALSE())+IF(M13=0,0,$EW13) -> 0 | AG13: =VLOOKUP(N13,MATERIAL,5,FALSE())+IF(N13=0,0,$EW13) -> 0 | AH13: =VLOOKUP(O13,MATERIAL,5,FALSE())+IF(O13=0,0,$EW13) -> 0 | AI13: =VLOOKUP(P13,MATERIAL,5,FALSE())+IF(P13=0,0,$EW13) -> 0 | AJ13: =VLOOKUP(Q13,MATERIAL,5,FALSE())+IF(Q13=0,0,$EW13) -> 0 | ... AQ13: =VLOOKUP(X13,MATERIAL,5,FALSE())+IF(X13=0,0,$EW13) -> 0 | AR13: =VLOOKUP(J13,MATERIAL,6,FALSE())+IF(J13=0,0,$EW13) -> 0 | AS13: =VLOOKUP(K13,MATERIAL,6,FALSE())+IF(K13=0,0,$EW13) -> 0 | AT13: =VLOOKUP(L13,MATERIAL,6,FALSE())+IF(L13=0,0,$EW13) -> 0 | AU13: =VLOOKUP(M13,MATERIAL,6,FALSE())+IF(M13=0,0,$EW13) -> 0 | AV13: =VLOOKUP(N13,MATERIAL,6,FALSE())+IF(N13=0,0,$EW13) -> 0 | AW13: =VLOOKUP(O13,MATERIAL,6,FALSE())+IF(O13=0,0,$EW13) -> 0 | AX13: =VLOOKUP(P13,MATERIAL,6,FALSE())+IF(P13=0,0,$EW13) -> 0 | AY13: =VLOOKUP(Q13,MATERIAL,6,FALSE())+IF(Q13=0,0,$EW13) -> 0 | ... BF13: =VLOOKUP(X13,MATERIAL,6,FALSE())+IF(X13=0,0,$EW13) -> 0 | BG13: =VLOOKUP(J13,MATERIAL,7,FALSE())+IF(J13=0,0,$EW13) -> 0 | BH13: =VLOOKUP(K13,MATERIAL,7,FALSE())+IF(K13=0,0,$EW13) -> 0 | BI13: =VLOOKUP(L13,MATERIAL,7,FALSE())+IF(L13=0,0,$EW13) -> 0 | BJ13: =VLOOKUP(M13,MATERIAL,7,FALSE())+IF(M13=0,0,$EW13) -> 0 | BK13: =VLOOKUP(N13,MATERIAL,7,FALSE())+IF(N13=0,0,$EW13) -> 0 | BL13: =VLOOKUP(O13,MATERIAL,7,FALSE())+IF(O13=0,0,$EW13) -> 0 | BM13: =VLOOKUP(P13,MATERIAL,7,FALSE())+IF(P13=0,0,$EW13) -> 0 | BN13: =VLOOKUP(Q13,MATERIAL,7,FALSE())+IF(Q13=0,0,$EW13) -> 0 | ... BU13: =VLOOKUP(X13,MATERIAL,7,FALSE())+IF(X13=0,0,$EW13) -> 0 | BV13: =VLOOKUP(J13,MATERIAL,8,FALSE())+IF(J13=0,0,$EW13) -> 0 | BW13: =VLOOKUP(K13,MATERIAL,8,FALSE())+IF(K13=0,0,$EW13) -> 0 | BX13: =VLOOKUP(L13,MATERIAL,8,FALSE())+IF(L13=0,0,$EW13) -> 0 | BY13: =VLOOKUP(M13,MATERIAL,8,FALSE())+IF(M13=0,0,$EW13) -> 0 | BZ13: =VLOOKUP(N13,MATERIAL,8,FALSE())+IF(N13=0,0,$EW13) -> 0 | CA13: =VLOOKUP(O13,MATERIAL,8,FALSE())+IF(O13=0,0,$EW13) -> 0 | CB13: =VLOOKUP(P13,MATERIAL,8,FALSE())+IF(P13=0,0,$EW13) -> 0 | CC13: =VLOOKUP(Q13,MATERIAL,8,FALSE())+IF(Q13=0,0,$EW13) -> 0 | ... CJ13: =VLOOKUP(X13,MATERIAL,8,FALSE())+IF(X13=0,0,$EW13) -> 0 | CK13: =VLOOKUP(J13,MATERIAL,4,FALSE()) -> 0 | CL13: =VLOOKUP(K13,MATERIAL,4,FALSE()) -> 0 | CM13: =VLOOKUP(L13,MATERIAL,4,FALSE()) -> 0 | CN13: =VLOOKUP(M13,MATERIAL,4,FALSE()) -> 0 | CO13: =VLOOKUP(N13,MATERIAL,4,FALSE()) -> 0 | CP13: =VLOOKUP(O13,MATERIAL,4,FALSE()) -> 0 | CQ13: =VLOOKUP(P13,MATERIAL,4,FALSE()) -> 0 | CR13: =VLOOKUP(Q13,MATERIAL,4,FALSE()) -> 0 | ... CY13: =VLOOKUP(X13,MATERIAL,4,FALSE()) -> 0 | CZ13: =IF(J13=0,0,LEFT(J13,1)) -> 0 | DA13: =IF(K13=0,0,LEFT(K13,1)) -> 0 | DB13: =IF(L13=0,0,LEFT(L13,1)) -> 0 | DC13: =IF(M13=0,0,LEFT(M13,1)) -> 0 | DD13: =IF(N13=0,0,LEFT(N13,1)) -> 0 | DE13: =IF(O13=0,0,LEFT(O13,1)) -> 0 | DF13: =IF(P13=0,0,LEFT(P13,1)) -> 0 | DG13: =IF(Q13=0,0,LEFT(Q13,1)) -> 0 | ... DN13: =IF(X13=0,0,LEFT(X13,1)) -> 0 | EF13: =VLOOKUP(J13,MATERIAL,9,FALSE()) -> 0 | EG13: =VLOOKUP(K13,MATERIAL,9,FALSE()) -> 0 | EH13: =VLOOKUP(L13,MATERIAL,9,FALSE()) -> 0 | EI13: =VLOOKUP(M13,MATERIAL,9,FALSE()) -> 0 | EJ13: =VLOOKUP(N13,MATERIAL,9,FALSE()) -> 0 | EK13: =VLOOKUP(O13,MATERIAL,9,FALSE()) -> 0 | EL13: =VLOOKUP(P13,MATERIAL,9,FALSE()) -> 0 | EM13: =VLOOKUP(Q13,MATERIAL,9,FALSE()) -> 0 | ... ET13: =VLOOKUP(X13,MATERIAL,9,FALSE()) -> 0 | EU13: =IF($B13="",0,VLOOKUP($B13,ITEMS,EU$2,FALSE())) -> 0 | EV13: =VLOOKUP(EU13,MWS,2) -> 0 | EW13: =VLOOKUP(EU13,MWS,3) -> 0
A14: =EV14 -> 0 | C14: El | D14: =AH1 -> 4 | E14: =AW1 -> 4 | F14: =BL1 -> 2 | G14: =CA1 -> 4 | H14: =MAX(EK5:EK32) -> 0 | J14: =IF($B14="",0,VLOOKUP($B14,ITEMS,J$2,FALSE())) -> 0 | K14: =IF($B14="",0,VLOOKUP($B14,ITEMS,K$2,FALSE())) -> 0 | L14: =IF($B14="",0,VLOOKUP($B14,ITEMS,L$2,FALSE())) -> 0 | M14: =IF($B14="",0,VLOOKUP($B14,ITEMS,M$2,FALSE())) -> 0 | N14: =IF($B14="",0,VLOOKUP($B14,ITEMS,N$2,FALSE())) -> 0 | O14: =IF($B14="",0,VLOOKUP($B14,ITEMS,O$2,FALSE())) -> 0 | P14: =IF($B14="",0,VLOOKUP($B14,ITEMS,P$2,FALSE())) -> 0 | Q14: =IF($B14="",0,VLOOKUP($B14,ITEMS,Q$2,FALSE())) -> 0 | ... X14: =IF($B14="",0,VLOOKUP($B14,ITEMS,X$2,FALSE())) -> 0 | Y14: =IF($B14="",0,VLOOKUP($B14,ITEMS,17,FALSE())) -> 0 | Z14: =IF($B14="",0,VLOOKUP($B14,ITEMS,18,FALSE())) -> 0 | AA14: =IF($B14="",0,VLOOKUP($B14,ITEMS,19,FALSE())) -> 0 | AB14: =IF($B14="",0,VLOOKUP($B14,ITEMS,20,FALSE())) -> 0 | AC14: =VLOOKUP(J14,MATERIAL,5,FALSE())+IF(J14=0,0,$EW14) -> 0 | AD14: =VLOOKUP(K14,MATERIAL,5,FALSE())+IF(K14=0,0,$EW14) -> 0 | AE14: =VLOOKUP(L14,MATERIAL,5,FALSE())+IF(L14=0,0,$EW14) -> 0 | AF14: =VLOOKUP(M14,MATERIAL,5,FALSE())+IF(M14=0,0,$EW14) -> 0 | AG14: =VLOOKUP(N14,MATERIAL,5,FALSE())+IF(N14=0,0,$EW14) -> 0 | AH14: =VLOOKUP(O14,MATERIAL,5,FALSE())+IF(O14=0,0,$EW14) -> 0 | AI14: =VLOOKUP(P14,MATERIAL,5,FALSE())+IF(P14=0,0,$EW14) -> 0 | AJ14: =VLOOKUP(Q14,MATERIAL,5,FALSE())+IF(Q14=0,0,$EW14) -> 0 | ... AQ14: =VLOOKUP(X14,MATERIAL,5,FALSE())+IF(X14=0,0,$EW14) -> 0 | AR14: =VLOOKUP(J14,MATERIAL,6,FALSE())+IF(J14=0,0,$EW14) -> 0 | AS14: =VLOOKUP(K14,MATERIAL,6,FALSE())+IF(K14=0,0,$EW14) -> 0 | AT14: =VLOOKUP(L14,MATERIAL,6,FALSE())+IF(L14=0,0,$EW14) -> 0 | AU14: =VLOOKUP(M14,MATERIAL,6,FALSE())+IF(M14=0,0,$EW14) -> 0 | AV14: =VLOOKUP(N14,MATERIAL,6,FALSE())+IF(N14=0,0,$EW14) -> 0 | AW14: =VLOOKUP(O14,MATERIAL,6,FALSE())+IF(O14=0,0,$EW14) -> 0 | AX14: =VLOOKUP(P14,MATERIAL,6,FALSE())+IF(P14=0,0,$EW14) -> 0 | AY14: =VLOOKUP(Q14,MATERIAL,6,FALSE())+IF(Q14=0,0,$EW14) -> 0 | ... BF14: =VLOOKUP(X14,MATERIAL,6,FALSE())+IF(X14=0,0,$EW14) -> 0 | BG14: =VLOOKUP(J14,MATERIAL,7,FALSE())+IF(J14=0,0,$EW14) -> 0 | BH14: =VLOOKUP(K14,MATERIAL,7,FALSE())+IF(K14=0,0,$EW14) -> 0 | BI14: =VLOOKUP(L14,MATERIAL,7,FALSE())+IF(L14=0,0,$EW14) -> 0 | BJ14: =VLOOKUP(M14,MATERIAL,7,FALSE())+IF(M14=0,0,$EW14) -> 0 | BK14: =VLOOKUP(N14,MATERIAL,7,FALSE())+IF(N14=0,0,$EW14) -> 0 | BL14: =VLOOKUP(O14,MATERIAL,7,FALSE())+IF(O14=0,0,$EW14) -> 0 | BM14: =VLOOKUP(P14,MATERIAL,7,FALSE())+IF(P14=0,0,$EW14) -> 0 | BN14: =VLOOKUP(Q14,MATERIAL,7,FALSE())+IF(Q14=0,0,$EW14) -> 0 | ... BU14: =VLOOKUP(X14,MATERIAL,7,FALSE())+IF(X14=0,0,$EW14) -> 0 | BV14: =VLOOKUP(J14,MATERIAL,8,FALSE())+IF(J14=0,0,$EW14) -> 0 | BW14: =VLOOKUP(K14,MATERIAL,8,FALSE())+IF(K14=0,0,$EW14) -> 0 | BX14: =VLOOKUP(L14,MATERIAL,8,FALSE())+IF(L14=0,0,$EW14) -> 0 | BY14: =VLOOKUP(M14,MATERIAL,8,FALSE())+IF(M14=0,0,$EW14) -> 0 | BZ14: =VLOOKUP(N14,MATERIAL,8,FALSE())+IF(N14=0,0,$EW14) -> 0 | CA14: =VLOOKUP(O14,MATERIAL,8,FALSE())+IF(O14=0,0,$EW14) -> 0 | CB14: =VLOOKUP(P14,MATERIAL,8,FALSE())+IF(P14=0,0,$EW14) -> 0 | CC14: =VLOOKUP(Q14,MATERIAL,8,FALSE())+IF(Q14=0,0,$EW14) -> 0 | ... CJ14: =VLOOKUP(X14,MATERIAL,8,FALSE())+IF(X14=0,0,$EW14) -> 0 | CK14: =VLOOKUP(J14,MATERIAL,4,FALSE()) -> 0 | CL14: =VLOOKUP(K14,MATERIAL,4,FALSE()) -> 0 | CM14: =VLOOKUP(L14,MATERIAL,4,FALSE()) -> 0 | CN14: =VLOOKUP(M14,MATERIAL,4,FALSE()) -> 0 | CO14: =VLOOKUP(N14,MATERIAL,4,FALSE()) -> 0 | CP14: =VLOOKUP(O14,MATERIAL,4,FALSE()) -> 0 | CQ14: =VLOOKUP(P14,MATERIAL,4,FALSE()) -> 0 | CR14: =VLOOKUP(Q14,MATERIAL,4,FALSE()) -> 0 | ... CY14: =VLOOKUP(X14,MATERIAL,4,FALSE()) -> 0 | CZ14: =IF(J14=0,0,LEFT(J14,1)) -> 0 | DA14: =IF(K14=0,0,LEFT(K14,1)) -> 0 | DB14: =IF(L14=0,0,LEFT(L14,1)) -> 0 | DC14: =IF(M14=0,0,LEFT(M14,1)) -> 0 | DD14: =IF(N14=0,0,LEFT(N14,1)) -> 0 | DE14: =IF(O14=0,0,LEFT(O14,1)) -> 0 | DF14: =IF(P14=0,0,LEFT(P14,1)) -> 0 | DG14: =IF(Q14=0,0,LEFT(Q14,1)) -> 0 | ... DN14: =IF(X14=0,0,LEFT(X14,1)) -> 0 | DO14: =SUM(CK5:CK32) -> 2.5 | DP14: =SUM(CL5:CL32) -> 0 | DQ14: =SUM(CM5:CM32) -> 0 | DR14: =SUM(CN5:CN32) -> 3.5 | DS14: =SUM(CO5:CO32) -> 3 | DT14: =SUM(CP5:CP32) -> 3 | DU14: =SUM(CQ5:CQ32) -> 2 | DV14: =SUM(CR5:CR32) -> 0 | ... EC14: =SUM(CY5:CY32) -> 2 | ED14: Total | EF14: =VLOOKUP(J14,MATERIAL,9,FALSE()) -> 0 | EG14: =VLOOKUP(K14,MATERIAL,9,FALSE()) -> 0 | EH14: =VLOOKUP(L14,MATERIAL,9,FALSE()) -> 0 | EI14: =VLOOKUP(M14,MATERIAL,9,FALSE()) -> 0 | EJ14: =VLOOKUP(N14,MATERIAL,9,FALSE()) -> 0 | EK14: =VLOOKUP(O14,MATERIAL,9,FALSE()) -> 0 | EL14: =VLOOKUP(P14,MATERIAL,9,FALSE()) -> 0 | EM14: =VLOOKUP(Q14,MATERIAL,9,FALSE()) -> 0 | ... ET14: =VLOOKUP(X14,MATERIAL,9,FALSE()) -> 0 | EU14: =IF($B14="",0,VLOOKUP($B14,ITEMS,EU$2,FALSE())) -> 0 | EV14: =VLOOKUP(EU14,MWS,2) -> 0 | EW14: =VLOOKUP(EU14,MWS,3) -> 0
A15: =EV15 -> 0 | C15: Fo | D15: =AI1 -> 4 | E15: =AX1 -> 3 | F15: =BM1 -> 2 | G15: =CB1 -> 3 | H15: =MAX(EL5:EL32) -> 0 | J15: =IF($B15="",0,VLOOKUP($B15,ITEMS,J$2,FALSE())) -> 0 | K15: =IF($B15="",0,VLOOKUP($B15,ITEMS,K$2,FALSE())) -> 0 | L15: =IF($B15="",0,VLOOKUP($B15,ITEMS,L$2,FALSE())) -> 0 | M15: =IF($B15="",0,VLOOKUP($B15,ITEMS,M$2,FALSE())) -> 0 | N15: =IF($B15="",0,VLOOKUP($B15,ITEMS,N$2,FALSE())) -> 0 | O15: =IF($B15="",0,VLOOKUP($B15,ITEMS,O$2,FALSE())) -> 0 | P15: =IF($B15="",0,VLOOKUP($B15,ITEMS,P$2,FALSE())) -> 0 | Q15: =IF($B15="",0,VLOOKUP($B15,ITEMS,Q$2,FALSE())) -> 0 | ... X15: =IF($B15="",0,VLOOKUP($B15,ITEMS,X$2,FALSE())) -> 0 | Y15: =IF($B15="",0,VLOOKUP($B15,ITEMS,17,FALSE())) -> 0 | Z15: =IF($B15="",0,VLOOKUP($B15,ITEMS,18,FALSE())) -> 0 | AA15: =IF($B15="",0,VLOOKUP($B15,ITEMS,19,FALSE())) -> 0 | AB15: =IF($B15="",0,VLOOKUP($B15,ITEMS,20,FALSE())) -> 0 | AC15: =VLOOKUP(J15,MATERIAL,5,FALSE())+IF(J15=0,0,$EW15) -> 0 | AD15: =VLOOKUP(K15,MATERIAL,5,FALSE())+IF(K15=0,0,$EW15) -> 0 | AE15: =VLOOKUP(L15,MATERIAL,5,FALSE())+IF(L15=0,0,$EW15) -> 0 | AF15: =VLOOKUP(M15,MATERIAL,5,FALSE())+IF(M15=0,0,$EW15) -> 0 | AG15: =VLOOKUP(N15,MATERIAL,5,FALSE())+IF(N15=0,0,$EW15) -> 0 | AH15: =VLOOKUP(O15,MATERIAL,5,FALSE())+IF(O15=0,0,$EW15) -> 0 | AI15: =VLOOKUP(P15,MATERIAL,5,FALSE())+IF(P15=0,0,$EW15) -> 0 | AJ15: =VLOOKUP(Q15,MATERIAL,5,FALSE())+IF(Q15=0,0,$EW15) -> 0 | ... AQ15: =VLOOKUP(X15,MATERIAL,5,FALSE())+IF(X15=0,0,$EW15) -> 0 | AR15: =VLOOKUP(J15,MATERIAL,6,FALSE())+IF(J15=0,0,$EW15) -> 0 | AS15: =VLOOKUP(K15,MATERIAL,6,FALSE())+IF(K15=0,0,$EW15) -> 0 | AT15: =VLOOKUP(L15,MATERIAL,6,FALSE())+IF(L15=0,0,$EW15) -> 0 | AU15: =VLOOKUP(M15,MATERIAL,6,FALSE())+IF(M15=0,0,$EW15) -> 0 | AV15: =VLOOKUP(N15,MATERIAL,6,FALSE())+IF(N15=0,0,$EW15) -> 0 | AW15: =VLOOKUP(O15,MATERIAL,6,FALSE())+IF(O15=0,0,$EW15) -> 0 | AX15: =VLOOKUP(P15,MATERIAL,6,FALSE())+IF(P15=0,0,$EW15) -> 0 | AY15: =VLOOKUP(Q15,MATERIAL,6,FALSE())+IF(Q15=0,0,$EW15) -> 0 | ... BF15: =VLOOKUP(X15,MATERIAL,6,FALSE())+IF(X15=0,0,$EW15) -> 0 | BG15: =VLOOKUP(J15,MATERIAL,7,FALSE())+IF(J15=0,0,$EW15) -> 0 | BH15: =VLOOKUP(K15,MATERIAL,7,FALSE())+IF(K15=0,0,$EW15) -> 0 | BI15: =VLOOKUP(L15,MATERIAL,7,FALSE())+IF(L15=0,0,$EW15) -> 0 | BJ15: =VLOOKUP(M15,MATERIAL,7,FALSE())+IF(M15=0,0,$EW15) -> 0 | BK15: =VLOOKUP(N15,MATERIAL,7,FALSE())+IF(N15=0,0,$EW15) -> 0 | BL15: =VLOOKUP(O15,MATERIAL,7,FALSE())+IF(O15=0,0,$EW15) -> 0 | BM15: =VLOOKUP(P15,MATERIAL,7,FALSE())+IF(P15=0,0,$EW15) -> 0 | BN15: =VLOOKUP(Q15,MATERIAL,7,FALSE())+IF(Q15=0,0,$EW15) -> 0 | ... BU15: =VLOOKUP(X15,MATERIAL,7,FALSE())+IF(X15=0,0,$EW15) -> 0 | BV15: =VLOOKUP(J15,MATERIAL,8,FALSE())+IF(J15=0,0,$EW15) -> 0 | BW15: =VLOOKUP(K15,MATERIAL,8,FALSE())+IF(K15=0,0,$EW15) -> 0 | BX15: =VLOOKUP(L15,MATERIAL,8,FALSE())+IF(L15=0,0,$EW15) -> 0 | BY15: =VLOOKUP(M15,MATERIAL,8,FALSE())+IF(M15=0,0,$EW15) -> 0 | BZ15: =VLOOKUP(N15,MATERIAL,8,FALSE())+IF(N15=0,0,$EW15) -> 0 | CA15: =VLOOKUP(O15,MATERIAL,8,FALSE())+IF(O15=0,0,$EW15) -> 0 | CB15: =VLOOKUP(P15,MATERIAL,8,FALSE())+IF(P15=0,0,$EW15) -> 0 | CC15: =VLOOKUP(Q15,MATERIAL,8,FALSE())+IF(Q15=0,0,$EW15) -> 0 | ... CJ15: =VLOOKUP(X15,MATERIAL,8,FALSE())+IF(X15=0,0,$EW15) -> 0 | CK15: =VLOOKUP(J15,MATERIAL,4,FALSE()) -> 0 | CL15: =VLOOKUP(K15,MATERIAL,4,FALSE()) -> 0 | CM15: =VLOOKUP(L15,MATERIAL,4,FALSE()) -> 0 | CN15: =VLOOKUP(M15,MATERIAL,4,FALSE()) -> 0 | CO15: =VLOOKUP(N15,MATERIAL,4,FALSE()) -> 0 | CP15: =VLOOKUP(O15,MATERIAL,4,FALSE()) -> 0 | CQ15: =VLOOKUP(P15,MATERIAL,4,FALSE()) -> 0 | CR15: =VLOOKUP(Q15,MATERIAL,4,FALSE()) -> 0 | ... CY15: =VLOOKUP(X15,MATERIAL,4,FALSE()) -> 0 | CZ15: =IF(J15=0,0,LEFT(J15,1)) -> 0 | DA15: =IF(K15=0,0,LEFT(K15,1)) -> 0 | DB15: =IF(L15=0,0,LEFT(L15,1)) -> 0 | DC15: =IF(M15=0,0,LEFT(M15,1)) -> 0 | DD15: =IF(N15=0,0,LEFT(N15,1)) -> 0 | DE15: =IF(O15=0,0,LEFT(O15,1)) -> 0 | DF15: =IF(P15=0,0,LEFT(P15,1)) -> 0 | DG15: =IF(Q15=0,0,LEFT(Q15,1)) -> 0 | ... DN15: =IF(X15=0,0,LEFT(X15,1)) -> 0 | DO15: =DO5/1.5+DO6/2+DO7/3 -> 1 | DP15: =DP5/1.5+DP6/2+DP7/3 -> 0 | DQ15: =DQ5/1.5+DQ6/2+DQ7/3 -> 0 | DR15: =DR5/1.5+DR6/2+DR7/3 -> 1 | DS15: =DS5/1.5+DS6/2+DS7/3 -> 1 | DT15: =DT5/1.5+DT6/2+DT7/3 -> 1 | DU15: =DU5/1.5+DU6/2+DU7/3 -> 1 | DV15: =DV5/1.5+DV6/2+DV7/3 -> 0 | ... EC15: =EC5/1.5+EC6/2+EC7/3 -> 0 | ED15: DQG | EF15: =VLOOKUP(J15,MATERIAL,9,FALSE()) -> 0 | EG15: =VLOOKUP(K15,MATERIAL,9,FALSE()) -> 0 | EH15: =VLOOKUP(L15,MATERIAL,9,FALSE()) -> 0 | EI15: =VLOOKUP(M15,MATERIAL,9,FALSE()) -> 0 | EJ15: =VLOOKUP(N15,MATERIAL,9,FALSE()) -> 0 | EK15: =VLOOKUP(O15,MATERIAL,9,FALSE()) -> 0 | EL15: =VLOOKUP(P15,MATERIAL,9,FALSE()) -> 0 | EM15: =VLOOKUP(Q15,MATERIAL,9,FALSE()) -> 0 | ... ET15: =VLOOKUP(X15,MATERIAL,9,FALSE()) -> 0 | EU15: =IF($B15="",0,VLOOKUP($B15,ITEMS,EU$2,FALSE())) -> 0 | EV15: =VLOOKUP(EU15,MWS,2) -> 0 | EW15: =VLOOKUP(EU15,MWS,3) -> 0
A16: =EV16 -> 0 | C16: Ha | D16: =AJ1 -> 0 | E16: =AY1 -> 0 | F16: =BN1 -> 0 | G16: =CC1 -> 0 | H16: =MAX(EM5:EM32) -> 0 | J16: =IF($B16="",0,VLOOKUP($B16,ITEMS,J$2,FALSE())) -> 0 | K16: =IF($B16="",0,VLOOKUP($B16,ITEMS,K$2,FALSE())) -> 0 | L16: =IF($B16="",0,VLOOKUP($B16,ITEMS,L$2,FALSE())) -> 0 | M16: =IF($B16="",0,VLOOKUP($B16,ITEMS,M$2,FALSE())) -> 0 | N16: =IF($B16="",0,VLOOKUP($B16,ITEMS,N$2,FALSE())) -> 0 | O16: =IF($B16="",0,VLOOKUP($B16,ITEMS,O$2,FALSE())) -> 0 | P16: =IF($B16="",0,VLOOKUP($B16,ITEMS,P$2,FALSE())) -> 0 | Q16: =IF($B16="",0,VLOOKUP($B16,ITEMS,Q$2,FALSE())) -> 0 | ... X16: =IF($B16="",0,VLOOKUP($B16,ITEMS,X$2,FALSE())) -> 0 | Y16: =IF($B16="",0,VLOOKUP($B16,ITEMS,17,FALSE())) -> 0 | Z16: =IF($B16="",0,VLOOKUP($B16,ITEMS,18,FALSE())) -> 0 | AA16: =IF($B16="",0,VLOOKUP($B16,ITEMS,19,FALSE())) -> 0 | AB16: =IF($B16="",0,VLOOKUP($B16,ITEMS,20,FALSE())) -> 0 | AC16: =VLOOKUP(J16,MATERIAL,5,FALSE())+IF(J16=0,0,$EW16) -> 0 | AD16: =VLOOKUP(K16,MATERIAL,5,FALSE())+IF(K16=0,0,$EW16) -> 0 | AE16: =VLOOKUP(L16,MATERIAL,5,FALSE())+IF(L16=0,0,$EW16) -> 0 | AF16: =VLOOKUP(M16,MATERIAL,5,FALSE())+IF(M16=0,0,$EW16) -> 0 | AG16: =VLOOKUP(N16,MATERIAL,5,FALSE())+IF(N16=0,0,$EW16) -> 0 | AH16: =VLOOKUP(O16,MATERIAL,5,FALSE())+IF(O16=0,0,$EW16) -> 0 | AI16: =VLOOKUP(P16,MATERIAL,5,FALSE())+IF(P16=0,0,$EW16) -> 0 | AJ16: =VLOOKUP(Q16,MATERIAL,5,FALSE())+IF(Q16=0,0,$EW16) -> 0 | ... AQ16: =VLOOKUP(X16,MATERIAL,5,FALSE())+IF(X16=0,0,$EW16) -> 0 | AR16: =VLOOKUP(J16,MATERIAL,6,FALSE())+IF(J16=0,0,$EW16) -> 0 | AS16: =VLOOKUP(K16,MATERIAL,6,FALSE())+IF(K16=0,0,$EW16) -> 0 | AT16: =VLOOKUP(L16,MATERIAL,6,FALSE())+IF(L16=0,0,$EW16) -> 0 | AU16: =VLOOKUP(M16,MATERIAL,6,FALSE())+IF(M16=0,0,$EW16) -> 0 | AV16: =VLOOKUP(N16,MATERIAL,6,FALSE())+IF(N16=0,0,$EW16) -> 0 | AW16: =VLOOKUP(O16,MATERIAL,6,FALSE())+IF(O16=0,0,$EW16) -> 0 | AX16: =VLOOKUP(P16,MATERIAL,6,FALSE())+IF(P16=0,0,$EW16) -> 0 | AY16: =VLOOKUP(Q16,MATERIAL,6,FALSE())+IF(Q16=0,0,$EW16) -> 0 | ... BF16: =VLOOKUP(X16,MATERIAL,6,FALSE())+IF(X16=0,0,$EW16) -> 0 | BG16: =VLOOKUP(J16,MATERIAL,7,FALSE())+IF(J16=0,0,$EW16) -> 0 | BH16: =VLOOKUP(K16,MATERIAL,7,FALSE())+IF(K16=0,0,$EW16) -> 0 | BI16: =VLOOKUP(L16,MATERIAL,7,FALSE())+IF(L16=0,0,$EW16) -> 0 | BJ16: =VLOOKUP(M16,MATERIAL,7,FALSE())+IF(M16=0,0,$EW16) -> 0 | BK16: =VLOOKUP(N16,MATERIAL,7,FALSE())+IF(N16=0,0,$EW16) -> 0 | BL16: =VLOOKUP(O16,MATERIAL,7,FALSE())+IF(O16=0,0,$EW16) -> 0 | BM16: =VLOOKUP(P16,MATERIAL,7,FALSE())+IF(P16=0,0,$EW16) -> 0 | BN16: =VLOOKUP(Q16,MATERIAL,7,FALSE())+IF(Q16=0,0,$EW16) -> 0 | ... BU16: =VLOOKUP(X16,MATERIAL,7,FALSE())+IF(X16=0,0,$EW16) -> 0 | BV16: =VLOOKUP(J16,MATERIAL,8,FALSE())+IF(J16=0,0,$EW16) -> 0 | BW16: =VLOOKUP(K16,MATERIAL,8,FALSE())+IF(K16=0,0,$EW16) -> 0 | BX16: =VLOOKUP(L16,MATERIAL,8,FALSE())+IF(L16=0,0,$EW16) -> 0 | BY16: =VLOOKUP(M16,MATERIAL,8,FALSE())+IF(M16=0,0,$EW16) -> 0 | BZ16: =VLOOKUP(N16,MATERIAL,8,FALSE())+IF(N16=0,0,$EW16) -> 0 | CA16: =VLOOKUP(O16,MATERIAL,8,FALSE())+IF(O16=0,0,$EW16) -> 0 | CB16: =VLOOKUP(P16,MATERIAL,8,FALSE())+IF(P16=0,0,$EW16) -> 0 | CC16: =VLOOKUP(Q16,MATERIAL,8,FALSE())+IF(Q16=0,0,$EW16) -> 0 | ... CJ16: =VLOOKUP(X16,MATERIAL,8,FALSE())+IF(X16=0,0,$EW16) -> 0 | CK16: =VLOOKUP(J16,MATERIAL,4,FALSE()) -> 0 | CL16: =VLOOKUP(K16,MATERIAL,4,FALSE()) -> 0 | CM16: =VLOOKUP(L16,MATERIAL,4,FALSE()) -> 0 | CN16: =VLOOKUP(M16,MATERIAL,4,FALSE()) -> 0 | CO16: =VLOOKUP(N16,MATERIAL,4,FALSE()) -> 0 | CP16: =VLOOKUP(O16,MATERIAL,4,FALSE()) -> 0 | CQ16: =VLOOKUP(P16,MATERIAL,4,FALSE()) -> 0 | CR16: =VLOOKUP(Q16,MATERIAL,4,FALSE()) -> 0 | ... CY16: =VLOOKUP(X16,MATERIAL,4,FALSE()) -> 0 | CZ16: =IF(J16=0,0,LEFT(J16,1)) -> 0 | DA16: =IF(K16=0,0,LEFT(K16,1)) -> 0 | DB16: =IF(L16=0,0,LEFT(L16,1)) -> 0 | DC16: =IF(M16=0,0,LEFT(M16,1)) -> 0 | DD16: =IF(N16=0,0,LEFT(N16,1)) -> 0 | DE16: =IF(O16=0,0,LEFT(O16,1)) -> 0 | DF16: =IF(P16=0,0,LEFT(P16,1)) -> 0 | DG16: =IF(Q16=0,0,LEFT(Q16,1)) -> 0 | ... DN16: =IF(X16=0,0,LEFT(X16,1)) -> 0 | DO16: =DO9+DO10+DO11+DO12 -> 1 | DP16: =DP9+DP10+DP11+DP12 -> 0 | DQ16: =DQ9+DQ10+DQ11+DQ12 -> 0 | DR16: =DR9+DR10+DR11+DR12 -> 0 | DS16: =DS9+DS10+DS11+DS12 -> 0 | DT16: =DT9+DT10+DT11+DT12 -> 0 | DU16: =DU9+DU10+DU11+DU12 -> 0 | DV16: =DV9+DV10+DV11+DV12 -> 0 | ... EC16: =EC9+EC10+EC11+EC12 -> 0 | ED16: MKSP | EF16: =VLOOKUP(J16,MATERIAL,9,FALSE()) -> 0 | EG16: =VLOOKUP(K16,MATERIAL,9,FALSE()) -> 0 | EH16: =VLOOKUP(L16,MATERIAL,9,FALSE()) -> 0 | EI16: =VLOOKUP(M16,MATERIAL,9,FALSE()) -> 0 | EJ16: =VLOOKUP(N16,MATERIAL,9,FALSE()) -> 0 | EK16: =VLOOKUP(O16,MATERIAL,9,FALSE()) -> 0 | EL16: =VLOOKUP(P16,MATERIAL,9,FALSE()) -> 0 | EM16: =VLOOKUP(Q16,MATERIAL,9,FALSE()) -> 0 | ... ET16: =VLOOKUP(X16,MATERIAL,9,FALSE()) -> 0 | EU16: =IF($B16="",0,VLOOKUP($B16,ITEMS,EU$2,FALSE())) -> 0 | EV16: =VLOOKUP(EU16,MWS,2) -> 0 | EW16: =VLOOKUP(EU16,MWS,3) -> 0
A17: =EV17 -> 0 | C17: Tx | D17: =AK1 -> 4 | E17: =AZ1 -> 4 | F17: =BO1 -> 2 | G17: =CD1 -> 5 | H17: =MAX(EN5:EN32) -> 0 | J17: =IF($B17="",0,VLOOKUP($B17,ITEMS,J$2,FALSE())) -> 0 | K17: =IF($B17="",0,VLOOKUP($B17,ITEMS,K$2,FALSE())) -> 0 | L17: =IF($B17="",0,VLOOKUP($B17,ITEMS,L$2,FALSE())) -> 0 | M17: =IF($B17="",0,VLOOKUP($B17,ITEMS,M$2,FALSE())) -> 0 | N17: =IF($B17="",0,VLOOKUP($B17,ITEMS,N$2,FALSE())) -> 0 | O17: =IF($B17="",0,VLOOKUP($B17,ITEMS,O$2,FALSE())) -> 0 | P17: =IF($B17="",0,VLOOKUP($B17,ITEMS,P$2,FALSE())) -> 0 | Q17: =IF($B17="",0,VLOOKUP($B17,ITEMS,Q$2,FALSE())) -> 0 | ... X17: =IF($B17="",0,VLOOKUP($B17,ITEMS,X$2,FALSE())) -> 0 | Y17: =IF($B17="",0,VLOOKUP($B17,ITEMS,17,FALSE())) -> 0 | Z17: =IF($B17="",0,VLOOKUP($B17,ITEMS,18,FALSE())) -> 0 | AA17: =IF($B17="",0,VLOOKUP($B17,ITEMS,19,FALSE())) -> 0 | AB17: =IF($B17="",0,VLOOKUP($B17,ITEMS,20,FALSE())) -> 0 | AC17: =VLOOKUP(J17,MATERIAL,5,FALSE())+IF(J17=0,0,$EW17) -> 0 | AD17: =VLOOKUP(K17,MATERIAL,5,FALSE())+IF(K17=0,0,$EW17) -> 0 | AE17: =VLOOKUP(L17,MATERIAL,5,FALSE())+IF(L17=0,0,$EW17) -> 0 | AF17: =VLOOKUP(M17,MATERIAL,5,FALSE())+IF(M17=0,0,$EW17) -> 0 | AG17: =VLOOKUP(N17,MATERIAL,5,FALSE())+IF(N17=0,0,$EW17) -> 0 | AH17: =VLOOKUP(O17,MATERIAL,5,FALSE())+IF(O17=0,0,$EW17) -> 0 | AI17: =VLOOKUP(P17,MATERIAL,5,FALSE())+IF(P17=0,0,$EW17) -> 0 | AJ17: =VLOOKUP(Q17,MATERIAL,5,FALSE())+IF(Q17=0,0,$EW17) -> 0 | ... AQ17: =VLOOKUP(X17,MATERIAL,5,FALSE())+IF(X17=0,0,$EW17) -> 0 | AR17: =VLOOKUP(J17,MATERIAL,6,FALSE())+IF(J17=0,0,$EW17) -> 0 | AS17: =VLOOKUP(K17,MATERIAL,6,FALSE())+IF(K17=0,0,$EW17) -> 0 | AT17: =VLOOKUP(L17,MATERIAL,6,FALSE())+IF(L17=0,0,$EW17) -> 0 | AU17: =VLOOKUP(M17,MATERIAL,6,FALSE())+IF(M17=0,0,$EW17) -> 0 | AV17: =VLOOKUP(N17,MATERIAL,6,FALSE())+IF(N17=0,0,$EW17) -> 0 | AW17: =VLOOKUP(O17,MATERIAL,6,FALSE())+IF(O17=0,0,$EW17) -> 0 | AX17: =VLOOKUP(P17,MATERIAL,6,FALSE())+IF(P17=0,0,$EW17) -> 0 | AY17: =VLOOKUP(Q17,MATERIAL,6,FALSE())+IF(Q17=0,0,$EW17) -> 0 | ... BF17: =VLOOKUP(X17,MATERIAL,6,FALSE())+IF(X17=0,0,$EW17) -> 0 | BG17: =VLOOKUP(J17,MATERIAL,7,FALSE())+IF(J17=0,0,$EW17) -> 0 | BH17: =VLOOKUP(K17,MATERIAL,7,FALSE())+IF(K17=0,0,$EW17) -> 0 | BI17: =VLOOKUP(L17,MATERIAL,7,FALSE())+IF(L17=0,0,$EW17) -> 0 | BJ17: =VLOOKUP(M17,MATERIAL,7,FALSE())+IF(M17=0,0,$EW17) -> 0 | BK17: =VLOOKUP(N17,MATERIAL,7,FALSE())+IF(N17=0,0,$EW17) -> 0 | BL17: =VLOOKUP(O17,MATERIAL,7,FALSE())+IF(O17=0,0,$EW17) -> 0 | BM17: =VLOOKUP(P17,MATERIAL,7,FALSE())+IF(P17=0,0,$EW17) -> 0 | BN17: =VLOOKUP(Q17,MATERIAL,7,FALSE())+IF(Q17=0,0,$EW17) -> 0 | ... BU17: =VLOOKUP(X17,MATERIAL,7,FALSE())+IF(X17=0,0,$EW17) -> 0 | BV17: =VLOOKUP(J17,MATERIAL,8,FALSE())+IF(J17=0,0,$EW17) -> 0 | BW17: =VLOOKUP(K17,MATERIAL,8,FALSE())+IF(K17=0,0,$EW17) -> 0 | BX17: =VLOOKUP(L17,MATERIAL,8,FALSE())+IF(L17=0,0,$EW17) -> 0 | BY17: =VLOOKUP(M17,MATERIAL,8,FALSE())+IF(M17=0,0,$EW17) -> 0 | BZ17: =VLOOKUP(N17,MATERIAL,8,FALSE())+IF(N17=0,0,$EW17) -> 0 | CA17: =VLOOKUP(O17,MATERIAL,8,FALSE())+IF(O17=0,0,$EW17) -> 0 | CB17: =VLOOKUP(P17,MATERIAL,8,FALSE())+IF(P17=0,0,$EW17) -> 0 | CC17: =VLOOKUP(Q17,MATERIAL,8,FALSE())+IF(Q17=0,0,$EW17) -> 0 | ... CJ17: =VLOOKUP(X17,MATERIAL,8,FALSE())+IF(X17=0,0,$EW17) -> 0 | CK17: =VLOOKUP(J17,MATERIAL,4,FALSE()) -> 0 | CL17: =VLOOKUP(K17,MATERIAL,4,FALSE()) -> 0 | CM17: =VLOOKUP(L17,MATERIAL,4,FALSE()) -> 0 | CN17: =VLOOKUP(M17,MATERIAL,4,FALSE()) -> 0 | CO17: =VLOOKUP(N17,MATERIAL,4,FALSE()) -> 0 | CP17: =VLOOKUP(O17,MATERIAL,4,FALSE()) -> 0 | CQ17: =VLOOKUP(P17,MATERIAL,4,FALSE()) -> 0 | CR17: =VLOOKUP(Q17,MATERIAL,4,FALSE()) -> 0 | ... CY17: =VLOOKUP(X17,MATERIAL,4,FALSE()) -> 0 | CZ17: =IF(J17=0,0,LEFT(J17,1)) -> 0 | DA17: =IF(K17=0,0,LEFT(K17,1)) -> 0 | DB17: =IF(L17=0,0,LEFT(L17,1)) -> 0 | DC17: =IF(M17=0,0,LEFT(M17,1)) -> 0 | DD17: =IF(N17=0,0,LEFT(N17,1)) -> 0 | DE17: =IF(O17=0,0,LEFT(O17,1)) -> 0 | DF17: =IF(P17=0,0,LEFT(P17,1)) -> 0 | DG17: =IF(Q17=0,0,LEFT(Q17,1)) -> 0 | ... DN17: =IF(X17=0,0,LEFT(X17,1)) -> 0 | DO17: =DO6/2+DO7/3+DO8+DO9+DO10+DO12 -> 1 | DP17: =DP6/2+DP7/3+DP8+DP9+DP10+DP12 -> 0 | DQ17: =DQ6/2+DQ7/3+DQ8+DQ9+DQ10+DQ12 -> 0 | DR17: =DR6/2+DR7/3+DR8+DR9+DR10+DR12 -> 1 | DS17: =DS6/2+DS7/3+DS8+DS9+DS10+DS12 -> 1 | DT17: =DT6/2+DT7/3+DT8+DT9+DT10+DT12 -> 1 | DU17: =DU6/2+DU7/3+DU8+DU9+DU10+DU12 -> 1 | DV17: =DV6/2+DV7/3+DV8+DV9+DV10+DV12 -> 0 | ... EC17: =EC6/2+EC7/3+EC8+EC9+EC10+EC12 -> 1 | ED17: QGLKSP | EE17: Head | EF17: =VLOOKUP(J17,MATERIAL,9,FALSE()) -> 0 | EG17: =VLOOKUP(K17,MATERIAL,9,FALSE()) -> 0 | EH17: =VLOOKUP(L17,MATERIAL,9,FALSE()) -> 0 | EI17: =VLOOKUP(M17,MATERIAL,9,FALSE()) -> 0 | EJ17: =VLOOKUP(N17,MATERIAL,9,FALSE()) -> 0 | EK17: =VLOOKUP(O17,MATERIAL,9,FALSE()) -> 0 | EL17: =VLOOKUP(P17,MATERIAL,9,FALSE()) -> 0 | EM17: =VLOOKUP(Q17,MATERIAL,9,FALSE()) -> 0 | ... ET17: =VLOOKUP(X17,MATERIAL,9,FALSE()) -> 0 | EU17: =IF($B17="",0,VLOOKUP($B17,ITEMS,EU$2,FALSE())) -> 0 | EV17: =VLOOKUP(EU17,MWS,2) -> 0 | EW17: =VLOOKUP(EU17,MWS,3) -> 0
A18: =EV18 -> 0 | C18: Ab | D18: =AL1 -> 4 | E18: =BA1 -> 4 | F18: =BP1 -> 2 | G18: =CE1 -> 5 | H18: =MAX(EO5:EO32) -> 0 | J18: =IF($B18="",0,VLOOKUP($B18,ITEMS,J$2,FALSE())) -> 0 | K18: =IF($B18="",0,VLOOKUP($B18,ITEMS,K$2,FALSE())) -> 0 | L18: =IF($B18="",0,VLOOKUP($B18,ITEMS,L$2,FALSE())) -> 0 | M18: =IF($B18="",0,VLOOKUP($B18,ITEMS,M$2,FALSE())) -> 0 | N18: =IF($B18="",0,VLOOKUP($B18,ITEMS,N$2,FALSE())) -> 0 | O18: =IF($B18="",0,VLOOKUP($B18,ITEMS,O$2,FALSE())) -> 0 | P18: =IF($B18="",0,VLOOKUP($B18,ITEMS,P$2,FALSE())) -> 0 | Q18: =IF($B18="",0,VLOOKUP($B18,ITEMS,Q$2,FALSE())) -> 0 | ... X18: =IF($B18="",0,VLOOKUP($B18,ITEMS,X$2,FALSE())) -> 0 | Y18: =IF($B18="",0,VLOOKUP($B18,ITEMS,17,FALSE())) -> 0 | Z18: =IF($B18="",0,VLOOKUP($B18,ITEMS,18,FALSE())) -> 0 | AA18: =IF($B18="",0,VLOOKUP($B18,ITEMS,19,FALSE())) -> 0 | AB18: =IF($B18="",0,VLOOKUP($B18,ITEMS,20,FALSE())) -> 0 | AC18: =VLOOKUP(J18,MATERIAL,5,FALSE())+IF(J18=0,0,$EW18) -> 0 | AD18: =VLOOKUP(K18,MATERIAL,5,FALSE())+IF(K18=0,0,$EW18) -> 0 | AE18: =VLOOKUP(L18,MATERIAL,5,FALSE())+IF(L18=0,0,$EW18) -> 0 | AF18: =VLOOKUP(M18,MATERIAL,5,FALSE())+IF(M18=0,0,$EW18) -> 0 | AG18: =VLOOKUP(N18,MATERIAL,5,FALSE())+IF(N18=0,0,$EW18) -> 0 | AH18: =VLOOKUP(O18,MATERIAL,5,FALSE())+IF(O18=0,0,$EW18) -> 0 | AI18: =VLOOKUP(P18,MATERIAL,5,FALSE())+IF(P18=0,0,$EW18) -> 0 | AJ18: =VLOOKUP(Q18,MATERIAL,5,FALSE())+IF(Q18=0,0,$EW18) -> 0 | ... AQ18: =VLOOKUP(X18,MATERIAL,5,FALSE())+IF(X18=0,0,$EW18) -> 0 | AR18: =VLOOKUP(J18,MATERIAL,6,FALSE())+IF(J18=0,0,$EW18) -> 0 | AS18: =VLOOKUP(K18,MATERIAL,6,FALSE())+IF(K18=0,0,$EW18) -> 0 | AT18: =VLOOKUP(L18,MATERIAL,6,FALSE())+IF(L18=0,0,$EW18) -> 0 | AU18: =VLOOKUP(M18,MATERIAL,6,FALSE())+IF(M18=0,0,$EW18) -> 0 | AV18: =VLOOKUP(N18,MATERIAL,6,FALSE())+IF(N18=0,0,$EW18) -> 0 | AW18: =VLOOKUP(O18,MATERIAL,6,FALSE())+IF(O18=0,0,$EW18) -> 0 | AX18: =VLOOKUP(P18,MATERIAL,6,FALSE())+IF(P18=0,0,$EW18) -> 0 | AY18: =VLOOKUP(Q18,MATERIAL,6,FALSE())+IF(Q18=0,0,$EW18) -> 0 | ... BF18: =VLOOKUP(X18,MATERIAL,6,FALSE())+IF(X18=0,0,$EW18) -> 0 | BG18: =VLOOKUP(J18,MATERIAL,7,FALSE())+IF(J18=0,0,$EW18) -> 0 | BH18: =VLOOKUP(K18,MATERIAL,7,FALSE())+IF(K18=0,0,$EW18) -> 0 | BI18: =VLOOKUP(L18,MATERIAL,7,FALSE())+IF(L18=0,0,$EW18) -> 0 | BJ18: =VLOOKUP(M18,MATERIAL,7,FALSE())+IF(M18=0,0,$EW18) -> 0 | BK18: =VLOOKUP(N18,MATERIAL,7,FALSE())+IF(N18=0,0,$EW18) -> 0 | BL18: =VLOOKUP(O18,MATERIAL,7,FALSE())+IF(O18=0,0,$EW18) -> 0 | BM18: =VLOOKUP(P18,MATERIAL,7,FALSE())+IF(P18=0,0,$EW18) -> 0 | BN18: =VLOOKUP(Q18,MATERIAL,7,FALSE())+IF(Q18=0,0,$EW18) -> 0 | ... BU18: =VLOOKUP(X18,MATERIAL,7,FALSE())+IF(X18=0,0,$EW18) -> 0 | BV18: =VLOOKUP(J18,MATERIAL,8,FALSE())+IF(J18=0,0,$EW18) -> 0 | BW18: =VLOOKUP(K18,MATERIAL,8,FALSE())+IF(K18=0,0,$EW18) -> 0 | BX18: =VLOOKUP(L18,MATERIAL,8,FALSE())+IF(L18=0,0,$EW18) -> 0 | BY18: =VLOOKUP(M18,MATERIAL,8,FALSE())+IF(M18=0,0,$EW18) -> 0 | BZ18: =VLOOKUP(N18,MATERIAL,8,FALSE())+IF(N18=0,0,$EW18) -> 0 | CA18: =VLOOKUP(O18,MATERIAL,8,FALSE())+IF(O18=0,0,$EW18) -> 0 | CB18: =VLOOKUP(P18,MATERIAL,8,FALSE())+IF(P18=0,0,$EW18) -> 0 | CC18: =VLOOKUP(Q18,MATERIAL,8,FALSE())+IF(Q18=0,0,$EW18) -> 0 | ... CJ18: =VLOOKUP(X18,MATERIAL,8,FALSE())+IF(X18=0,0,$EW18) -> 0 | CK18: =VLOOKUP(J18,MATERIAL,4,FALSE()) -> 0 | CL18: =VLOOKUP(K18,MATERIAL,4,FALSE()) -> 0 | CM18: =VLOOKUP(L18,MATERIAL,4,FALSE()) -> 0 | CN18: =VLOOKUP(M18,MATERIAL,4,FALSE()) -> 0 | CO18: =VLOOKUP(N18,MATERIAL,4,FALSE()) -> 0 | CP18: =VLOOKUP(O18,MATERIAL,4,FALSE()) -> 0 | CQ18: =VLOOKUP(P18,MATERIAL,4,FALSE()) -> 0 | CR18: =VLOOKUP(Q18,MATERIAL,4,FALSE()) -> 0 | ... CY18: =VLOOKUP(X18,MATERIAL,4,FALSE()) -> 0 | CZ18: =IF(J18=0,0,LEFT(J18,1)) -> 0 | DA18: =IF(K18=0,0,LEFT(K18,1)) -> 0 | DB18: =IF(L18=0,0,LEFT(L18,1)) -> 0 | DC18: =IF(M18=0,0,LEFT(M18,1)) -> 0 | DD18: =IF(N18=0,0,LEFT(N18,1)) -> 0 | DE18: =IF(O18=0,0,LEFT(O18,1)) -> 0 | DF18: =IF(P18=0,0,LEFT(P18,1)) -> 0 | DG18: =IF(Q18=0,0,LEFT(Q18,1)) -> 0 | ... DN18: =IF(X18=0,0,LEFT(X18,1)) -> 0 | DO18: =DO6/2+DO7/3+DO8 -> 0 | DP18: =DP6/2+DP7/3+DP8 -> 0 | DQ18: =DQ6/2+DQ7/3+DQ8 -> 0 | DR18: =DR6/2+DR7/3+DR8 -> 1 | DS18: =DS6/2+DS7/3+DS8 -> 1 | DT18: =DT6/2+DT7/3+DT8 -> 1 | DU18: =DU6/2+DU7/3+DU8 -> 1 | DV18: =DV6/2+DV7/3+DV8 -> 0 | ... EC18: =EC6/2+EC7/3+EC8 -> 1 | ED18: QGL | EE18: Torso & Arms | EF18: =VLOOKUP(J18,MATERIAL,9,FALSE()) -> 0 | EG18: =VLOOKUP(K18,MATERIAL,9,FALSE()) -> 0 | EH18: =VLOOKUP(L18,MATERIAL,9,FALSE()) -> 0 | EI18: =VLOOKUP(M18,MATERIAL,9,FALSE()) -> 0 | EJ18: =VLOOKUP(N18,MATERIAL,9,FALSE()) -> 0 | EK18: =VLOOKUP(O18,MATERIAL,9,FALSE()) -> 0 | EL18: =VLOOKUP(P18,MATERIAL,9,FALSE()) -> 0 | EM18: =VLOOKUP(Q18,MATERIAL,9,FALSE()) -> 0 | ... ET18: =VLOOKUP(X18,MATERIAL,9,FALSE()) -> 0 | EU18: =IF($B18="",0,VLOOKUP($B18,ITEMS,EU$2,FALSE())) -> 0 | EV18: =VLOOKUP(EU18,MWS,2) -> 0 | EW18: =VLOOKUP(EU18,MWS,3) -> 0
A19: =EV19 -> 0 | C19: Pv | D19: =AM1 -> 4 | E19: =BB1 -> 5 | F19: =BQ1 -> 2 | G19: =CF1 -> 6 | H19: =MAX(EP5:EP32) -> 0 | J19: =IF($B19="",0,VLOOKUP($B19,ITEMS,J$2,FALSE())) -> 0 | K19: =IF($B19="",0,VLOOKUP($B19,ITEMS,K$2,FALSE())) -> 0 | L19: =IF($B19="",0,VLOOKUP($B19,ITEMS,L$2,FALSE())) -> 0 | M19: =IF($B19="",0,VLOOKUP($B19,ITEMS,M$2,FALSE())) -> 0 | N19: =IF($B19="",0,VLOOKUP($B19,ITEMS,N$2,FALSE())) -> 0 | O19: =IF($B19="",0,VLOOKUP($B19,ITEMS,O$2,FALSE())) -> 0 | P19: =IF($B19="",0,VLOOKUP($B19,ITEMS,P$2,FALSE())) -> 0 | Q19: =IF($B19="",0,VLOOKUP($B19,ITEMS,Q$2,FALSE())) -> 0 | ... X19: =IF($B19="",0,VLOOKUP($B19,ITEMS,X$2,FALSE())) -> 0 | Y19: =IF($B19="",0,VLOOKUP($B19,ITEMS,17,FALSE())) -> 0 | Z19: =IF($B19="",0,VLOOKUP($B19,ITEMS,18,FALSE())) -> 0 | AA19: =IF($B19="",0,VLOOKUP($B19,ITEMS,19,FALSE())) -> 0 | AB19: =IF($B19="",0,VLOOKUP($B19,ITEMS,20,FALSE())) -> 0 | AC19: =VLOOKUP(J19,MATERIAL,5,FALSE())+IF(J19=0,0,$EW19) -> 0 | AD19: =VLOOKUP(K19,MATERIAL,5,FALSE())+IF(K19=0,0,$EW19) -> 0 | AE19: =VLOOKUP(L19,MATERIAL,5,FALSE())+IF(L19=0,0,$EW19) -> 0 | AF19: =VLOOKUP(M19,MATERIAL,5,FALSE())+IF(M19=0,0,$EW19) -> 0 | AG19: =VLOOKUP(N19,MATERIAL,5,FALSE())+IF(N19=0,0,$EW19) -> 0 | AH19: =VLOOKUP(O19,MATERIAL,5,FALSE())+IF(O19=0,0,$EW19) -> 0 | AI19: =VLOOKUP(P19,MATERIAL,5,FALSE())+IF(P19=0,0,$EW19) -> 0 | AJ19: =VLOOKUP(Q19,MATERIAL,5,FALSE())+IF(Q19=0,0,$EW19) -> 0 | ... AQ19: =VLOOKUP(X19,MATERIAL,5,FALSE())+IF(X19=0,0,$EW19) -> 0 | AR19: =VLOOKUP(J19,MATERIAL,6,FALSE())+IF(J19=0,0,$EW19) -> 0 | AS19: =VLOOKUP(K19,MATERIAL,6,FALSE())+IF(K19=0,0,$EW19) -> 0 | AT19: =VLOOKUP(L19,MATERIAL,6,FALSE())+IF(L19=0,0,$EW19) -> 0 | AU19: =VLOOKUP(M19,MATERIAL,6,FALSE())+IF(M19=0,0,$EW19) -> 0 | AV19: =VLOOKUP(N19,MATERIAL,6,FALSE())+IF(N19=0,0,$EW19) -> 0 | AW19: =VLOOKUP(O19,MATERIAL,6,FALSE())+IF(O19=0,0,$EW19) -> 0 | AX19: =VLOOKUP(P19,MATERIAL,6,FALSE())+IF(P19=0,0,$EW19) -> 0 | AY19: =VLOOKUP(Q19,MATERIAL,6,FALSE())+IF(Q19=0,0,$EW19) -> 0 | ... BF19: =VLOOKUP(X19,MATERIAL,6,FALSE())+IF(X19=0,0,$EW19) -> 0 | BG19: =VLOOKUP(J19,MATERIAL,7,FALSE())+IF(J19=0,0,$EW19) -> 0 | BH19: =VLOOKUP(K19,MATERIAL,7,FALSE())+IF(K19=0,0,$EW19) -> 0 | BI19: =VLOOKUP(L19,MATERIAL,7,FALSE())+IF(L19=0,0,$EW19) -> 0 | BJ19: =VLOOKUP(M19,MATERIAL,7,FALSE())+IF(M19=0,0,$EW19) -> 0 | BK19: =VLOOKUP(N19,MATERIAL,7,FALSE())+IF(N19=0,0,$EW19) -> 0 | BL19: =VLOOKUP(O19,MATERIAL,7,FALSE())+IF(O19=0,0,$EW19) -> 0 | BM19: =VLOOKUP(P19,MATERIAL,7,FALSE())+IF(P19=0,0,$EW19) -> 0 | BN19: =VLOOKUP(Q19,MATERIAL,7,FALSE())+IF(Q19=0,0,$EW19) -> 0 | ... BU19: =VLOOKUP(X19,MATERIAL,7,FALSE())+IF(X19=0,0,$EW19) -> 0 | BV19: =VLOOKUP(J19,MATERIAL,8,FALSE())+IF(J19=0,0,$EW19) -> 0 | BW19: =VLOOKUP(K19,MATERIAL,8,FALSE())+IF(K19=0,0,$EW19) -> 0 | BX19: =VLOOKUP(L19,MATERIAL,8,FALSE())+IF(L19=0,0,$EW19) -> 0 | BY19: =VLOOKUP(M19,MATERIAL,8,FALSE())+IF(M19=0,0,$EW19) -> 0 | BZ19: =VLOOKUP(N19,MATERIAL,8,FALSE())+IF(N19=0,0,$EW19) -> 0 | CA19: =VLOOKUP(O19,MATERIAL,8,FALSE())+IF(O19=0,0,$EW19) -> 0 | CB19: =VLOOKUP(P19,MATERIAL,8,FALSE())+IF(P19=0,0,$EW19) -> 0 | CC19: =VLOOKUP(Q19,MATERIAL,8,FALSE())+IF(Q19=0,0,$EW19) -> 0 | ... CJ19: =VLOOKUP(X19,MATERIAL,8,FALSE())+IF(X19=0,0,$EW19) -> 0 | CK19: =VLOOKUP(J19,MATERIAL,4,FALSE()) -> 0 | CL19: =VLOOKUP(K19,MATERIAL,4,FALSE()) -> 0 | CM19: =VLOOKUP(L19,MATERIAL,4,FALSE()) -> 0 | CN19: =VLOOKUP(M19,MATERIAL,4,FALSE()) -> 0 | CO19: =VLOOKUP(N19,MATERIAL,4,FALSE()) -> 0 | CP19: =VLOOKUP(O19,MATERIAL,4,FALSE()) -> 0 | CQ19: =VLOOKUP(P19,MATERIAL,4,FALSE()) -> 0 | CR19: =VLOOKUP(Q19,MATERIAL,4,FALSE()) -> 0 | ... CY19: =VLOOKUP(X19,MATERIAL,4,FALSE()) -> 0 | CZ19: =IF(J19=0,0,LEFT(J19,1)) -> 0 | DA19: =IF(K19=0,0,LEFT(K19,1)) -> 0 | DB19: =IF(L19=0,0,LEFT(L19,1)) -> 0 | DC19: =IF(M19=0,0,LEFT(M19,1)) -> 0 | DD19: =IF(N19=0,0,LEFT(N19,1)) -> 0 | DE19: =IF(O19=0,0,LEFT(O19,1)) -> 0 | DF19: =IF(P19=0,0,LEFT(P19,1)) -> 0 | DG19: =IF(Q19=0,0,LEFT(Q19,1)) -> 0 | ... DN19: =IF(X19=0,0,LEFT(X19,1)) -> 0 | DO19: =DO6/2+DO7/3+DO8+DO10 -> 0 | DP19: =DP6/2+DP7/3+DP8+DP10 -> 0 | DQ19: =DQ6/2+DQ7/3+DQ8+DQ10 -> 0 | DR19: =DR6/2+DR7/3+DR8+DR10 -> 1 | DS19: =DS6/2+DS7/3+DS8+DS10 -> 1 | DT19: =DT6/2+DT7/3+DT8+DT10 -> 1 | DU19: =DU6/2+DU7/3+DU8+DU10 -> 1 | DV19: =DV6/2+DV7/3+DV8+DV10 -> 0 | ... EC19: =EC6/2+EC7/3+EC8+EC10 -> 1 | ED19: QGLS | EE19: Legs | EF19: =VLOOKUP(J19,MATERIAL,9,FALSE()) -> 0 | EG19: =VLOOKUP(K19,MATERIAL,9,FALSE()) -> 0 | EH19: =VLOOKUP(L19,MATERIAL,9,FALSE()) -> 0 | EI19: =VLOOKUP(M19,MATERIAL,9,FALSE()) -> 0 | EJ19: =VLOOKUP(N19,MATERIAL,9,FALSE()) -> 0 | EK19: =VLOOKUP(O19,MATERIAL,9,FALSE()) -> 0 | EL19: =VLOOKUP(P19,MATERIAL,9,FALSE()) -> 0 | EM19: =VLOOKUP(Q19,MATERIAL,9,FALSE()) -> 0 | ... ET19: =VLOOKUP(X19,MATERIAL,9,FALSE()) -> 0 | EU19: =IF($B19="",0,VLOOKUP($B19,ITEMS,EU$2,FALSE())) -> 0 | EV19: =VLOOKUP(EU19,MWS,2) -> 0 | EW19: =VLOOKUP(EU19,MWS,3) -> 0
A20: =EV20 -> 0 | C20: Th | D20: =AN1 -> 4 | E20: =BC1 -> 5 | F20: =BR1 -> 2 | G20: =CG1 -> 6 | H20: =MAX(EQ5:EQ32) -> 0 | J20: =IF($B20="",0,VLOOKUP($B20,ITEMS,J$2,FALSE())) -> 0 | K20: =IF($B20="",0,VLOOKUP($B20,ITEMS,K$2,FALSE())) -> 0 | L20: =IF($B20="",0,VLOOKUP($B20,ITEMS,L$2,FALSE())) -> 0 | M20: =IF($B20="",0,VLOOKUP($B20,ITEMS,M$2,FALSE())) -> 0 | N20: =IF($B20="",0,VLOOKUP($B20,ITEMS,N$2,FALSE())) -> 0 | O20: =IF($B20="",0,VLOOKUP($B20,ITEMS,O$2,FALSE())) -> 0 | P20: =IF($B20="",0,VLOOKUP($B20,ITEMS,P$2,FALSE())) -> 0 | Q20: =IF($B20="",0,VLOOKUP($B20,ITEMS,Q$2,FALSE())) -> 0 | ... X20: =IF($B20="",0,VLOOKUP($B20,ITEMS,X$2,FALSE())) -> 0 | Y20: =IF($B20="",0,VLOOKUP($B20,ITEMS,17,FALSE())) -> 0 | Z20: =IF($B20="",0,VLOOKUP($B20,ITEMS,18,FALSE())) -> 0 | AA20: =IF($B20="",0,VLOOKUP($B20,ITEMS,19,FALSE())) -> 0 | AB20: =IF($B20="",0,VLOOKUP($B20,ITEMS,20,FALSE())) -> 0 | AC20: =VLOOKUP(J20,MATERIAL,5,FALSE())+IF(J20=0,0,$EW20) -> 0 | AD20: =VLOOKUP(K20,MATERIAL,5,FALSE())+IF(K20=0,0,$EW20) -> 0 | AE20: =VLOOKUP(L20,MATERIAL,5,FALSE())+IF(L20=0,0,$EW20) -> 0 | AF20: =VLOOKUP(M20,MATERIAL,5,FALSE())+IF(M20=0,0,$EW20) -> 0 | AG20: =VLOOKUP(N20,MATERIAL,5,FALSE())+IF(N20=0,0,$EW20) -> 0 | AH20: =VLOOKUP(O20,MATERIAL,5,FALSE())+IF(O20=0,0,$EW20) -> 0 | AI20: =VLOOKUP(P20,MATERIAL,5,FALSE())+IF(P20=0,0,$EW20) -> 0 | AJ20: =VLOOKUP(Q20,MATERIAL,5,FALSE())+IF(Q20=0,0,$EW20) -> 0 | ... AQ20: =VLOOKUP(X20,MATERIAL,5,FALSE())+IF(X20=0,0,$EW20) -> 0 | AR20: =VLOOKUP(J20,MATERIAL,6,FALSE())+IF(J20=0,0,$EW20) -> 0 | AS20: =VLOOKUP(K20,MATERIAL,6,FALSE())+IF(K20=0,0,$EW20) -> 0 | AT20: =VLOOKUP(L20,MATERIAL,6,FALSE())+IF(L20=0,0,$EW20) -> 0 | AU20: =VLOOKUP(M20,MATERIAL,6,FALSE())+IF(M20=0,0,$EW20) -> 0 | AV20: =VLOOKUP(N20,MATERIAL,6,FALSE())+IF(N20=0,0,$EW20) -> 0 | AW20: =VLOOKUP(O20,MATERIAL,6,FALSE())+IF(O20=0,0,$EW20) -> 0 | AX20: =VLOOKUP(P20,MATERIAL,6,FALSE())+IF(P20=0,0,$EW20) -> 0 | AY20: =VLOOKUP(Q20,MATERIAL,6,FALSE())+IF(Q20=0,0,$EW20) -> 0 | ... BF20: =VLOOKUP(X20,MATERIAL,6,FALSE())+IF(X20=0,0,$EW20) -> 0 | BG20: =VLOOKUP(J20,MATERIAL,7,FALSE())+IF(J20=0,0,$EW20) -> 0 | BH20: =VLOOKUP(K20,MATERIAL,7,FALSE())+IF(K20=0,0,$EW20) -> 0 | BI20: =VLOOKUP(L20,MATERIAL,7,FALSE())+IF(L20=0,0,$EW20) -> 0 | BJ20: =VLOOKUP(M20,MATERIAL,7,FALSE())+IF(M20=0,0,$EW20) -> 0 | BK20: =VLOOKUP(N20,MATERIAL,7,FALSE())+IF(N20=0,0,$EW20) -> 0 | BL20: =VLOOKUP(O20,MATERIAL,7,FALSE())+IF(O20=0,0,$EW20) -> 0 | BM20: =VLOOKUP(P20,MATERIAL,7,FALSE())+IF(P20=0,0,$EW20) -> 0 | BN20: =VLOOKUP(Q20,MATERIAL,7,FALSE())+IF(Q20=0,0,$EW20) -> 0 | ... BU20: =VLOOKUP(X20,MATERIAL,7,FALSE())+IF(X20=0,0,$EW20) -> 0 | BV20: =VLOOKUP(J20,MATERIAL,8,FALSE())+IF(J20=0,0,$EW20) -> 0 | BW20: =VLOOKUP(K20,MATERIAL,8,FALSE())+IF(K20=0,0,$EW20) -> 0 | BX20: =VLOOKUP(L20,MATERIAL,8,FALSE())+IF(L20=0,0,$EW20) -> 0 | BY20: =VLOOKUP(M20,MATERIAL,8,FALSE())+IF(M20=0,0,$EW20) -> 0 | BZ20: =VLOOKUP(N20,MATERIAL,8,FALSE())+IF(N20=0,0,$EW20) -> 0 | CA20: =VLOOKUP(O20,MATERIAL,8,FALSE())+IF(O20=0,0,$EW20) -> 0 | CB20: =VLOOKUP(P20,MATERIAL,8,FALSE())+IF(P20=0,0,$EW20) -> 0 | CC20: =VLOOKUP(Q20,MATERIAL,8,FALSE())+IF(Q20=0,0,$EW20) -> 0 | ... CJ20: =VLOOKUP(X20,MATERIAL,8,FALSE())+IF(X20=0,0,$EW20) -> 0 | CK20: =VLOOKUP(J20,MATERIAL,4,FALSE()) -> 0 | CL20: =VLOOKUP(K20,MATERIAL,4,FALSE()) -> 0 | CM20: =VLOOKUP(L20,MATERIAL,4,FALSE()) -> 0 | CN20: =VLOOKUP(M20,MATERIAL,4,FALSE()) -> 0 | CO20: =VLOOKUP(N20,MATERIAL,4,FALSE()) -> 0 | CP20: =VLOOKUP(O20,MATERIAL,4,FALSE()) -> 0 | CQ20: =VLOOKUP(P20,MATERIAL,4,FALSE()) -> 0 | CR20: =VLOOKUP(Q20,MATERIAL,4,FALSE()) -> 0 | ... CY20: =VLOOKUP(X20,MATERIAL,4,FALSE()) -> 0 | CZ20: =IF(J20=0,0,LEFT(J20,1)) -> 0 | DA20: =IF(K20=0,0,LEFT(K20,1)) -> 0 | DB20: =IF(L20=0,0,LEFT(L20,1)) -> 0 | DC20: =IF(M20=0,0,LEFT(M20,1)) -> 0 | DD20: =IF(N20=0,0,LEFT(N20,1)) -> 0 | DE20: =IF(O20=0,0,LEFT(O20,1)) -> 0 | DF20: =IF(P20=0,0,LEFT(P20,1)) -> 0 | DG20: =IF(Q20=0,0,LEFT(Q20,1)) -> 0 | ... DN20: =IF(X20=0,0,LEFT(X20,1)) -> 0 | DO20: =DO7/3+DO8+DO9+DO10+DO12 -> 1 | DP20: =DP7/3+DP8+DP9+DP10+DP12 -> 0 | DQ20: =DQ7/3+DQ8+DQ9+DQ10+DQ12 -> 0 | DR20: =DR7/3+DR8+DR9+DR10+DR12 -> 0 | DS20: =DS7/3+DS8+DS9+DS10+DS12 -> 0 | DT20: =DT7/3+DT8+DT9+DT10+DT12 -> 0 | DU20: =DU7/3+DU8+DU9+DU10+DU12 -> 0 | DV20: =DV7/3+DV8+DV9+DV10+DV12 -> 0 | ... EC20: =EC7/3+EC8+EC9+EC10+EC12 -> 1 | ED20: GLKSP | EE20: Torso | EF20: =VLOOKUP(J20,MATERIAL,9,FALSE()) -> 0 | EG20: =VLOOKUP(K20,MATERIAL,9,FALSE()) -> 0 | EH20: =VLOOKUP(L20,MATERIAL,9,FALSE()) -> 0 | EI20: =VLOOKUP(M20,MATERIAL,9,FALSE()) -> 0 | EJ20: =VLOOKUP(N20,MATERIAL,9,FALSE()) -> 0 | EK20: =VLOOKUP(O20,MATERIAL,9,FALSE()) -> 0 | EL20: =VLOOKUP(P20,MATERIAL,9,FALSE()) -> 0 | EM20: =VLOOKUP(Q20,MATERIAL,9,FALSE()) -> 0 | ... ET20: =VLOOKUP(X20,MATERIAL,9,FALSE()) -> 0 | EU20: =IF($B20="",0,VLOOKUP($B20,ITEMS,EU$2,FALSE())) -> 0 | EV20: =VLOOKUP(EU20,MWS,2) -> 0 | EW20: =VLOOKUP(EU20,MWS,3) -> 0
A21: =EV21 -> 0 | C21: Kn | D21: =AO1 -> 0 | E21: =BD1 -> 2 | F21: =BS1 -> 0 | G21: =CH1 -> 3 | H21: =MAX(ER5:ER32) -> 0 | J21: =IF($B21="",0,VLOOKUP($B21,ITEMS,J$2,FALSE())) -> 0 | K21: =IF($B21="",0,VLOOKUP($B21,ITEMS,K$2,FALSE())) -> 0 | L21: =IF($B21="",0,VLOOKUP($B21,ITEMS,L$2,FALSE())) -> 0 | M21: =IF($B21="",0,VLOOKUP($B21,ITEMS,M$2,FALSE())) -> 0 | N21: =IF($B21="",0,VLOOKUP($B21,ITEMS,N$2,FALSE())) -> 0 | O21: =IF($B21="",0,VLOOKUP($B21,ITEMS,O$2,FALSE())) -> 0 | P21: =IF($B21="",0,VLOOKUP($B21,ITEMS,P$2,FALSE())) -> 0 | Q21: =IF($B21="",0,VLOOKUP($B21,ITEMS,Q$2,FALSE())) -> 0 | ... X21: =IF($B21="",0,VLOOKUP($B21,ITEMS,X$2,FALSE())) -> 0 | Y21: =IF($B21="",0,VLOOKUP($B21,ITEMS,17,FALSE())) -> 0 | Z21: =IF($B21="",0,VLOOKUP($B21,ITEMS,18,FALSE())) -> 0 | AA21: =IF($B21="",0,VLOOKUP($B21,ITEMS,19,FALSE())) -> 0 | AB21: =IF($B21="",0,VLOOKUP($B21,ITEMS,20,FALSE())) -> 0 | AC21: =VLOOKUP(J21,MATERIAL,5,FALSE())+IF(J21=0,0,$EW21) -> 0 | AD21: =VLOOKUP(K21,MATERIAL,5,FALSE())+IF(K21=0,0,$EW21) -> 0 | AE21: =VLOOKUP(L21,MATERIAL,5,FALSE())+IF(L21=0,0,$EW21) -> 0 | AF21: =VLOOKUP(M21,MATERIAL,5,FALSE())+IF(M21=0,0,$EW21) -> 0 | AG21: =VLOOKUP(N21,MATERIAL,5,FALSE())+IF(N21=0,0,$EW21) -> 0 | AH21: =VLOOKUP(O21,MATERIAL,5,FALSE())+IF(O21=0,0,$EW21) -> 0 | AI21: =VLOOKUP(P21,MATERIAL,5,FALSE())+IF(P21=0,0,$EW21) -> 0 | AJ21: =VLOOKUP(Q21,MATERIAL,5,FALSE())+IF(Q21=0,0,$EW21) -> 0 | ... AQ21: =VLOOKUP(X21,MATERIAL,5,FALSE())+IF(X21=0,0,$EW21) -> 0 | AR21: =VLOOKUP(J21,MATERIAL,6,FALSE())+IF(J21=0,0,$EW21) -> 0 | AS21: =VLOOKUP(K21,MATERIAL,6,FALSE())+IF(K21=0,0,$EW21) -> 0 | AT21: =VLOOKUP(L21,MATERIAL,6,FALSE())+IF(L21=0,0,$EW21) -> 0 | AU21: =VLOOKUP(M21,MATERIAL,6,FALSE())+IF(M21=0,0,$EW21) -> 0 | AV21: =VLOOKUP(N21,MATERIAL,6,FALSE())+IF(N21=0,0,$EW21) -> 0 | AW21: =VLOOKUP(O21,MATERIAL,6,FALSE())+IF(O21=0,0,$EW21) -> 0 | AX21: =VLOOKUP(P21,MATERIAL,6,FALSE())+IF(P21=0,0,$EW21) -> 0 | AY21: =VLOOKUP(Q21,MATERIAL,6,FALSE())+IF(Q21=0,0,$EW21) -> 0 | ... BF21: =VLOOKUP(X21,MATERIAL,6,FALSE())+IF(X21=0,0,$EW21) -> 0 | BG21: =VLOOKUP(J21,MATERIAL,7,FALSE())+IF(J21=0,0,$EW21) -> 0 | BH21: =VLOOKUP(K21,MATERIAL,7,FALSE())+IF(K21=0,0,$EW21) -> 0 | BI21: =VLOOKUP(L21,MATERIAL,7,FALSE())+IF(L21=0,0,$EW21) -> 0 | BJ21: =VLOOKUP(M21,MATERIAL,7,FALSE())+IF(M21=0,0,$EW21) -> 0 | BK21: =VLOOKUP(N21,MATERIAL,7,FALSE())+IF(N21=0,0,$EW21) -> 0 | BL21: =VLOOKUP(O21,MATERIAL,7,FALSE())+IF(O21=0,0,$EW21) -> 0 | BM21: =VLOOKUP(P21,MATERIAL,7,FALSE())+IF(P21=0,0,$EW21) -> 0 | BN21: =VLOOKUP(Q21,MATERIAL,7,FALSE())+IF(Q21=0,0,$EW21) -> 0 | ... BU21: =VLOOKUP(X21,MATERIAL,7,FALSE())+IF(X21=0,0,$EW21) -> 0 | BV21: =VLOOKUP(J21,MATERIAL,8,FALSE())+IF(J21=0,0,$EW21) -> 0 | BW21: =VLOOKUP(K21,MATERIAL,8,FALSE())+IF(K21=0,0,$EW21) -> 0 | BX21: =VLOOKUP(L21,MATERIAL,8,FALSE())+IF(L21=0,0,$EW21) -> 0 | BY21: =VLOOKUP(M21,MATERIAL,8,FALSE())+IF(M21=0,0,$EW21) -> 0 | BZ21: =VLOOKUP(N21,MATERIAL,8,FALSE())+IF(N21=0,0,$EW21) -> 0 | CA21: =VLOOKUP(O21,MATERIAL,8,FALSE())+IF(O21=0,0,$EW21) -> 0 | CB21: =VLOOKUP(P21,MATERIAL,8,FALSE())+IF(P21=0,0,$EW21) -> 0 | CC21: =VLOOKUP(Q21,MATERIAL,8,FALSE())+IF(Q21=0,0,$EW21) -> 0 | ... CJ21: =VLOOKUP(X21,MATERIAL,8,FALSE())+IF(X21=0,0,$EW21) -> 0 | CK21: =VLOOKUP(J21,MATERIAL,4,FALSE()) -> 0 | CL21: =VLOOKUP(K21,MATERIAL,4,FALSE()) -> 0 | CM21: =VLOOKUP(L21,MATERIAL,4,FALSE()) -> 0 | CN21: =VLOOKUP(M21,MATERIAL,4,FALSE()) -> 0 | CO21: =VLOOKUP(N21,MATERIAL,4,FALSE()) -> 0 | CP21: =VLOOKUP(O21,MATERIAL,4,FALSE()) -> 0 | CQ21: =VLOOKUP(P21,MATERIAL,4,FALSE()) -> 0 | CR21: =VLOOKUP(Q21,MATERIAL,4,FALSE()) -> 0 | ... CY21: =VLOOKUP(X21,MATERIAL,4,FALSE()) -> 0 | CZ21: =IF(J21=0,0,LEFT(J21,1)) -> 0 | DA21: =IF(K21=0,0,LEFT(K21,1)) -> 0 | DB21: =IF(L21=0,0,LEFT(L21,1)) -> 0 | DC21: =IF(M21=0,0,LEFT(M21,1)) -> 0 | DD21: =IF(N21=0,0,LEFT(N21,1)) -> 0 | DE21: =IF(O21=0,0,LEFT(O21,1)) -> 0 | DF21: =IF(P21=0,0,LEFT(P21,1)) -> 0 | DG21: =IF(Q21=0,0,LEFT(Q21,1)) -> 0 | ... DN21: =IF(X21=0,0,LEFT(X21,1)) -> 0 | DO21: =DO7/3+DO8+DO10 -> 0 | DP21: =DP7/3+DP8+DP10 -> 0 | DQ21: =DQ7/3+DQ8+DQ10 -> 0 | DR21: =DR7/3+DR8+DR10 -> 0 | DS21: =DS7/3+DS8+DS10 -> 0 | DT21: =DT7/3+DT8+DT10 -> 0 | DU21: =DU7/3+DU8+DU10 -> 0 | DV21: =DV7/3+DV8+DV10 -> 0 | ... EC21: =EC7/3+EC8+EC10 -> 1 | ED21: SGL | EE21: Arms | EF21: =VLOOKUP(J21,MATERIAL,9,FALSE()) -> 0 | EG21: =VLOOKUP(K21,MATERIAL,9,FALSE()) -> 0 | EH21: =VLOOKUP(L21,MATERIAL,9,FALSE()) -> 0 | EI21: =VLOOKUP(M21,MATERIAL,9,FALSE()) -> 0 | EJ21: =VLOOKUP(N21,MATERIAL,9,FALSE()) -> 0 | EK21: =VLOOKUP(O21,MATERIAL,9,FALSE()) -> 0 | EL21: =VLOOKUP(P21,MATERIAL,9,FALSE()) -> 0 | EM21: =VLOOKUP(Q21,MATERIAL,9,FALSE()) -> 0 | ... ET21: =VLOOKUP(X21,MATERIAL,9,FALSE()) -> 0 | EU21: =IF($B21="",0,VLOOKUP($B21,ITEMS,EU$2,FALSE())) -> 0 | EV21: =VLOOKUP(EU21,MWS,2) -> 0 | EW21: =VLOOKUP(EU21,MWS,3) -> 0
A22: =EV22 -> 0 | C22: Cf | D22: =AP1 -> 0 | E22: =BE1 -> 1 | F22: =BT1 -> 0 | G22: =CI1 -> 2 | H22: =MAX(ES5:ES32) -> 0 | J22: =IF($B22="",0,VLOOKUP($B22,ITEMS,J$2,FALSE())) -> 0 | K22: =IF($B22="",0,VLOOKUP($B22,ITEMS,K$2,FALSE())) -> 0 | L22: =IF($B22="",0,VLOOKUP($B22,ITEMS,L$2,FALSE())) -> 0 | M22: =IF($B22="",0,VLOOKUP($B22,ITEMS,M$2,FALSE())) -> 0 | N22: =IF($B22="",0,VLOOKUP($B22,ITEMS,N$2,FALSE())) -> 0 | O22: =IF($B22="",0,VLOOKUP($B22,ITEMS,O$2,FALSE())) -> 0 | P22: =IF($B22="",0,VLOOKUP($B22,ITEMS,P$2,FALSE())) -> 0 | Q22: =IF($B22="",0,VLOOKUP($B22,ITEMS,Q$2,FALSE())) -> 0 | ... X22: =IF($B22="",0,VLOOKUP($B22,ITEMS,X$2,FALSE())) -> 0 | Y22: =IF($B22="",0,VLOOKUP($B22,ITEMS,17,FALSE())) -> 0 | Z22: =IF($B22="",0,VLOOKUP($B22,ITEMS,18,FALSE())) -> 0 | AA22: =IF($B22="",0,VLOOKUP($B22,ITEMS,19,FALSE())) -> 0 | AB22: =IF($B22="",0,VLOOKUP($B22,ITEMS,20,FALSE())) -> 0 | AC22: =VLOOKUP(J22,MATERIAL,5,FALSE())+IF(J22=0,0,$EW22) -> 0 | AD22: =VLOOKUP(K22,MATERIAL,5,FALSE())+IF(K22=0,0,$EW22) -> 0 | AE22: =VLOOKUP(L22,MATERIAL,5,FALSE())+IF(L22=0,0,$EW22) -> 0 | AF22: =VLOOKUP(M22,MATERIAL,5,FALSE())+IF(M22=0,0,$EW22) -> 0 | AG22: =VLOOKUP(N22,MATERIAL,5,FALSE())+IF(N22=0,0,$EW22) -> 0 | AH22: =VLOOKUP(O22,MATERIAL,5,FALSE())+IF(O22=0,0,$EW22) -> 0 | AI22: =VLOOKUP(P22,MATERIAL,5,FALSE())+IF(P22=0,0,$EW22) -> 0 | AJ22: =VLOOKUP(Q22,MATERIAL,5,FALSE())+IF(Q22=0,0,$EW22) -> 0 | ... AQ22: =VLOOKUP(X22,MATERIAL,5,FALSE())+IF(X22=0,0,$EW22) -> 0 | AR22: =VLOOKUP(J22,MATERIAL,6,FALSE())+IF(J22=0,0,$EW22) -> 0 | AS22: =VLOOKUP(K22,MATERIAL,6,FALSE())+IF(K22=0,0,$EW22) -> 0 | AT22: =VLOOKUP(L22,MATERIAL,6,FALSE())+IF(L22=0,0,$EW22) -> 0 | AU22: =VLOOKUP(M22,MATERIAL,6,FALSE())+IF(M22=0,0,$EW22) -> 0 | AV22: =VLOOKUP(N22,MATERIAL,6,FALSE())+IF(N22=0,0,$EW22) -> 0 | AW22: =VLOOKUP(O22,MATERIAL,6,FALSE())+IF(O22=0,0,$EW22) -> 0 | AX22: =VLOOKUP(P22,MATERIAL,6,FALSE())+IF(P22=0,0,$EW22) -> 0 | AY22: =VLOOKUP(Q22,MATERIAL,6,FALSE())+IF(Q22=0,0,$EW22) -> 0 | ... BF22: =VLOOKUP(X22,MATERIAL,6,FALSE())+IF(X22=0,0,$EW22) -> 0 | BG22: =VLOOKUP(J22,MATERIAL,7,FALSE())+IF(J22=0,0,$EW22) -> 0 | BH22: =VLOOKUP(K22,MATERIAL,7,FALSE())+IF(K22=0,0,$EW22) -> 0 | BI22: =VLOOKUP(L22,MATERIAL,7,FALSE())+IF(L22=0,0,$EW22) -> 0 | BJ22: =VLOOKUP(M22,MATERIAL,7,FALSE())+IF(M22=0,0,$EW22) -> 0 | BK22: =VLOOKUP(N22,MATERIAL,7,FALSE())+IF(N22=0,0,$EW22) -> 0 | BL22: =VLOOKUP(O22,MATERIAL,7,FALSE())+IF(O22=0,0,$EW22) -> 0 | BM22: =VLOOKUP(P22,MATERIAL,7,FALSE())+IF(P22=0,0,$EW22) -> 0 | BN22: =VLOOKUP(Q22,MATERIAL,7,FALSE())+IF(Q22=0,0,$EW22) -> 0 | ... BU22: =VLOOKUP(X22,MATERIAL,7,FALSE())+IF(X22=0,0,$EW22) -> 0 | BV22: =VLOOKUP(J22,MATERIAL,8,FALSE())+IF(J22=0,0,$EW22) -> 0 | BW22: =VLOOKUP(K22,MATERIAL,8,FALSE())+IF(K22=0,0,$EW22) -> 0 | BX22: =VLOOKUP(L22,MATERIAL,8,FALSE())+IF(L22=0,0,$EW22) -> 0 | BY22: =VLOOKUP(M22,MATERIAL,8,FALSE())+IF(M22=0,0,$EW22) -> 0 | BZ22: =VLOOKUP(N22,MATERIAL,8,FALSE())+IF(N22=0,0,$EW22) -> 0 | CA22: =VLOOKUP(O22,MATERIAL,8,FALSE())+IF(O22=0,0,$EW22) -> 0 | CB22: =VLOOKUP(P22,MATERIAL,8,FALSE())+IF(P22=0,0,$EW22) -> 0 | CC22: =VLOOKUP(Q22,MATERIAL,8,FALSE())+IF(Q22=0,0,$EW22) -> 0 | ... CJ22: =VLOOKUP(X22,MATERIAL,8,FALSE())+IF(X22=0,0,$EW22) -> 0 | CK22: =VLOOKUP(J22,MATERIAL,4,FALSE()) -> 0 | CL22: =VLOOKUP(K22,MATERIAL,4,FALSE()) -> 0 | CM22: =VLOOKUP(L22,MATERIAL,4,FALSE()) -> 0 | CN22: =VLOOKUP(M22,MATERIAL,4,FALSE()) -> 0 | CO22: =VLOOKUP(N22,MATERIAL,4,FALSE()) -> 0 | CP22: =VLOOKUP(O22,MATERIAL,4,FALSE()) -> 0 | CQ22: =VLOOKUP(P22,MATERIAL,4,FALSE()) -> 0 | CR22: =VLOOKUP(Q22,MATERIAL,4,FALSE()) -> 0 | ... CY22: =VLOOKUP(X22,MATERIAL,4,FALSE()) -> 0 | CZ22: =IF(J22=0,0,LEFT(J22,1)) -> 0 | DA22: =IF(K22=0,0,LEFT(K22,1)) -> 0 | DB22: =IF(L22=0,0,LEFT(L22,1)) -> 0 | DC22: =IF(M22=0,0,LEFT(M22,1)) -> 0 | DD22: =IF(N22=0,0,LEFT(N22,1)) -> 0 | DE22: =IF(O22=0,0,LEFT(O22,1)) -> 0 | DF22: =IF(P22=0,0,LEFT(P22,1)) -> 0 | DG22: =IF(Q22=0,0,LEFT(Q22,1)) -> 0 | ... DN22: =IF(X22=0,0,LEFT(X22,1)) -> 0 | DO22: =DO7/3+DO8+DO9+DO12 -> 1 | DP22: =DP7/3+DP8+DP9+DP12 -> 0 | DQ22: =DQ7/3+DQ8+DQ9+DQ12 -> 0 | DR22: =DR7/3+DR8+DR9+DR12 -> 0 | DS22: =DS7/3+DS8+DS9+DS12 -> 0 | DT22: =DT7/3+DT8+DT9+DT12 -> 0 | DU22: =DU7/3+DU8+DU9+DU12 -> 0 | DV22: =DV7/3+DV8+DV9+DV12 -> 0 | ... EC22: =EC7/3+EC8+EC9+EC12 -> 1 | ED22: GLKP | EE22: Arms & Legs | EF22: =VLOOKUP(J22,MATERIAL,9,FALSE()) -> 0 | EG22: =VLOOKUP(K22,MATERIAL,9,FALSE()) -> 0 | EH22: =VLOOKUP(L22,MATERIAL,9,FALSE()) -> 0 | EI22: =VLOOKUP(M22,MATERIAL,9,FALSE()) -> 0 | EJ22: =VLOOKUP(N22,MATERIAL,9,FALSE()) -> 0 | EK22: =VLOOKUP(O22,MATERIAL,9,FALSE()) -> 0 | EL22: =VLOOKUP(P22,MATERIAL,9,FALSE()) -> 0 | EM22: =VLOOKUP(Q22,MATERIAL,9,FALSE()) -> 0 | ... ET22: =VLOOKUP(X22,MATERIAL,9,FALSE()) -> 0 | EU22: =IF($B22="",0,VLOOKUP($B22,ITEMS,EU$2,FALSE())) -> 0 | EV22: =VLOOKUP(EU22,MWS,2) -> 0 | EW22: =VLOOKUP(EU22,MWS,3) -> 0
A23: =EV23 -> 0 | C23: Ft | D23: =AQ1 -> 1 | E23: =BF1 -> 3 | F23: =BU1 -> 1 | G23: =CJ1 -> 4 | H23: =MAX(ET5:ET32) -> 0 | J23: =IF($B23="",0,VLOOKUP($B23,ITEMS,J$2,FALSE())) -> 0 | K23: =IF($B23="",0,VLOOKUP($B23,ITEMS,K$2,FALSE())) -> 0 | L23: =IF($B23="",0,VLOOKUP($B23,ITEMS,L$2,FALSE())) -> 0 | M23: =IF($B23="",0,VLOOKUP($B23,ITEMS,M$2,FALSE())) -> 0 | N23: =IF($B23="",0,VLOOKUP($B23,ITEMS,N$2,FALSE())) -> 0 | O23: =IF($B23="",0,VLOOKUP($B23,ITEMS,O$2,FALSE())) -> 0 | P23: =IF($B23="",0,VLOOKUP($B23,ITEMS,P$2,FALSE())) -> 0 | Q23: =IF($B23="",0,VLOOKUP($B23,ITEMS,Q$2,FALSE())) -> 0 | ... X23: =IF($B23="",0,VLOOKUP($B23,ITEMS,X$2,FALSE())) -> 0 | Y23: =IF($B23="",0,VLOOKUP($B23,ITEMS,17,FALSE())) -> 0 | Z23: =IF($B23="",0,VLOOKUP($B23,ITEMS,18,FALSE())) -> 0 | AA23: =IF($B23="",0,VLOOKUP($B23,ITEMS,19,FALSE())) -> 0 | AB23: =IF($B23="",0,VLOOKUP($B23,ITEMS,20,FALSE())) -> 0 | AC23: =VLOOKUP(J23,MATERIAL,5,FALSE())+IF(J23=0,0,$EW23) -> 0 | AD23: =VLOOKUP(K23,MATERIAL,5,FALSE())+IF(K23=0,0,$EW23) -> 0 | AE23: =VLOOKUP(L23,MATERIAL,5,FALSE())+IF(L23=0,0,$EW23) -> 0 | AF23: =VLOOKUP(M23,MATERIAL,5,FALSE())+IF(M23=0,0,$EW23) -> 0 | AG23: =VLOOKUP(N23,MATERIAL,5,FALSE())+IF(N23=0,0,$EW23) -> 0 | AH23: =VLOOKUP(O23,MATERIAL,5,FALSE())+IF(O23=0,0,$EW23) -> 0 | AI23: =VLOOKUP(P23,MATERIAL,5,FALSE())+IF(P23=0,0,$EW23) -> 0 | AJ23: =VLOOKUP(Q23,MATERIAL,5,FALSE())+IF(Q23=0,0,$EW23) -> 0 | ... AQ23: =VLOOKUP(X23,MATERIAL,5,FALSE())+IF(X23=0,0,$EW23) -> 0 | AR23: =VLOOKUP(J23,MATERIAL,6,FALSE())+IF(J23=0,0,$EW23) -> 0 | AS23: =VLOOKUP(K23,MATERIAL,6,FALSE())+IF(K23=0,0,$EW23) -> 0 | AT23: =VLOOKUP(L23,MATERIAL,6,FALSE())+IF(L23=0,0,$EW23) -> 0 | AU23: =VLOOKUP(M23,MATERIAL,6,FALSE())+IF(M23=0,0,$EW23) -> 0 | AV23: =VLOOKUP(N23,MATERIAL,6,FALSE())+IF(N23=0,0,$EW23) -> 0 | AW23: =VLOOKUP(O23,MATERIAL,6,FALSE())+IF(O23=0,0,$EW23) -> 0 | AX23: =VLOOKUP(P23,MATERIAL,6,FALSE())+IF(P23=0,0,$EW23) -> 0 | AY23: =VLOOKUP(Q23,MATERIAL,6,FALSE())+IF(Q23=0,0,$EW23) -> 0 | ... BF23: =VLOOKUP(X23,MATERIAL,6,FALSE())+IF(X23=0,0,$EW23) -> 0 | BG23: =VLOOKUP(J23,MATERIAL,7,FALSE())+IF(J23=0,0,$EW23) -> 0 | BH23: =VLOOKUP(K23,MATERIAL,7,FALSE())+IF(K23=0,0,$EW23) -> 0 | BI23: =VLOOKUP(L23,MATERIAL,7,FALSE())+IF(L23=0,0,$EW23) -> 0 | BJ23: =VLOOKUP(M23,MATERIAL,7,FALSE())+IF(M23=0,0,$EW23) -> 0 | BK23: =VLOOKUP(N23,MATERIAL,7,FALSE())+IF(N23=0,0,$EW23) -> 0 | BL23: =VLOOKUP(O23,MATERIAL,7,FALSE())+IF(O23=0,0,$EW23) -> 0 | BM23: =VLOOKUP(P23,MATERIAL,7,FALSE())+IF(P23=0,0,$EW23) -> 0 | BN23: =VLOOKUP(Q23,MATERIAL,7,FALSE())+IF(Q23=0,0,$EW23) -> 0 | ... BU23: =VLOOKUP(X23,MATERIAL,7,FALSE())+IF(X23=0,0,$EW23) -> 0 | BV23: =VLOOKUP(J23,MATERIAL,8,FALSE())+IF(J23=0,0,$EW23) -> 0 | BW23: =VLOOKUP(K23,MATERIAL,8,FALSE())+IF(K23=0,0,$EW23) -> 0 | BX23: =VLOOKUP(L23,MATERIAL,8,FALSE())+IF(L23=0,0,$EW23) -> 0 | BY23: =VLOOKUP(M23,MATERIAL,8,FALSE())+IF(M23=0,0,$EW23) -> 0 | BZ23: =VLOOKUP(N23,MATERIAL,8,FALSE())+IF(N23=0,0,$EW23) -> 0 | CA23: =VLOOKUP(O23,MATERIAL,8,FALSE())+IF(O23=0,0,$EW23) -> 0 | CB23: =VLOOKUP(P23,MATERIAL,8,FALSE())+IF(P23=0,0,$EW23) -> 0 | CC23: =VLOOKUP(Q23,MATERIAL,8,FALSE())+IF(Q23=0,0,$EW23) -> 0 | ... CJ23: =VLOOKUP(X23,MATERIAL,8,FALSE())+IF(X23=0,0,$EW23) -> 0 | CK23: =VLOOKUP(J23,MATERIAL,4,FALSE()) -> 0 | CL23: =VLOOKUP(K23,MATERIAL,4,FALSE()) -> 0 | CM23: =VLOOKUP(L23,MATERIAL,4,FALSE()) -> 0 | CN23: =VLOOKUP(M23,MATERIAL,4,FALSE()) -> 0 | CO23: =VLOOKUP(N23,MATERIAL,4,FALSE()) -> 0 | CP23: =VLOOKUP(O23,MATERIAL,4,FALSE()) -> 0 | CQ23: =VLOOKUP(P23,MATERIAL,4,FALSE()) -> 0 | CR23: =VLOOKUP(Q23,MATERIAL,4,FALSE()) -> 0 | ... CY23: =VLOOKUP(X23,MATERIAL,4,FALSE()) -> 0 | CZ23: =IF(J23=0,0,LEFT(J23,1)) -> 0 | DA23: =IF(K23=0,0,LEFT(K23,1)) -> 0 | DB23: =IF(L23=0,0,LEFT(L23,1)) -> 0 | DC23: =IF(M23=0,0,LEFT(M23,1)) -> 0 | DD23: =IF(N23=0,0,LEFT(N23,1)) -> 0 | DE23: =IF(O23=0,0,LEFT(O23,1)) -> 0 | DF23: =IF(P23=0,0,LEFT(P23,1)) -> 0 | DG23: =IF(Q23=0,0,LEFT(Q23,1)) -> 0 | ... DN23: =IF(X23=0,0,LEFT(X23,1)) -> 0 | EF23: =VLOOKUP(J23,MATERIAL,9,FALSE()) -> 0 | EG23: =VLOOKUP(K23,MATERIAL,9,FALSE()) -> 0 | EH23: =VLOOKUP(L23,MATERIAL,9,FALSE()) -> 0 | EI23: =VLOOKUP(M23,MATERIAL,9,FALSE()) -> 0 | EJ23: =VLOOKUP(N23,MATERIAL,9,FALSE()) -> 0 | EK23: =VLOOKUP(O23,MATERIAL,9,FALSE()) -> 0 | EL23: =VLOOKUP(P23,MATERIAL,9,FALSE()) -> 0 | EM23: =VLOOKUP(Q23,MATERIAL,9,FALSE()) -> 0 | ... ET23: =VLOOKUP(X23,MATERIAL,9,FALSE()) -> 0 | EU23: =IF($B23="",0,VLOOKUP($B23,ITEMS,EU$2,FALSE())) -> 0 | EV23: =VLOOKUP(EU23,MWS,2) -> 0 | EW23: =VLOOKUP(EU23,MWS,3) -> 0
A24: =EV24 -> 0 | J24: =IF($B24="",0,VLOOKUP($B24,ITEMS,J$2,FALSE())) -> 0 | K24: =IF($B24="",0,VLOOKUP($B24,ITEMS,K$2,FALSE())) -> 0 | L24: =IF($B24="",0,VLOOKUP($B24,ITEMS,L$2,FALSE())) -> 0 | M24: =IF($B24="",0,VLOOKUP($B24,ITEMS,M$2,FALSE())) -> 0 | N24: =IF($B24="",0,VLOOKUP($B24,ITEMS,N$2,FALSE())) -> 0 | O24: =IF($B24="",0,VLOOKUP($B24,ITEMS,O$2,FALSE())) -> 0 | P24: =IF($B24="",0,VLOOKUP($B24,ITEMS,P$2,FALSE())) -> 0 | Q24: =IF($B24="",0,VLOOKUP($B24,ITEMS,Q$2,FALSE())) -> 0 | ... X24: =IF($B24="",0,VLOOKUP($B24,ITEMS,X$2,FALSE())) -> 0 | Y24: =IF($B24="",0,VLOOKUP($B24,ITEMS,17,FALSE())) -> 0 | Z24: =IF($B24="",0,VLOOKUP($B24,ITEMS,18,FALSE())) -> 0 | AA24: =IF($B24="",0,VLOOKUP($B24,ITEMS,19,FALSE())) -> 0 | AB24: =IF($B24="",0,VLOOKUP($B24,ITEMS,20,FALSE())) -> 0 | AC24: =VLOOKUP(J24,MATERIAL,5,FALSE())+IF(J24=0,0,$EW24) -> 0 | AD24: =VLOOKUP(K24,MATERIAL,5,FALSE())+IF(K24=0,0,$EW24) -> 0 | AE24: =VLOOKUP(L24,MATERIAL,5,FALSE())+IF(L24=0,0,$EW24) -> 0 | AF24: =VLOOKUP(M24,MATERIAL,5,FALSE())+IF(M24=0,0,$EW24) -> 0 | AG24: =VLOOKUP(N24,MATERIAL,5,FALSE())+IF(N24=0,0,$EW24) -> 0 | AH24: =VLOOKUP(O24,MATERIAL,5,FALSE())+IF(O24=0,0,$EW24) -> 0 | AI24: =VLOOKUP(P24,MATERIAL,5,FALSE())+IF(P24=0,0,$EW24) -> 0 | AJ24: =VLOOKUP(Q24,MATERIAL,5,FALSE())+IF(Q24=0,0,$EW24) -> 0 | ... AQ24: =VLOOKUP(X24,MATERIAL,5,FALSE())+IF(X24=0,0,$EW24) -> 0 | AR24: =VLOOKUP(J24,MATERIAL,6,FALSE())+IF(J24=0,0,$EW24) -> 0 | AS24: =VLOOKUP(K24,MATERIAL,6,FALSE())+IF(K24=0,0,$EW24) -> 0 | AT24: =VLOOKUP(L24,MATERIAL,6,FALSE())+IF(L24=0,0,$EW24) -> 0 | AU24: =VLOOKUP(M24,MATERIAL,6,FALSE())+IF(M24=0,0,$EW24) -> 0 | AV24: =VLOOKUP(N24,MATERIAL,6,FALSE())+IF(N24=0,0,$EW24) -> 0 | AW24: =VLOOKUP(O24,MATERIAL,6,FALSE())+IF(O24=0,0,$EW24) -> 0 | AX24: =VLOOKUP(P24,MATERIAL,6,FALSE())+IF(P24=0,0,$EW24) -> 0 | AY24: =VLOOKUP(Q24,MATERIAL,6,FALSE())+IF(Q24=0,0,$EW24) -> 0 | ... BF24: =VLOOKUP(X24,MATERIAL,6,FALSE())+IF(X24=0,0,$EW24) -> 0 | BG24: =VLOOKUP(J24,MATERIAL,7,FALSE())+IF(J24=0,0,$EW24) -> 0 | BH24: =VLOOKUP(K24,MATERIAL,7,FALSE())+IF(K24=0,0,$EW24) -> 0 | BI24: =VLOOKUP(L24,MATERIAL,7,FALSE())+IF(L24=0,0,$EW24) -> 0 | BJ24: =VLOOKUP(M24,MATERIAL,7,FALSE())+IF(M24=0,0,$EW24) -> 0 | BK24: =VLOOKUP(N24,MATERIAL,7,FALSE())+IF(N24=0,0,$EW24) -> 0 | BL24: =VLOOKUP(O24,MATERIAL,7,FALSE())+IF(O24=0,0,$EW24) -> 0 | BM24: =VLOOKUP(P24,MATERIAL,7,FALSE())+IF(P24=0,0,$EW24) -> 0 | BN24: =VLOOKUP(Q24,MATERIAL,7,FALSE())+IF(Q24=0,0,$EW24) -> 0 | ... BU24: =VLOOKUP(X24,MATERIAL,7,FALSE())+IF(X24=0,0,$EW24) -> 0 | BV24: =VLOOKUP(J24,MATERIAL,8,FALSE())+IF(J24=0,0,$EW24) -> 0 | BW24: =VLOOKUP(K24,MATERIAL,8,FALSE())+IF(K24=0,0,$EW24) -> 0 | BX24: =VLOOKUP(L24,MATERIAL,8,FALSE())+IF(L24=0,0,$EW24) -> 0 | BY24: =VLOOKUP(M24,MATERIAL,8,FALSE())+IF(M24=0,0,$EW24) -> 0 | BZ24: =VLOOKUP(N24,MATERIAL,8,FALSE())+IF(N24=0,0,$EW24) -> 0 | CA24: =VLOOKUP(O24,MATERIAL,8,FALSE())+IF(O24=0,0,$EW24) -> 0 | CB24: =VLOOKUP(P24,MATERIAL,8,FALSE())+IF(P24=0,0,$EW24) -> 0 | CC24: =VLOOKUP(Q24,MATERIAL,8,FALSE())+IF(Q24=0,0,$EW24) -> 0 | ... CJ24: =VLOOKUP(X24,MATERIAL,8,FALSE())+IF(X24=0,0,$EW24) -> 0 | CK24: =VLOOKUP(J24,MATERIAL,4,FALSE()) -> 0 | CL24: =VLOOKUP(K24,MATERIAL,4,FALSE()) -> 0 | CM24: =VLOOKUP(L24,MATERIAL,4,FALSE()) -> 0 | CN24: =VLOOKUP(M24,MATERIAL,4,FALSE()) -> 0 | CO24: =VLOOKUP(N24,MATERIAL,4,FALSE()) -> 0 | CP24: =VLOOKUP(O24,MATERIAL,4,FALSE()) -> 0 | CQ24: =VLOOKUP(P24,MATERIAL,4,FALSE()) -> 0 | CR24: =VLOOKUP(Q24,MATERIAL,4,FALSE()) -> 0 | ... CY24: =VLOOKUP(X24,MATERIAL,4,FALSE()) -> 0 | CZ24: =IF(J24=0,0,LEFT(J24,1)) -> 0 | DA24: =IF(K24=0,0,LEFT(K24,1)) -> 0 | DB24: =IF(L24=0,0,LEFT(L24,1)) -> 0 | DC24: =IF(M24=0,0,LEFT(M24,1)) -> 0 | DD24: =IF(N24=0,0,LEFT(N24,1)) -> 0 | DE24: =IF(O24=0,0,LEFT(O24,1)) -> 0 | DF24: =IF(P24=0,0,LEFT(P24,1)) -> 0 | DG24: =IF(Q24=0,0,LEFT(Q24,1)) -> 0 | ... DN24: =IF(X24=0,0,LEFT(X24,1)) -> 0 | DO24: 6 | DP24: 6 | DQ24: 6 | DR24: 7 | DS24: 7 | DT24: 7 | DU24: 7 | DV24: 7 | DW24: 7 | DX24: 7 | DY24: 7 | DZ24: 7 | EA24: 7 | EB24: 6 | EC24: 6 | ED24: Total Lim | EF24: =VLOOKUP(J24,MATERIAL,9,FALSE()) -> 0 | EG24: =VLOOKUP(K24,MATERIAL,9,FALSE()) -> 0 | EH24: =VLOOKUP(L24,MATERIAL,9,FALSE()) -> 0 | EI24: =VLOOKUP(M24,MATERIAL,9,FALSE()) -> 0 | EJ24: =VLOOKUP(N24,MATERIAL,9,FALSE()) -> 0 | EK24: =VLOOKUP(O24,MATERIAL,9,FALSE()) -> 0 | EL24: =VLOOKUP(P24,MATERIAL,9,FALSE()) -> 0 | EM24: =VLOOKUP(Q24,MATERIAL,9,FALSE()) -> 0 | ... ET24: =VLOOKUP(X24,MATERIAL,9,FALSE()) -> 0 | EU24: =IF($B24="",0,VLOOKUP($B24,ITEMS,EU$2,FALSE())) -> 0 | EV24: =VLOOKUP(EU24,MWS,2) -> 0 | EW24: =VLOOKUP(EU24,MWS,3) -> 0
A25: =EV25 -> 0 | D25: Bulk Penalty: | G25: Front | J25: =IF($B25="",0,VLOOKUP($B25,ITEMS,J$2,FALSE())) -> 0 | K25: =IF($B25="",0,VLOOKUP($B25,ITEMS,K$2,FALSE())) -> 0 | L25: =IF($B25="",0,VLOOKUP($B25,ITEMS,L$2,FALSE())) -> 0 | M25: =IF($B25="",0,VLOOKUP($B25,ITEMS,M$2,FALSE())) -> 0 | N25: =IF($B25="",0,VLOOKUP($B25,ITEMS,N$2,FALSE())) -> 0 | O25: =IF($B25="",0,VLOOKUP($B25,ITEMS,O$2,FALSE())) -> 0 | P25: =IF($B25="",0,VLOOKUP($B25,ITEMS,P$2,FALSE())) -> 0 | Q25: =IF($B25="",0,VLOOKUP($B25,ITEMS,Q$2,FALSE())) -> 0 | ... X25: =IF($B25="",0,VLOOKUP($B25,ITEMS,X$2,FALSE())) -> 0 | Y25: =IF($B25="",0,VLOOKUP($B25,ITEMS,17,FALSE())) -> 0 | Z25: =IF($B25="",0,VLOOKUP($B25,ITEMS,18,FALSE())) -> 0 | AA25: =IF($B25="",0,VLOOKUP($B25,ITEMS,19,FALSE())) -> 0 | AB25: =IF($B25="",0,VLOOKUP($B25,ITEMS,20,FALSE())) -> 0 | AC25: =VLOOKUP(J25,MATERIAL,5,FALSE())+IF(J25=0,0,$EW25) -> 0 | AD25: =VLOOKUP(K25,MATERIAL,5,FALSE())+IF(K25=0,0,$EW25) -> 0 | AE25: =VLOOKUP(L25,MATERIAL,5,FALSE())+IF(L25=0,0,$EW25) -> 0 | AF25: =VLOOKUP(M25,MATERIAL,5,FALSE())+IF(M25=0,0,$EW25) -> 0 | AG25: =VLOOKUP(N25,MATERIAL,5,FALSE())+IF(N25=0,0,$EW25) -> 0 | AH25: =VLOOKUP(O25,MATERIAL,5,FALSE())+IF(O25=0,0,$EW25) -> 0 | AI25: =VLOOKUP(P25,MATERIAL,5,FALSE())+IF(P25=0,0,$EW25) -> 0 | AJ25: =VLOOKUP(Q25,MATERIAL,5,FALSE())+IF(Q25=0,0,$EW25) -> 0 | ... AQ25: =VLOOKUP(X25,MATERIAL,5,FALSE())+IF(X25=0,0,$EW25) -> 0 | AR25: =VLOOKUP(J25,MATERIAL,6,FALSE())+IF(J25=0,0,$EW25) -> 0 | AS25: =VLOOKUP(K25,MATERIAL,6,FALSE())+IF(K25=0,0,$EW25) -> 0 | AT25: =VLOOKUP(L25,MATERIAL,6,FALSE())+IF(L25=0,0,$EW25) -> 0 | AU25: =VLOOKUP(M25,MATERIAL,6,FALSE())+IF(M25=0,0,$EW25) -> 0 | AV25: =VLOOKUP(N25,MATERIAL,6,FALSE())+IF(N25=0,0,$EW25) -> 0 | AW25: =VLOOKUP(O25,MATERIAL,6,FALSE())+IF(O25=0,0,$EW25) -> 0 | AX25: =VLOOKUP(P25,MATERIAL,6,FALSE())+IF(P25=0,0,$EW25) -> 0 | AY25: =VLOOKUP(Q25,MATERIAL,6,FALSE())+IF(Q25=0,0,$EW25) -> 0 | ... BF25: =VLOOKUP(X25,MATERIAL,6,FALSE())+IF(X25=0,0,$EW25) -> 0 | BG25: =VLOOKUP(J25,MATERIAL,7,FALSE())+IF(J25=0,0,$EW25) -> 0 | BH25: =VLOOKUP(K25,MATERIAL,7,FALSE())+IF(K25=0,0,$EW25) -> 0 | BI25: =VLOOKUP(L25,MATERIAL,7,FALSE())+IF(L25=0,0,$EW25) -> 0 | BJ25: =VLOOKUP(M25,MATERIAL,7,FALSE())+IF(M25=0,0,$EW25) -> 0 | BK25: =VLOOKUP(N25,MATERIAL,7,FALSE())+IF(N25=0,0,$EW25) -> 0 | BL25: =VLOOKUP(O25,MATERIAL,7,FALSE())+IF(O25=0,0,$EW25) -> 0 | BM25: =VLOOKUP(P25,MATERIAL,7,FALSE())+IF(P25=0,0,$EW25) -> 0 | BN25: =VLOOKUP(Q25,MATERIAL,7,FALSE())+IF(Q25=0,0,$EW25) -> 0 | ... BU25: =VLOOKUP(X25,MATERIAL,7,FALSE())+IF(X25=0,0,$EW25) -> 0 | BV25: =VLOOKUP(J25,MATERIAL,8,FALSE())+IF(J25=0,0,$EW25) -> 0 | BW25: =VLOOKUP(K25,MATERIAL,8,FALSE())+IF(K25=0,0,$EW25) -> 0 | BX25: =VLOOKUP(L25,MATERIAL,8,FALSE())+IF(L25=0,0,$EW25) -> 0 | BY25: =VLOOKUP(M25,MATERIAL,8,FALSE())+IF(M25=0,0,$EW25) -> 0 | BZ25: =VLOOKUP(N25,MATERIAL,8,FALSE())+IF(N25=0,0,$EW25) -> 0 | CA25: =VLOOKUP(O25,MATERIAL,8,FALSE())+IF(O25=0,0,$EW25) -> 0 | CB25: =VLOOKUP(P25,MATERIAL,8,FALSE())+IF(P25=0,0,$EW25) -> 0 | CC25: =VLOOKUP(Q25,MATERIAL,8,FALSE())+IF(Q25=0,0,$EW25) -> 0 | ... CJ25: =VLOOKUP(X25,MATERIAL,8,FALSE())+IF(X25=0,0,$EW25) -> 0 | CK25: =VLOOKUP(J25,MATERIAL,4,FALSE()) -> 0 | CL25: =VLOOKUP(K25,MATERIAL,4,FALSE()) -> 0 | CM25: =VLOOKUP(L25,MATERIAL,4,FALSE()) -> 0 | CN25: =VLOOKUP(M25,MATERIAL,4,FALSE()) -> 0 | CO25: =VLOOKUP(N25,MATERIAL,4,FALSE()) -> 0 | CP25: =VLOOKUP(O25,MATERIAL,4,FALSE()) -> 0 | CQ25: =VLOOKUP(P25,MATERIAL,4,FALSE()) -> 0 | CR25: =VLOOKUP(Q25,MATERIAL,4,FALSE()) -> 0 | ... CY25: =VLOOKUP(X25,MATERIAL,4,FALSE()) -> 0 | CZ25: =IF(J25=0,0,LEFT(J25,1)) -> 0 | DA25: =IF(K25=0,0,LEFT(K25,1)) -> 0 | DB25: =IF(L25=0,0,LEFT(L25,1)) -> 0 | DC25: =IF(M25=0,0,LEFT(M25,1)) -> 0 | DD25: =IF(N25=0,0,LEFT(N25,1)) -> 0 | DE25: =IF(O25=0,0,LEFT(O25,1)) -> 0 | DF25: =IF(P25=0,0,LEFT(P25,1)) -> 0 | DG25: =IF(Q25=0,0,LEFT(Q25,1)) -> 0 | ... DN25: =IF(X25=0,0,LEFT(X25,1)) -> 0 | DO25: 4 | DP25: 4 | DQ25: 4 | DR25: 5 | DS25: 5 | DT25: 5 | DU25: 5 | DV25: 5 | DW25: 5 | DX25: 5 | DY25: 5 | DZ25: 6 | EA25: 5 | EB25: 4 | EC25: 4 | ED25: Bulk | EF25: =VLOOKUP(J25,MATERIAL,9,FALSE()) -> 0 | EG25: =VLOOKUP(K25,MATERIAL,9,FALSE()) -> 0 | EH25: =VLOOKUP(L25,MATERIAL,9,FALSE()) -> 0 | EI25: =VLOOKUP(M25,MATERIAL,9,FALSE()) -> 0 | EJ25: =VLOOKUP(N25,MATERIAL,9,FALSE()) -> 0 | EK25: =VLOOKUP(O25,MATERIAL,9,FALSE()) -> 0 | EL25: =VLOOKUP(P25,MATERIAL,9,FALSE()) -> 0 | EM25: =VLOOKUP(Q25,MATERIAL,9,FALSE()) -> 0 | ... ET25: =VLOOKUP(X25,MATERIAL,9,FALSE()) -> 0 | EU25: =IF($B25="",0,VLOOKUP($B25,ITEMS,EU$2,FALSE())) -> 0 | EV25: =VLOOKUP(EU25,MWS,2) -> 0 | EW25: =VLOOKUP(EU25,MWS,3) -> 0
A26: =EV26 -> 0 | D26: Head | E26: =DT36*5 -> 0 | F26: =IF(DT40=1,"Too many layers!",IF(DT37=1,"Too much padding!",IF(OR(DT38=1,DT39=1),"Illegal combination of layers",""))) | J26: =IF($B26="",0,VLOOKUP($B26,ITEMS,J$2,FALSE())) -> 0 | K26: =IF($B26="",0,VLOOKUP($B26,ITEMS,K$2,FALSE())) -> 0 | L26: =IF($B26="",0,VLOOKUP($B26,ITEMS,L$2,FALSE())) -> 0 | M26: =IF($B26="",0,VLOOKUP($B26,ITEMS,M$2,FALSE())) -> 0 | N26: =IF($B26="",0,VLOOKUP($B26,ITEMS,N$2,FALSE())) -> 0 | O26: =IF($B26="",0,VLOOKUP($B26,ITEMS,O$2,FALSE())) -> 0 | P26: =IF($B26="",0,VLOOKUP($B26,ITEMS,P$2,FALSE())) -> 0 | Q26: =IF($B26="",0,VLOOKUP($B26,ITEMS,Q$2,FALSE())) -> 0 | ... X26: =IF($B26="",0,VLOOKUP($B26,ITEMS,X$2,FALSE())) -> 0 | Y26: =IF($B26="",0,VLOOKUP($B26,ITEMS,17,FALSE())) -> 0 | Z26: =IF($B26="",0,VLOOKUP($B26,ITEMS,18,FALSE())) -> 0 | AA26: =IF($B26="",0,VLOOKUP($B26,ITEMS,19,FALSE())) -> 0 | AB26: =IF($B26="",0,VLOOKUP($B26,ITEMS,20,FALSE())) -> 0 | AC26: =VLOOKUP(J26,MATERIAL,5,FALSE())+IF(J26=0,0,$EW26) -> 0 | AD26: =VLOOKUP(K26,MATERIAL,5,FALSE())+IF(K26=0,0,$EW26) -> 0 | AE26: =VLOOKUP(L26,MATERIAL,5,FALSE())+IF(L26=0,0,$EW26) -> 0 | AF26: =VLOOKUP(M26,MATERIAL,5,FALSE())+IF(M26=0,0,$EW26) -> 0 | AG26: =VLOOKUP(N26,MATERIAL,5,FALSE())+IF(N26=0,0,$EW26) -> 0 | AH26: =VLOOKUP(O26,MATERIAL,5,FALSE())+IF(O26=0,0,$EW26) -> 0 | AI26: =VLOOKUP(P26,MATERIAL,5,FALSE())+IF(P26=0,0,$EW26) -> 0 | AJ26: =VLOOKUP(Q26,MATERIAL,5,FALSE())+IF(Q26=0,0,$EW26) -> 0 | ... AQ26: =VLOOKUP(X26,MATERIAL,5,FALSE())+IF(X26=0,0,$EW26) -> 0 | AR26: =VLOOKUP(J26,MATERIAL,6,FALSE())+IF(J26=0,0,$EW26) -> 0 | AS26: =VLOOKUP(K26,MATERIAL,6,FALSE())+IF(K26=0,0,$EW26) -> 0 | AT26: =VLOOKUP(L26,MATERIAL,6,FALSE())+IF(L26=0,0,$EW26) -> 0 | AU26: =VLOOKUP(M26,MATERIAL,6,FALSE())+IF(M26=0,0,$EW26) -> 0 | AV26: =VLOOKUP(N26,MATERIAL,6,FALSE())+IF(N26=0,0,$EW26) -> 0 | AW26: =VLOOKUP(O26,MATERIAL,6,FALSE())+IF(O26=0,0,$EW26) -> 0 | AX26: =VLOOKUP(P26,MATERIAL,6,FALSE())+IF(P26=0,0,$EW26) -> 0 | AY26: =VLOOKUP(Q26,MATERIAL,6,FALSE())+IF(Q26=0,0,$EW26) -> 0 | ... BF26: =VLOOKUP(X26,MATERIAL,6,FALSE())+IF(X26=0,0,$EW26) -> 0 | BG26: =VLOOKUP(J26,MATERIAL,7,FALSE())+IF(J26=0,0,$EW26) -> 0 | BH26: =VLOOKUP(K26,MATERIAL,7,FALSE())+IF(K26=0,0,$EW26) -> 0 | BI26: =VLOOKUP(L26,MATERIAL,7,FALSE())+IF(L26=0,0,$EW26) -> 0 | BJ26: =VLOOKUP(M26,MATERIAL,7,FALSE())+IF(M26=0,0,$EW26) -> 0 | BK26: =VLOOKUP(N26,MATERIAL,7,FALSE())+IF(N26=0,0,$EW26) -> 0 | BL26: =VLOOKUP(O26,MATERIAL,7,FALSE())+IF(O26=0,0,$EW26) -> 0 | BM26: =VLOOKUP(P26,MATERIAL,7,FALSE())+IF(P26=0,0,$EW26) -> 0 | BN26: =VLOOKUP(Q26,MATERIAL,7,FALSE())+IF(Q26=0,0,$EW26) -> 0 | ... BU26: =VLOOKUP(X26,MATERIAL,7,FALSE())+IF(X26=0,0,$EW26) -> 0 | BV26: =VLOOKUP(J26,MATERIAL,8,FALSE())+IF(J26=0,0,$EW26) -> 0 | BW26: =VLOOKUP(K26,MATERIAL,8,FALSE())+IF(K26=0,0,$EW26) -> 0 | BX26: =VLOOKUP(L26,MATERIAL,8,FALSE())+IF(L26=0,0,$EW26) -> 0 | BY26: =VLOOKUP(M26,MATERIAL,8,FALSE())+IF(M26=0,0,$EW26) -> 0 | BZ26: =VLOOKUP(N26,MATERIAL,8,FALSE())+IF(N26=0,0,$EW26) -> 0 | CA26: =VLOOKUP(O26,MATERIAL,8,FALSE())+IF(O26=0,0,$EW26) -> 0 | CB26: =VLOOKUP(P26,MATERIAL,8,FALSE())+IF(P26=0,0,$EW26) -> 0 | CC26: =VLOOKUP(Q26,MATERIAL,8,FALSE())+IF(Q26=0,0,$EW26) -> 0 | ... CJ26: =VLOOKUP(X26,MATERIAL,8,FALSE())+IF(X26=0,0,$EW26) -> 0 | CK26: =VLOOKUP(J26,MATERIAL,4,FALSE()) -> 0 | CL26: =VLOOKUP(K26,MATERIAL,4,FALSE()) -> 0 | CM26: =VLOOKUP(L26,MATERIAL,4,FALSE()) -> 0 | CN26: =VLOOKUP(M26,MATERIAL,4,FALSE()) -> 0 | CO26: =VLOOKUP(N26,MATERIAL,4,FALSE()) -> 0 | CP26: =VLOOKUP(O26,MATERIAL,4,FALSE()) -> 0 | CQ26: =VLOOKUP(P26,MATERIAL,4,FALSE()) -> 0 | CR26: =VLOOKUP(Q26,MATERIAL,4,FALSE()) -> 0 | ... CY26: =VLOOKUP(X26,MATERIAL,4,FALSE()) -> 0 | CZ26: =IF(J26=0,0,LEFT(J26,1)) -> 0 | DA26: =IF(K26=0,0,LEFT(K26,1)) -> 0 | DB26: =IF(L26=0,0,LEFT(L26,1)) -> 0 | DC26: =IF(M26=0,0,LEFT(M26,1)) -> 0 | DD26: =IF(N26=0,0,LEFT(N26,1)) -> 0 | DE26: =IF(O26=0,0,LEFT(O26,1)) -> 0 | DF26: =IF(P26=0,0,LEFT(P26,1)) -> 0 | DG26: =IF(Q26=0,0,LEFT(Q26,1)) -> 0 | ... DN26: =IF(X26=0,0,LEFT(X26,1)) -> 0 | DO26: =IF(DO14>DO24,1,0) -> 0 | DP26: =IF(DP14>DP24,1,0) -> 0 | DQ26: =IF(DQ14>DQ24,1,0) -> 0 | DR26: =IF(DR14>DR24,1,0) -> 0 | DS26: =IF(DS14>DS24,1,0) -> 0 | DT26: =IF(DT14>DT24,1,0) -> 0 | DU26: =IF(DU14>DU24,1,0) -> 0 | DV26: =IF(DV14>DV24,1,0) -> 0 | ... EC26: =IF(EC14>EC24,1,0) -> 0 | ED26: Lim | EF26: =VLOOKUP(J26,MATERIAL,9,FALSE()) -> 0 | EG26: =VLOOKUP(K26,MATERIAL,9,FALSE()) -> 0 | EH26: =VLOOKUP(L26,MATERIAL,9,FALSE()) -> 0 | EI26: =VLOOKUP(M26,MATERIAL,9,FALSE()) -> 0 | EJ26: =VLOOKUP(N26,MATERIAL,9,FALSE()) -> 0 | EK26: =VLOOKUP(O26,MATERIAL,9,FALSE()) -> 0 | EL26: =VLOOKUP(P26,MATERIAL,9,FALSE()) -> 0 | EM26: =VLOOKUP(Q26,MATERIAL,9,FALSE()) -> 0 | ... ET26: =VLOOKUP(X26,MATERIAL,9,FALSE()) -> 0 | EU26: =IF($B26="",0,VLOOKUP($B26,ITEMS,EU$2,FALSE())) -> 0 | EV26: =VLOOKUP(EU26,MWS,2) -> 0 | EW26: =VLOOKUP(EU26,MWS,3) -> 0
A27: =EV27 -> 0 | D27: Arms | E27: =DU36*5 -> 0 | F27: =IF(DU40=1,"Too many layers!",IF(DU37=1,"Too much padding!",IF(OR(DU38=1,DU39=1),"Illegal combination of layers",""))) | J27: =IF($B27="",0,VLOOKUP($B27,ITEMS,J$2,FALSE())) -> 0 | K27: =IF($B27="",0,VLOOKUP($B27,ITEMS,K$2,FALSE())) -> 0 | L27: =IF($B27="",0,VLOOKUP($B27,ITEMS,L$2,FALSE())) -> 0 | M27: =IF($B27="",0,VLOOKUP($B27,ITEMS,M$2,FALSE())) -> 0 | N27: =IF($B27="",0,VLOOKUP($B27,ITEMS,N$2,FALSE())) -> 0 | O27: =IF($B27="",0,VLOOKUP($B27,ITEMS,O$2,FALSE())) -> 0 | P27: =IF($B27="",0,VLOOKUP($B27,ITEMS,P$2,FALSE())) -> 0 | Q27: =IF($B27="",0,VLOOKUP($B27,ITEMS,Q$2,FALSE())) -> 0 | ... X27: =IF($B27="",0,VLOOKUP($B27,ITEMS,X$2,FALSE())) -> 0 | Y27: =IF($B27="",0,VLOOKUP($B27,ITEMS,17,FALSE())) -> 0 | Z27: =IF($B27="",0,VLOOKUP($B27,ITEMS,18,FALSE())) -> 0 | AA27: =IF($B27="",0,VLOOKUP($B27,ITEMS,19,FALSE())) -> 0 | AB27: =IF($B27="",0,VLOOKUP($B27,ITEMS,20,FALSE())) -> 0 | AC27: =VLOOKUP(J27,MATERIAL,5,FALSE())+IF(J27=0,0,$EW27) -> 0 | AD27: =VLOOKUP(K27,MATERIAL,5,FALSE())+IF(K27=0,0,$EW27) -> 0 | AE27: =VLOOKUP(L27,MATERIAL,5,FALSE())+IF(L27=0,0,$EW27) -> 0 | AF27: =VLOOKUP(M27,MATERIAL,5,FALSE())+IF(M27=0,0,$EW27) -> 0 | AG27: =VLOOKUP(N27,MATERIAL,5,FALSE())+IF(N27=0,0,$EW27) -> 0 | AH27: =VLOOKUP(O27,MATERIAL,5,FALSE())+IF(O27=0,0,$EW27) -> 0 | AI27: =VLOOKUP(P27,MATERIAL,5,FALSE())+IF(P27=0,0,$EW27) -> 0 | AJ27: =VLOOKUP(Q27,MATERIAL,5,FALSE())+IF(Q27=0,0,$EW27) -> 0 | ... AQ27: =VLOOKUP(X27,MATERIAL,5,FALSE())+IF(X27=0,0,$EW27) -> 0 | AR27: =VLOOKUP(J27,MATERIAL,6,FALSE())+IF(J27=0,0,$EW27) -> 0 | AS27: =VLOOKUP(K27,MATERIAL,6,FALSE())+IF(K27=0,0,$EW27) -> 0 | AT27: =VLOOKUP(L27,MATERIAL,6,FALSE())+IF(L27=0,0,$EW27) -> 0 | AU27: =VLOOKUP(M27,MATERIAL,6,FALSE())+IF(M27=0,0,$EW27) -> 0 | AV27: =VLOOKUP(N27,MATERIAL,6,FALSE())+IF(N27=0,0,$EW27) -> 0 | AW27: =VLOOKUP(O27,MATERIAL,6,FALSE())+IF(O27=0,0,$EW27) -> 0 | AX27: =VLOOKUP(P27,MATERIAL,6,FALSE())+IF(P27=0,0,$EW27) -> 0 | AY27: =VLOOKUP(Q27,MATERIAL,6,FALSE())+IF(Q27=0,0,$EW27) -> 0 | ... BF27: =VLOOKUP(X27,MATERIAL,6,FALSE())+IF(X27=0,0,$EW27) -> 0 | BG27: =VLOOKUP(J27,MATERIAL,7,FALSE())+IF(J27=0,0,$EW27) -> 0 | BH27: =VLOOKUP(K27,MATERIAL,7,FALSE())+IF(K27=0,0,$EW27) -> 0 | BI27: =VLOOKUP(L27,MATERIAL,7,FALSE())+IF(L27=0,0,$EW27) -> 0 | BJ27: =VLOOKUP(M27,MATERIAL,7,FALSE())+IF(M27=0,0,$EW27) -> 0 | BK27: =VLOOKUP(N27,MATERIAL,7,FALSE())+IF(N27=0,0,$EW27) -> 0 | BL27: =VLOOKUP(O27,MATERIAL,7,FALSE())+IF(O27=0,0,$EW27) -> 0 | BM27: =VLOOKUP(P27,MATERIAL,7,FALSE())+IF(P27=0,0,$EW27) -> 0 | BN27: =VLOOKUP(Q27,MATERIAL,7,FALSE())+IF(Q27=0,0,$EW27) -> 0 | ... BU27: =VLOOKUP(X27,MATERIAL,7,FALSE())+IF(X27=0,0,$EW27) -> 0 | BV27: =VLOOKUP(J27,MATERIAL,8,FALSE())+IF(J27=0,0,$EW27) -> 0 | BW27: =VLOOKUP(K27,MATERIAL,8,FALSE())+IF(K27=0,0,$EW27) -> 0 | BX27: =VLOOKUP(L27,MATERIAL,8,FALSE())+IF(L27=0,0,$EW27) -> 0 | BY27: =VLOOKUP(M27,MATERIAL,8,FALSE())+IF(M27=0,0,$EW27) -> 0 | BZ27: =VLOOKUP(N27,MATERIAL,8,FALSE())+IF(N27=0,0,$EW27) -> 0 | CA27: =VLOOKUP(O27,MATERIAL,8,FALSE())+IF(O27=0,0,$EW27) -> 0 | CB27: =VLOOKUP(P27,MATERIAL,8,FALSE())+IF(P27=0,0,$EW27) -> 0 | CC27: =VLOOKUP(Q27,MATERIAL,8,FALSE())+IF(Q27=0,0,$EW27) -> 0 | ... CJ27: =VLOOKUP(X27,MATERIAL,8,FALSE())+IF(X27=0,0,$EW27) -> 0 | CK27: =VLOOKUP(J27,MATERIAL,4,FALSE()) -> 0 | CL27: =VLOOKUP(K27,MATERIAL,4,FALSE()) -> 0 | CM27: =VLOOKUP(L27,MATERIAL,4,FALSE()) -> 0 | CN27: =VLOOKUP(M27,MATERIAL,4,FALSE()) -> 0 | CO27: =VLOOKUP(N27,MATERIAL,4,FALSE()) -> 0 | CP27: =VLOOKUP(O27,MATERIAL,4,FALSE()) -> 0 | CQ27: =VLOOKUP(P27,MATERIAL,4,FALSE()) -> 0 | CR27: =VLOOKUP(Q27,MATERIAL,4,FALSE()) -> 0 | ... CY27: =VLOOKUP(X27,MATERIAL,4,FALSE()) -> 0 | CZ27: =IF(J27=0,0,LEFT(J27,1)) -> 0 | DA27: =IF(K27=0,0,LEFT(K27,1)) -> 0 | DB27: =IF(L27=0,0,LEFT(L27,1)) -> 0 | DC27: =IF(M27=0,0,LEFT(M27,1)) -> 0 | DD27: =IF(N27=0,0,LEFT(N27,1)) -> 0 | DE27: =IF(O27=0,0,LEFT(O27,1)) -> 0 | DF27: =IF(P27=0,0,LEFT(P27,1)) -> 0 | DG27: =IF(Q27=0,0,LEFT(Q27,1)) -> 0 | ... DN27: =IF(X27=0,0,LEFT(X27,1)) -> 0 | DO27: =IF(DO14>DO25,1,0) -> 0 | DP27: =IF(DP14>DP25,1,0) -> 0 | DQ27: =IF(DQ14>DQ25,1,0) -> 0 | DR27: =IF(DR14>DR25,1,0) -> 0 | DS27: =IF(DS14>DS25,1,0) -> 0 | DT27: =IF(DT14>DT25,1,0) -> 0 | DU27: =IF(DU14>DU25,1,0) -> 0 | DV27: =IF(DV14>DV25,1,0) -> 0 | ... EC27: =IF(EC14>EC25,1,0) -> 0 | ED27: Bulk | EF27: =VLOOKUP(J27,MATERIAL,9,FALSE()) -> 0 | EG27: =VLOOKUP(K27,MATERIAL,9,FALSE()) -> 0 | EH27: =VLOOKUP(L27,MATERIAL,9,FALSE()) -> 0 | EI27: =VLOOKUP(M27,MATERIAL,9,FALSE()) -> 0 | EJ27: =VLOOKUP(N27,MATERIAL,9,FALSE()) -> 0 | EK27: =VLOOKUP(O27,MATERIAL,9,FALSE()) -> 0 | EL27: =VLOOKUP(P27,MATERIAL,9,FALSE()) -> 0 | EM27: =VLOOKUP(Q27,MATERIAL,9,FALSE()) -> 0 | ... ET27: =VLOOKUP(X27,MATERIAL,9,FALSE()) -> 0 | EU27: =IF($B27="",0,VLOOKUP($B27,ITEMS,EU$2,FALSE())) -> 0 | EV27: =VLOOKUP(EU27,MWS,2) -> 0 | EW27: =VLOOKUP(EU27,MWS,3) -> 0
A28: =EV28 -> 0 | D28: Torso | E28: =DV36*5 -> 0 | F28: =IF(DV40=1,"Too many layers!",IF(DV37=1,"Too much padding!",IF(OR(DV38=1,DV39=1),"Illegal combination of layers",""))) | J28: =IF($B28="",0,VLOOKUP($B28,ITEMS,J$2,FALSE())) -> 0 | K28: =IF($B28="",0,VLOOKUP($B28,ITEMS,K$2,FALSE())) -> 0 | L28: =IF($B28="",0,VLOOKUP($B28,ITEMS,L$2,FALSE())) -> 0 | M28: =IF($B28="",0,VLOOKUP($B28,ITEMS,M$2,FALSE())) -> 0 | N28: =IF($B28="",0,VLOOKUP($B28,ITEMS,N$2,FALSE())) -> 0 | O28: =IF($B28="",0,VLOOKUP($B28,ITEMS,O$2,FALSE())) -> 0 | P28: =IF($B28="",0,VLOOKUP($B28,ITEMS,P$2,FALSE())) -> 0 | Q28: =IF($B28="",0,VLOOKUP($B28,ITEMS,Q$2,FALSE())) -> 0 | ... X28: =IF($B28="",0,VLOOKUP($B28,ITEMS,X$2,FALSE())) -> 0 | Y28: =IF($B28="",0,VLOOKUP($B28,ITEMS,17,FALSE())) -> 0 | Z28: =IF($B28="",0,VLOOKUP($B28,ITEMS,18,FALSE())) -> 0 | AA28: =IF($B28="",0,VLOOKUP($B28,ITEMS,19,FALSE())) -> 0 | AB28: =IF($B28="",0,VLOOKUP($B28,ITEMS,20,FALSE())) -> 0 | AC28: =VLOOKUP(J28,MATERIAL,5,FALSE())+IF(J28=0,0,$EW28) -> 0 | AD28: =VLOOKUP(K28,MATERIAL,5,FALSE())+IF(K28=0,0,$EW28) -> 0 | AE28: =VLOOKUP(L28,MATERIAL,5,FALSE())+IF(L28=0,0,$EW28) -> 0 | AF28: =VLOOKUP(M28,MATERIAL,5,FALSE())+IF(M28=0,0,$EW28) -> 0 | AG28: =VLOOKUP(N28,MATERIAL,5,FALSE())+IF(N28=0,0,$EW28) -> 0 | AH28: =VLOOKUP(O28,MATERIAL,5,FALSE())+IF(O28=0,0,$EW28) -> 0 | AI28: =VLOOKUP(P28,MATERIAL,5,FALSE())+IF(P28=0,0,$EW28) -> 0 | AJ28: =VLOOKUP(Q28,MATERIAL,5,FALSE())+IF(Q28=0,0,$EW28) -> 0 | ... AQ28: =VLOOKUP(X28,MATERIAL,5,FALSE())+IF(X28=0,0,$EW28) -> 0 | AR28: =VLOOKUP(J28,MATERIAL,6,FALSE())+IF(J28=0,0,$EW28) -> 0 | AS28: =VLOOKUP(K28,MATERIAL,6,FALSE())+IF(K28=0,0,$EW28) -> 0 | AT28: =VLOOKUP(L28,MATERIAL,6,FALSE())+IF(L28=0,0,$EW28) -> 0 | AU28: =VLOOKUP(M28,MATERIAL,6,FALSE())+IF(M28=0,0,$EW28) -> 0 | AV28: =VLOOKUP(N28,MATERIAL,6,FALSE())+IF(N28=0,0,$EW28) -> 0 | AW28: =VLOOKUP(O28,MATERIAL,6,FALSE())+IF(O28=0,0,$EW28) -> 0 | AX28: =VLOOKUP(P28,MATERIAL,6,FALSE())+IF(P28=0,0,$EW28) -> 0 | AY28: =VLOOKUP(Q28,MATERIAL,6,FALSE())+IF(Q28=0,0,$EW28) -> 0 | ... BF28: =VLOOKUP(X28,MATERIAL,6,FALSE())+IF(X28=0,0,$EW28) -> 0 | BG28: =VLOOKUP(J28,MATERIAL,7,FALSE())+IF(J28=0,0,$EW28) -> 0 | BH28: =VLOOKUP(K28,MATERIAL,7,FALSE())+IF(K28=0,0,$EW28) -> 0 | BI28: =VLOOKUP(L28,MATERIAL,7,FALSE())+IF(L28=0,0,$EW28) -> 0 | BJ28: =VLOOKUP(M28,MATERIAL,7,FALSE())+IF(M28=0,0,$EW28) -> 0 | BK28: =VLOOKUP(N28,MATERIAL,7,FALSE())+IF(N28=0,0,$EW28) -> 0 | BL28: =VLOOKUP(O28,MATERIAL,7,FALSE())+IF(O28=0,0,$EW28) -> 0 | BM28: =VLOOKUP(P28,MATERIAL,7,FALSE())+IF(P28=0,0,$EW28) -> 0 | BN28: =VLOOKUP(Q28,MATERIAL,7,FALSE())+IF(Q28=0,0,$EW28) -> 0 | ... BU28: =VLOOKUP(X28,MATERIAL,7,FALSE())+IF(X28=0,0,$EW28) -> 0 | BV28: =VLOOKUP(J28,MATERIAL,8,FALSE())+IF(J28=0,0,$EW28) -> 0 | BW28: =VLOOKUP(K28,MATERIAL,8,FALSE())+IF(K28=0,0,$EW28) -> 0 | BX28: =VLOOKUP(L28,MATERIAL,8,FALSE())+IF(L28=0,0,$EW28) -> 0 | BY28: =VLOOKUP(M28,MATERIAL,8,FALSE())+IF(M28=0,0,$EW28) -> 0 | BZ28: =VLOOKUP(N28,MATERIAL,8,FALSE())+IF(N28=0,0,$EW28) -> 0 | CA28: =VLOOKUP(O28,MATERIAL,8,FALSE())+IF(O28=0,0,$EW28) -> 0 | CB28: =VLOOKUP(P28,MATERIAL,8,FALSE())+IF(P28=0,0,$EW28) -> 0 | CC28: =VLOOKUP(Q28,MATERIAL,8,FALSE())+IF(Q28=0,0,$EW28) -> 0 | ... CJ28: =VLOOKUP(X28,MATERIAL,8,FALSE())+IF(X28=0,0,$EW28) -> 0 | CK28: =VLOOKUP(J28,MATERIAL,4,FALSE()) -> 0 | CL28: =VLOOKUP(K28,MATERIAL,4,FALSE()) -> 0 | CM28: =VLOOKUP(L28,MATERIAL,4,FALSE()) -> 0 | CN28: =VLOOKUP(M28,MATERIAL,4,FALSE()) -> 0 | CO28: =VLOOKUP(N28,MATERIAL,4,FALSE()) -> 0 | CP28: =VLOOKUP(O28,MATERIAL,4,FALSE()) -> 0 | CQ28: =VLOOKUP(P28,MATERIAL,4,FALSE()) -> 0 | CR28: =VLOOKUP(Q28,MATERIAL,4,FALSE()) -> 0 | ... CY28: =VLOOKUP(X28,MATERIAL,4,FALSE()) -> 0 | CZ28: =IF(J28=0,0,LEFT(J28,1)) -> 0 | DA28: =IF(K28=0,0,LEFT(K28,1)) -> 0 | DB28: =IF(L28=0,0,LEFT(L28,1)) -> 0 | DC28: =IF(M28=0,0,LEFT(M28,1)) -> 0 | DD28: =IF(N28=0,0,LEFT(N28,1)) -> 0 | DE28: =IF(O28=0,0,LEFT(O28,1)) -> 0 | DF28: =IF(P28=0,0,LEFT(P28,1)) -> 0 | DG28: =IF(Q28=0,0,LEFT(Q28,1)) -> 0 | ... DN28: =IF(X28=0,0,LEFT(X28,1)) -> 0 | EF28: =VLOOKUP(J28,MATERIAL,9,FALSE()) -> 0 | EG28: =VLOOKUP(K28,MATERIAL,9,FALSE()) -> 0 | EH28: =VLOOKUP(L28,MATERIAL,9,FALSE()) -> 0 | EI28: =VLOOKUP(M28,MATERIAL,9,FALSE()) -> 0 | EJ28: =VLOOKUP(N28,MATERIAL,9,FALSE()) -> 0 | EK28: =VLOOKUP(O28,MATERIAL,9,FALSE()) -> 0 | EL28: =VLOOKUP(P28,MATERIAL,9,FALSE()) -> 0 | EM28: =VLOOKUP(Q28,MATERIAL,9,FALSE()) -> 0 | ... ET28: =VLOOKUP(X28,MATERIAL,9,FALSE()) -> 0 | EU28: =IF($B28="",0,VLOOKUP($B28,ITEMS,EU$2,FALSE())) -> 0 | EV28: =VLOOKUP(EU28,MWS,2) -> 0 | EW28: =VLOOKUP(EU28,MWS,3) -> 0
A29: =EV29 -> 0 | D29: Legs | E29: =DW36*5 -> 0 | F29: =IF(DW40=1,"Too many layers!",IF(DW37=1,"Too much padding!",IF(OR(DW38=1,DW39=1),"Illegal combination of layers",""))) | J29: =IF($B29="",0,VLOOKUP($B29,ITEMS,J$2,FALSE())) -> 0 | K29: =IF($B29="",0,VLOOKUP($B29,ITEMS,K$2,FALSE())) -> 0 | L29: =IF($B29="",0,VLOOKUP($B29,ITEMS,L$2,FALSE())) -> 0 | M29: =IF($B29="",0,VLOOKUP($B29,ITEMS,M$2,FALSE())) -> 0 | N29: =IF($B29="",0,VLOOKUP($B29,ITEMS,N$2,FALSE())) -> 0 | O29: =IF($B29="",0,VLOOKUP($B29,ITEMS,O$2,FALSE())) -> 0 | P29: =IF($B29="",0,VLOOKUP($B29,ITEMS,P$2,FALSE())) -> 0 | Q29: =IF($B29="",0,VLOOKUP($B29,ITEMS,Q$2,FALSE())) -> 0 | ... X29: =IF($B29="",0,VLOOKUP($B29,ITEMS,X$2,FALSE())) -> 0 | Y29: =IF($B29="",0,VLOOKUP($B29,ITEMS,17,FALSE())) -> 0 | Z29: =IF($B29="",0,VLOOKUP($B29,ITEMS,18,FALSE())) -> 0 | AA29: =IF($B29="",0,VLOOKUP($B29,ITEMS,19,FALSE())) -> 0 | AB29: =IF($B29="",0,VLOOKUP($B29,ITEMS,20,FALSE())) -> 0 | AC29: =VLOOKUP(J29,MATERIAL,5,FALSE())+IF(J29=0,0,$EW29) -> 0 | AD29: =VLOOKUP(K29,MATERIAL,5,FALSE())+IF(K29=0,0,$EW29) -> 0 | AE29: =VLOOKUP(L29,MATERIAL,5,FALSE())+IF(L29=0,0,$EW29) -> 0 | AF29: =VLOOKUP(M29,MATERIAL,5,FALSE())+IF(M29=0,0,$EW29) -> 0 | AG29: =VLOOKUP(N29,MATERIAL,5,FALSE())+IF(N29=0,0,$EW29) -> 0 | AH29: =VLOOKUP(O29,MATERIAL,5,FALSE())+IF(O29=0,0,$EW29) -> 0 | AI29: =VLOOKUP(P29,MATERIAL,5,FALSE())+IF(P29=0,0,$EW29) -> 0 | AJ29: =VLOOKUP(Q29,MATERIAL,5,FALSE())+IF(Q29=0,0,$EW29) -> 0 | ... AQ29: =VLOOKUP(X29,MATERIAL,5,FALSE())+IF(X29=0,0,$EW29) -> 0 | AR29: =VLOOKUP(J29,MATERIAL,6,FALSE())+IF(J29=0,0,$EW29) -> 0 | AS29: =VLOOKUP(K29,MATERIAL,6,FALSE())+IF(K29=0,0,$EW29) -> 0 | AT29: =VLOOKUP(L29,MATERIAL,6,FALSE())+IF(L29=0,0,$EW29) -> 0 | AU29: =VLOOKUP(M29,MATERIAL,6,FALSE())+IF(M29=0,0,$EW29) -> 0 | AV29: =VLOOKUP(N29,MATERIAL,6,FALSE())+IF(N29=0,0,$EW29) -> 0 | AW29: =VLOOKUP(O29,MATERIAL,6,FALSE())+IF(O29=0,0,$EW29) -> 0 | AX29: =VLOOKUP(P29,MATERIAL,6,FALSE())+IF(P29=0,0,$EW29) -> 0 | AY29: =VLOOKUP(Q29,MATERIAL,6,FALSE())+IF(Q29=0,0,$EW29) -> 0 | ... BF29: =VLOOKUP(X29,MATERIAL,6,FALSE())+IF(X29=0,0,$EW29) -> 0 | BG29: =VLOOKUP(J29,MATERIAL,7,FALSE())+IF(J29=0,0,$EW29) -> 0 | BH29: =VLOOKUP(K29,MATERIAL,7,FALSE())+IF(K29=0,0,$EW29) -> 0 | BI29: =VLOOKUP(L29,MATERIAL,7,FALSE())+IF(L29=0,0,$EW29) -> 0 | BJ29: =VLOOKUP(M29,MATERIAL,7,FALSE())+IF(M29=0,0,$EW29) -> 0 | BK29: =VLOOKUP(N29,MATERIAL,7,FALSE())+IF(N29=0,0,$EW29) -> 0 | BL29: =VLOOKUP(O29,MATERIAL,7,FALSE())+IF(O29=0,0,$EW29) -> 0 | BM29: =VLOOKUP(P29,MATERIAL,7,FALSE())+IF(P29=0,0,$EW29) -> 0 | BN29: =VLOOKUP(Q29,MATERIAL,7,FALSE())+IF(Q29=0,0,$EW29) -> 0 | ... BU29: =VLOOKUP(X29,MATERIAL,7,FALSE())+IF(X29=0,0,$EW29) -> 0 | BV29: =VLOOKUP(J29,MATERIAL,8,FALSE())+IF(J29=0,0,$EW29) -> 0 | BW29: =VLOOKUP(K29,MATERIAL,8,FALSE())+IF(K29=0,0,$EW29) -> 0 | BX29: =VLOOKUP(L29,MATERIAL,8,FALSE())+IF(L29=0,0,$EW29) -> 0 | BY29: =VLOOKUP(M29,MATERIAL,8,FALSE())+IF(M29=0,0,$EW29) -> 0 | BZ29: =VLOOKUP(N29,MATERIAL,8,FALSE())+IF(N29=0,0,$EW29) -> 0 | CA29: =VLOOKUP(O29,MATERIAL,8,FALSE())+IF(O29=0,0,$EW29) -> 0 | CB29: =VLOOKUP(P29,MATERIAL,8,FALSE())+IF(P29=0,0,$EW29) -> 0 | CC29: =VLOOKUP(Q29,MATERIAL,8,FALSE())+IF(Q29=0,0,$EW29) -> 0 | ... CJ29: =VLOOKUP(X29,MATERIAL,8,FALSE())+IF(X29=0,0,$EW29) -> 0 | CK29: =VLOOKUP(J29,MATERIAL,4,FALSE()) -> 0 | CL29: =VLOOKUP(K29,MATERIAL,4,FALSE()) -> 0 | CM29: =VLOOKUP(L29,MATERIAL,4,FALSE()) -> 0 | CN29: =VLOOKUP(M29,MATERIAL,4,FALSE()) -> 0 | CO29: =VLOOKUP(N29,MATERIAL,4,FALSE()) -> 0 | CP29: =VLOOKUP(O29,MATERIAL,4,FALSE()) -> 0 | CQ29: =VLOOKUP(P29,MATERIAL,4,FALSE()) -> 0 | CR29: =VLOOKUP(Q29,MATERIAL,4,FALSE()) -> 0 | ... CY29: =VLOOKUP(X29,MATERIAL,4,FALSE()) -> 0 | CZ29: =IF(J29=0,0,LEFT(J29,1)) -> 0 | DA29: =IF(K29=0,0,LEFT(K29,1)) -> 0 | DB29: =IF(L29=0,0,LEFT(L29,1)) -> 0 | DC29: =IF(M29=0,0,LEFT(M29,1)) -> 0 | DD29: =IF(N29=0,0,LEFT(N29,1)) -> 0 | DE29: =IF(O29=0,0,LEFT(O29,1)) -> 0 | DF29: =IF(P29=0,0,LEFT(P29,1)) -> 0 | DG29: =IF(Q29=0,0,LEFT(Q29,1)) -> 0 | ... DN29: =IF(X29=0,0,LEFT(X29,1)) -> 0 | DT29: H | DU29: A | DV29: T | DW29: L | DX29: Lim | DZ29: Blk | EF29: =VLOOKUP(J29,MATERIAL,9,FALSE()) -> 0 | EG29: =VLOOKUP(K29,MATERIAL,9,FALSE()) -> 0 | EH29: =VLOOKUP(L29,MATERIAL,9,FALSE()) -> 0 | EI29: =VLOOKUP(M29,MATERIAL,9,FALSE()) -> 0 | EJ29: =VLOOKUP(N29,MATERIAL,9,FALSE()) -> 0 | EK29: =VLOOKUP(O29,MATERIAL,9,FALSE()) -> 0 | EL29: =VLOOKUP(P29,MATERIAL,9,FALSE()) -> 0 | EM29: =VLOOKUP(Q29,MATERIAL,9,FALSE()) -> 0 | ... ET29: =VLOOKUP(X29,MATERIAL,9,FALSE()) -> 0 | EU29: =IF($B29="",0,VLOOKUP($B29,ITEMS,EU$2,FALSE())) -> 0 | EV29: =VLOOKUP(EU29,MWS,2) -> 0 | EW29: =VLOOKUP(EU29,MWS,3) -> 0
A30: =EV30 -> 0 | J30: =IF($B30="",0,VLOOKUP($B30,ITEMS,J$2,FALSE())) -> 0 | K30: =IF($B30="",0,VLOOKUP($B30,ITEMS,K$2,FALSE())) -> 0 | L30: =IF($B30="",0,VLOOKUP($B30,ITEMS,L$2,FALSE())) -> 0 | M30: =IF($B30="",0,VLOOKUP($B30,ITEMS,M$2,FALSE())) -> 0 | N30: =IF($B30="",0,VLOOKUP($B30,ITEMS,N$2,FALSE())) -> 0 | O30: =IF($B30="",0,VLOOKUP($B30,ITEMS,O$2,FALSE())) -> 0 | P30: =IF($B30="",0,VLOOKUP($B30,ITEMS,P$2,FALSE())) -> 0 | Q30: =IF($B30="",0,VLOOKUP($B30,ITEMS,Q$2,FALSE())) -> 0 | ... X30: =IF($B30="",0,VLOOKUP($B30,ITEMS,X$2,FALSE())) -> 0 | Y30: =IF($B30="",0,VLOOKUP($B30,ITEMS,17,FALSE())) -> 0 | Z30: =IF($B30="",0,VLOOKUP($B30,ITEMS,18,FALSE())) -> 0 | AA30: =IF($B30="",0,VLOOKUP($B30,ITEMS,19,FALSE())) -> 0 | AB30: =IF($B30="",0,VLOOKUP($B30,ITEMS,20,FALSE())) -> 0 | AC30: =VLOOKUP(J30,MATERIAL,5,FALSE())+IF(J30=0,0,$EW30) -> 0 | AD30: =VLOOKUP(K30,MATERIAL,5,FALSE())+IF(K30=0,0,$EW30) -> 0 | AE30: =VLOOKUP(L30,MATERIAL,5,FALSE())+IF(L30=0,0,$EW30) -> 0 | AF30: =VLOOKUP(M30,MATERIAL,5,FALSE())+IF(M30=0,0,$EW30) -> 0 | AG30: =VLOOKUP(N30,MATERIAL,5,FALSE())+IF(N30=0,0,$EW30) -> 0 | AH30: =VLOOKUP(O30,MATERIAL,5,FALSE())+IF(O30=0,0,$EW30) -> 0 | AI30: =VLOOKUP(P30,MATERIAL,5,FALSE())+IF(P30=0,0,$EW30) -> 0 | AJ30: =VLOOKUP(Q30,MATERIAL,5,FALSE())+IF(Q30=0,0,$EW30) -> 0 | ... AQ30: =VLOOKUP(X30,MATERIAL,5,FALSE())+IF(X30=0,0,$EW30) -> 0 | AR30: =VLOOKUP(J30,MATERIAL,6,FALSE())+IF(J30=0,0,$EW30) -> 0 | AS30: =VLOOKUP(K30,MATERIAL,6,FALSE())+IF(K30=0,0,$EW30) -> 0 | AT30: =VLOOKUP(L30,MATERIAL,6,FALSE())+IF(L30=0,0,$EW30) -> 0 | AU30: =VLOOKUP(M30,MATERIAL,6,FALSE())+IF(M30=0,0,$EW30) -> 0 | AV30: =VLOOKUP(N30,MATERIAL,6,FALSE())+IF(N30=0,0,$EW30) -> 0 | AW30: =VLOOKUP(O30,MATERIAL,6,FALSE())+IF(O30=0,0,$EW30) -> 0 | AX30: =VLOOKUP(P30,MATERIAL,6,FALSE())+IF(P30=0,0,$EW30) -> 0 | AY30: =VLOOKUP(Q30,MATERIAL,6,FALSE())+IF(Q30=0,0,$EW30) -> 0 | ... BF30: =VLOOKUP(X30,MATERIAL,6,FALSE())+IF(X30=0,0,$EW30) -> 0 | BG30: =VLOOKUP(J30,MATERIAL,7,FALSE())+IF(J30=0,0,$EW30) -> 0 | BH30: =VLOOKUP(K30,MATERIAL,7,FALSE())+IF(K30=0,0,$EW30) -> 0 | BI30: =VLOOKUP(L30,MATERIAL,7,FALSE())+IF(L30=0,0,$EW30) -> 0 | BJ30: =VLOOKUP(M30,MATERIAL,7,FALSE())+IF(M30=0,0,$EW30) -> 0 | BK30: =VLOOKUP(N30,MATERIAL,7,FALSE())+IF(N30=0,0,$EW30) -> 0 | BL30: =VLOOKUP(O30,MATERIAL,7,FALSE())+IF(O30=0,0,$EW30) -> 0 | BM30: =VLOOKUP(P30,MATERIAL,7,FALSE())+IF(P30=0,0,$EW30) -> 0 | BN30: =VLOOKUP(Q30,MATERIAL,7,FALSE())+IF(Q30=0,0,$EW30) -> 0 | ... BU30: =VLOOKUP(X30,MATERIAL,7,FALSE())+IF(X30=0,0,$EW30) -> 0 | BV30: =VLOOKUP(J30,MATERIAL,8,FALSE())+IF(J30=0,0,$EW30) -> 0 | BW30: =VLOOKUP(K30,MATERIAL,8,FALSE())+IF(K30=0,0,$EW30) -> 0 | BX30: =VLOOKUP(L30,MATERIAL,8,FALSE())+IF(L30=0,0,$EW30) -> 0 | BY30: =VLOOKUP(M30,MATERIAL,8,FALSE())+IF(M30=0,0,$EW30) -> 0 | BZ30: =VLOOKUP(N30,MATERIAL,8,FALSE())+IF(N30=0,0,$EW30) -> 0 | CA30: =VLOOKUP(O30,MATERIAL,8,FALSE())+IF(O30=0,0,$EW30) -> 0 | CB30: =VLOOKUP(P30,MATERIAL,8,FALSE())+IF(P30=0,0,$EW30) -> 0 | CC30: =VLOOKUP(Q30,MATERIAL,8,FALSE())+IF(Q30=0,0,$EW30) -> 0 | ... CJ30: =VLOOKUP(X30,MATERIAL,8,FALSE())+IF(X30=0,0,$EW30) -> 0 | CK30: =VLOOKUP(J30,MATERIAL,4,FALSE()) -> 0 | CL30: =VLOOKUP(K30,MATERIAL,4,FALSE()) -> 0 | CM30: =VLOOKUP(L30,MATERIAL,4,FALSE()) -> 0 | CN30: =VLOOKUP(M30,MATERIAL,4,FALSE()) -> 0 | CO30: =VLOOKUP(N30,MATERIAL,4,FALSE()) -> 0 | CP30: =VLOOKUP(O30,MATERIAL,4,FALSE()) -> 0 | CQ30: =VLOOKUP(P30,MATERIAL,4,FALSE()) -> 0 | CR30: =VLOOKUP(Q30,MATERIAL,4,FALSE()) -> 0 | ... CY30: =VLOOKUP(X30,MATERIAL,4,FALSE()) -> 0 | CZ30: =IF(J30=0,0,LEFT(J30,1)) -> 0 | DA30: =IF(K30=0,0,LEFT(K30,1)) -> 0 | DB30: =IF(L30=0,0,LEFT(L30,1)) -> 0 | DC30: =IF(M30=0,0,LEFT(M30,1)) -> 0 | DD30: =IF(N30=0,0,LEFT(N30,1)) -> 0 | DE30: =IF(O30=0,0,LEFT(O30,1)) -> 0 | DF30: =IF(P30=0,0,LEFT(P30,1)) -> 0 | DG30: =IF(Q30=0,0,LEFT(Q30,1)) -> 0 | ... DN30: =IF(X30=0,0,LEFT(X30,1)) -> 0 | DR30: Total | DT30: =MAX(DO14:DQ14) -> 2.5 | DU30: =MAX(DR14:DV14) -> 3.5 | DV30: =MAX(DW14:DY14) -> 4.5 | DW30: =MAX(DZ14:EC14) -> 4.5 | EA30: =SUM(DR9:DV9)+SUM(DR12:DV12)+DV11+DV10 -> 0 | EB30: Arm Pieces | EF30: =VLOOKUP(J30,MATERIAL,9,FALSE()) -> 0 | EG30: =VLOOKUP(K30,MATERIAL,9,FALSE()) -> 0 | EH30: =VLOOKUP(L30,MATERIAL,9,FALSE()) -> 0 | EI30: =VLOOKUP(M30,MATERIAL,9,FALSE()) -> 0 | EJ30: =VLOOKUP(N30,MATERIAL,9,FALSE()) -> 0 | EK30: =VLOOKUP(O30,MATERIAL,9,FALSE()) -> 0 | EL30: =VLOOKUP(P30,MATERIAL,9,FALSE()) -> 0 | EM30: =VLOOKUP(Q30,MATERIAL,9,FALSE()) -> 0 | ... ET30: =VLOOKUP(X30,MATERIAL,9,FALSE()) -> 0 | EU30: =IF($B30="",0,VLOOKUP($B30,ITEMS,EU$2,FALSE())) -> 0 | EV30: =VLOOKUP(EU30,MWS,2) -> 0 | EW30: =VLOOKUP(EU30,MWS,3) -> 0
A31: =EV31 -> 0 | J31: =IF($B31="",0,VLOOKUP($B31,ITEMS,J$2,FALSE())) -> 0 | K31: =IF($B31="",0,VLOOKUP($B31,ITEMS,K$2,FALSE())) -> 0 | L31: =IF($B31="",0,VLOOKUP($B31,ITEMS,L$2,FALSE())) -> 0 | M31: =IF($B31="",0,VLOOKUP($B31,ITEMS,M$2,FALSE())) -> 0 | N31: =IF($B31="",0,VLOOKUP($B31,ITEMS,N$2,FALSE())) -> 0 | O31: =IF($B31="",0,VLOOKUP($B31,ITEMS,O$2,FALSE())) -> 0 | P31: =IF($B31="",0,VLOOKUP($B31,ITEMS,P$2,FALSE())) -> 0 | Q31: =IF($B31="",0,VLOOKUP($B31,ITEMS,Q$2,FALSE())) -> 0 | ... X31: =IF($B31="",0,VLOOKUP($B31,ITEMS,X$2,FALSE())) -> 0 | Y31: =IF($B31="",0,VLOOKUP($B31,ITEMS,17,FALSE())) -> 0 | Z31: =IF($B31="",0,VLOOKUP($B31,ITEMS,18,FALSE())) -> 0 | AA31: =IF($B31="",0,VLOOKUP($B31,ITEMS,19,FALSE())) -> 0 | AB31: =IF($B31="",0,VLOOKUP($B31,ITEMS,20,FALSE())) -> 0 | AC31: =VLOOKUP(J31,MATERIAL,5,FALSE())+IF(J31=0,0,$EW31) -> 0 | AD31: =VLOOKUP(K31,MATERIAL,5,FALSE())+IF(K31=0,0,$EW31) -> 0 | AE31: =VLOOKUP(L31,MATERIAL,5,FALSE())+IF(L31=0,0,$EW31) -> 0 | AF31: =VLOOKUP(M31,MATERIAL,5,FALSE())+IF(M31=0,0,$EW31) -> 0 | AG31: =VLOOKUP(N31,MATERIAL,5,FALSE())+IF(N31=0,0,$EW31) -> 0 | AH31: =VLOOKUP(O31,MATERIAL,5,FALSE())+IF(O31=0,0,$EW31) -> 0 | AI31: =VLOOKUP(P31,MATERIAL,5,FALSE())+IF(P31=0,0,$EW31) -> 0 | AJ31: =VLOOKUP(Q31,MATERIAL,5,FALSE())+IF(Q31=0,0,$EW31) -> 0 | ... AQ31: =VLOOKUP(X31,MATERIAL,5,FALSE())+IF(X31=0,0,$EW31) -> 0 | AR31: =VLOOKUP(J31,MATERIAL,6,FALSE())+IF(J31=0,0,$EW31) -> 0 | AS31: =VLOOKUP(K31,MATERIAL,6,FALSE())+IF(K31=0,0,$EW31) -> 0 | AT31: =VLOOKUP(L31,MATERIAL,6,FALSE())+IF(L31=0,0,$EW31) -> 0 | AU31: =VLOOKUP(M31,MATERIAL,6,FALSE())+IF(M31=0,0,$EW31) -> 0 | AV31: =VLOOKUP(N31,MATERIAL,6,FALSE())+IF(N31=0,0,$EW31) -> 0 | AW31: =VLOOKUP(O31,MATERIAL,6,FALSE())+IF(O31=0,0,$EW31) -> 0 | AX31: =VLOOKUP(P31,MATERIAL,6,FALSE())+IF(P31=0,0,$EW31) -> 0 | AY31: =VLOOKUP(Q31,MATERIAL,6,FALSE())+IF(Q31=0,0,$EW31) -> 0 | ... BF31: =VLOOKUP(X31,MATERIAL,6,FALSE())+IF(X31=0,0,$EW31) -> 0 | BG31: =VLOOKUP(J31,MATERIAL,7,FALSE())+IF(J31=0,0,$EW31) -> 0 | BH31: =VLOOKUP(K31,MATERIAL,7,FALSE())+IF(K31=0,0,$EW31) -> 0 | BI31: =VLOOKUP(L31,MATERIAL,7,FALSE())+IF(L31=0,0,$EW31) -> 0 | BJ31: =VLOOKUP(M31,MATERIAL,7,FALSE())+IF(M31=0,0,$EW31) -> 0 | BK31: =VLOOKUP(N31,MATERIAL,7,FALSE())+IF(N31=0,0,$EW31) -> 0 | BL31: =VLOOKUP(O31,MATERIAL,7,FALSE())+IF(O31=0,0,$EW31) -> 0 | BM31: =VLOOKUP(P31,MATERIAL,7,FALSE())+IF(P31=0,0,$EW31) -> 0 | BN31: =VLOOKUP(Q31,MATERIAL,7,FALSE())+IF(Q31=0,0,$EW31) -> 0 | ... BU31: =VLOOKUP(X31,MATERIAL,7,FALSE())+IF(X31=0,0,$EW31) -> 0 | BV31: =VLOOKUP(J31,MATERIAL,8,FALSE())+IF(J31=0,0,$EW31) -> 0 | BW31: =VLOOKUP(K31,MATERIAL,8,FALSE())+IF(K31=0,0,$EW31) -> 0 | BX31: =VLOOKUP(L31,MATERIAL,8,FALSE())+IF(L31=0,0,$EW31) -> 0 | BY31: =VLOOKUP(M31,MATERIAL,8,FALSE())+IF(M31=0,0,$EW31) -> 0 | BZ31: =VLOOKUP(N31,MATERIAL,8,FALSE())+IF(N31=0,0,$EW31) -> 0 | CA31: =VLOOKUP(O31,MATERIAL,8,FALSE())+IF(O31=0,0,$EW31) -> 0 | CB31: =VLOOKUP(P31,MATERIAL,8,FALSE())+IF(P31=0,0,$EW31) -> 0 | CC31: =VLOOKUP(Q31,MATERIAL,8,FALSE())+IF(Q31=0,0,$EW31) -> 0 | ... CJ31: =VLOOKUP(X31,MATERIAL,8,FALSE())+IF(X31=0,0,$EW31) -> 0 | CK31: =VLOOKUP(J31,MATERIAL,4,FALSE()) -> 0 | CL31: =VLOOKUP(K31,MATERIAL,4,FALSE()) -> 0 | CM31: =VLOOKUP(L31,MATERIAL,4,FALSE()) -> 0 | CN31: =VLOOKUP(M31,MATERIAL,4,FALSE()) -> 0 | CO31: =VLOOKUP(N31,MATERIAL,4,FALSE()) -> 0 | CP31: =VLOOKUP(O31,MATERIAL,4,FALSE()) -> 0 | CQ31: =VLOOKUP(P31,MATERIAL,4,FALSE()) -> 0 | CR31: =VLOOKUP(Q31,MATERIAL,4,FALSE()) -> 0 | ... CY31: =VLOOKUP(X31,MATERIAL,4,FALSE()) -> 0 | CZ31: =IF(J31=0,0,LEFT(J31,1)) -> 0 | DA31: =IF(K31=0,0,LEFT(K31,1)) -> 0 | DB31: =IF(L31=0,0,LEFT(L31,1)) -> 0 | DC31: =IF(M31=0,0,LEFT(M31,1)) -> 0 | DD31: =IF(N31=0,0,LEFT(N31,1)) -> 0 | DE31: =IF(O31=0,0,LEFT(O31,1)) -> 0 | DF31: =IF(P31=0,0,LEFT(P31,1)) -> 0 | DG31: =IF(Q31=0,0,LEFT(Q31,1)) -> 0 | ... DN31: =IF(X31=0,0,LEFT(X31,1)) -> 0 | DR31: Padded | DT31: =MAX(DO15:DQ15) -> 1 | DU31: =MAX(DR15:DV15) -> 1 | DV31: =MAX(DW15:DY15) -> 1 | DW31: =MAX(DZ15:EC15) -> 1 | DX31: 5 | DY31: =IF(MAX(DT31:DW31)>DX31,1,0) -> 0 | DZ31: 3 | EF31: =VLOOKUP(J31,MATERIAL,9,FALSE()) -> 0 | EG31: =VLOOKUP(K31,MATERIAL,9,FALSE()) -> 0 | EH31: =VLOOKUP(L31,MATERIAL,9,FALSE()) -> 0 | EI31: =VLOOKUP(M31,MATERIAL,9,FALSE()) -> 0 | EJ31: =VLOOKUP(N31,MATERIAL,9,FALSE()) -> 0 | EK31: =VLOOKUP(O31,MATERIAL,9,FALSE()) -> 0 | EL31: =VLOOKUP(P31,MATERIAL,9,FALSE()) -> 0 | EM31: =VLOOKUP(Q31,MATERIAL,9,FALSE()) -> 0 | ... ET31: =VLOOKUP(X31,MATERIAL,9,FALSE()) -> 0 | EU31: =IF($B31="",0,VLOOKUP($B31,ITEMS,EU$2,FALSE())) -> 0 | EV31: =VLOOKUP(EU31,MWS,2) -> 0 | EW31: =VLOOKUP(EU31,MWS,3) -> 0
A32: =EV32 -> 0 | J32: =IF($B32="",0,VLOOKUP($B32,ITEMS,J$2,FALSE())) -> 0 | K32: =IF($B32="",0,VLOOKUP($B32,ITEMS,K$2,FALSE())) -> 0 | L32: =IF($B32="",0,VLOOKUP($B32,ITEMS,L$2,FALSE())) -> 0 | M32: =IF($B32="",0,VLOOKUP($B32,ITEMS,M$2,FALSE())) -> 0 | N32: =IF($B32="",0,VLOOKUP($B32,ITEMS,N$2,FALSE())) -> 0 | O32: =IF($B32="",0,VLOOKUP($B32,ITEMS,O$2,FALSE())) -> 0 | P32: =IF($B32="",0,VLOOKUP($B32,ITEMS,P$2,FALSE())) -> 0 | Q32: =IF($B32="",0,VLOOKUP($B32,ITEMS,Q$2,FALSE())) -> 0 | ... X32: =IF($B32="",0,VLOOKUP($B32,ITEMS,X$2,FALSE())) -> 0 | Y32: =IF($B32="",0,VLOOKUP($B32,ITEMS,17,FALSE())) -> 0 | Z32: =IF($B32="",0,VLOOKUP($B32,ITEMS,18,FALSE())) -> 0 | AA32: =IF($B32="",0,VLOOKUP($B32,ITEMS,19,FALSE())) -> 0 | AB32: =IF($B32="",0,VLOOKUP($B32,ITEMS,20,FALSE())) -> 0 | AC32: =VLOOKUP(J32,MATERIAL,5,FALSE())+IF(J32=0,0,$EW32) -> 0 | AD32: =VLOOKUP(K32,MATERIAL,5,FALSE())+IF(K32=0,0,$EW32) -> 0 | AE32: =VLOOKUP(L32,MATERIAL,5,FALSE())+IF(L32=0,0,$EW32) -> 0 | AF32: =VLOOKUP(M32,MATERIAL,5,FALSE())+IF(M32=0,0,$EW32) -> 0 | AG32: =VLOOKUP(N32,MATERIAL,5,FALSE())+IF(N32=0,0,$EW32) -> 0 | AH32: =VLOOKUP(O32,MATERIAL,5,FALSE())+IF(O32=0,0,$EW32) -> 0 | AI32: =VLOOKUP(P32,MATERIAL,5,FALSE())+IF(P32=0,0,$EW32) -> 0 | AJ32: =VLOOKUP(Q32,MATERIAL,5,FALSE())+IF(Q32=0,0,$EW32) -> 0 | ... AQ32: =VLOOKUP(X32,MATERIAL,5,FALSE())+IF(X32=0,0,$EW32) -> 0 | AR32: =VLOOKUP(J32,MATERIAL,6,FALSE())+IF(J32=0,0,$EW32) -> 0 | AS32: =VLOOKUP(K32,MATERIAL,6,FALSE())+IF(K32=0,0,$EW32) -> 0 | AT32: =VLOOKUP(L32,MATERIAL,6,FALSE())+IF(L32=0,0,$EW32) -> 0 | AU32: =VLOOKUP(M32,MATERIAL,6,FALSE())+IF(M32=0,0,$EW32) -> 0 | AV32: =VLOOKUP(N32,MATERIAL,6,FALSE())+IF(N32=0,0,$EW32) -> 0 | AW32: =VLOOKUP(O32,MATERIAL,6,FALSE())+IF(O32=0,0,$EW32) -> 0 | AX32: =VLOOKUP(P32,MATERIAL,6,FALSE())+IF(P32=0,0,$EW32) -> 0 | AY32: =VLOOKUP(Q32,MATERIAL,6,FALSE())+IF(Q32=0,0,$EW32) -> 0 | ... BF32: =VLOOKUP(X32,MATERIAL,6,FALSE())+IF(X32=0,0,$EW32) -> 0 | BG32: =VLOOKUP(J32,MATERIAL,7,FALSE())+IF(J32=0,0,$EW32) -> 0 | BH32: =VLOOKUP(K32,MATERIAL,7,FALSE())+IF(K32=0,0,$EW32) -> 0 | BI32: =VLOOKUP(L32,MATERIAL,7,FALSE())+IF(L32=0,0,$EW32) -> 0 | BJ32: =VLOOKUP(M32,MATERIAL,7,FALSE())+IF(M32=0,0,$EW32) -> 0 | BK32: =VLOOKUP(N32,MATERIAL,7,FALSE())+IF(N32=0,0,$EW32) -> 0 | BL32: =VLOOKUP(O32,MATERIAL,7,FALSE())+IF(O32=0,0,$EW32) -> 0 | BM32: =VLOOKUP(P32,MATERIAL,7,FALSE())+IF(P32=0,0,$EW32) -> 0 | BN32: =VLOOKUP(Q32,MATERIAL,7,FALSE())+IF(Q32=0,0,$EW32) -> 0 | ... BU32: =VLOOKUP(X32,MATERIAL,7,FALSE())+IF(X32=0,0,$EW32) -> 0 | BV32: =VLOOKUP(J32,MATERIAL,8,FALSE())+IF(J32=0,0,$EW32) -> 0 | BW32: =VLOOKUP(K32,MATERIAL,8,FALSE())+IF(K32=0,0,$EW32) -> 0 | BX32: =VLOOKUP(L32,MATERIAL,8,FALSE())+IF(L32=0,0,$EW32) -> 0 | BY32: =VLOOKUP(M32,MATERIAL,8,FALSE())+IF(M32=0,0,$EW32) -> 0 | BZ32: =VLOOKUP(N32,MATERIAL,8,FALSE())+IF(N32=0,0,$EW32) -> 0 | CA32: =VLOOKUP(O32,MATERIAL,8,FALSE())+IF(O32=0,0,$EW32) -> 0 | CB32: =VLOOKUP(P32,MATERIAL,8,FALSE())+IF(P32=0,0,$EW32) -> 0 | CC32: =VLOOKUP(Q32,MATERIAL,8,FALSE())+IF(Q32=0,0,$EW32) -> 0 | ... CJ32: =VLOOKUP(X32,MATERIAL,8,FALSE())+IF(X32=0,0,$EW32) -> 0 | CK32: =VLOOKUP(J32,MATERIAL,4,FALSE()) -> 0 | CL32: =VLOOKUP(K32,MATERIAL,4,FALSE()) -> 0 | CM32: =VLOOKUP(L32,MATERIAL,4,FALSE()) -> 0 | CN32: =VLOOKUP(M32,MATERIAL,4,FALSE()) -> 0 | CO32: =VLOOKUP(N32,MATERIAL,4,FALSE()) -> 0 | CP32: =VLOOKUP(O32,MATERIAL,4,FALSE()) -> 0 | CQ32: =VLOOKUP(P32,MATERIAL,4,FALSE()) -> 0 | CR32: =VLOOKUP(Q32,MATERIAL,4,FALSE()) -> 0 | ... CY32: =VLOOKUP(X32,MATERIAL,4,FALSE()) -> 0 | CZ32: =IF(J32=0,0,LEFT(J32,1)) -> 0 | DA32: =IF(K32=0,0,LEFT(K32,1)) -> 0 | DB32: =IF(L32=0,0,LEFT(L32,1)) -> 0 | DC32: =IF(M32=0,0,LEFT(M32,1)) -> 0 | DD32: =IF(N32=0,0,LEFT(N32,1)) -> 0 | DE32: =IF(O32=0,0,LEFT(O32,1)) -> 0 | DF32: =IF(P32=0,0,LEFT(P32,1)) -> 0 | DG32: =IF(Q32=0,0,LEFT(Q32,1)) -> 0 | ... DN32: =IF(X32=0,0,LEFT(X32,1)) -> 0 | DR32: Mail | DT32: =MAX(DO16:DQ16) -> 1 | DU32: =MAX(DR16:DV16) -> 0 | DV32: =MAX(DW16:DY16) -> 0 | DW32: =MAX(DZ16:EC16) -> 0 | DX32: 2 | DY32: =IF(MAX(DT32:DW32)>DX32,1,0) -> 0 | EF32: =VLOOKUP(J32,MATERIAL,9,FALSE()) -> 0 | EG32: =VLOOKUP(K32,MATERIAL,9,FALSE()) -> 0 | EH32: =VLOOKUP(L32,MATERIAL,9,FALSE()) -> 0 | EI32: =VLOOKUP(M32,MATERIAL,9,FALSE()) -> 0 | EJ32: =VLOOKUP(N32,MATERIAL,9,FALSE()) -> 0 | EK32: =VLOOKUP(O32,MATERIAL,9,FALSE()) -> 0 | EL32: =VLOOKUP(P32,MATERIAL,9,FALSE()) -> 0 | EM32: =VLOOKUP(Q32,MATERIAL,9,FALSE()) -> 0 | ... ET32: =VLOOKUP(X32,MATERIAL,9,FALSE()) -> 0 | EU32: =IF($B32="",0,VLOOKUP($B32,ITEMS,EU$2,FALSE())) -> 0 | EV32: =VLOOKUP(EU32,MWS,2) -> 0 | EW32: =VLOOKUP(EU32,MWS,3) -> 0
DR33: A | DT33: =MAX(DO17:DQ17) -> 1 | DU33: =MAX(DR18:DV18) -> 1 | DV33: =MAX(DW18:DY18) -> 1 | DW33: =MAX(DZ19:EC19) -> 1 | DX33: 1 | DY33: =IF(MAX(DT33:DW33)>DX33,1,0) -> 0
DR34: B | DT34: 0 | DU34: =MAX(DR21:DV21) -> 0 | DV34: =MAX(DW20:DY20) -> 0 | DW34: =MAX(DZ22:EC22) -> 1 | DX34: 1 | DY34: =IF(MAX(DT34:DW34)>DX34,1,0) -> 0
DR35: C | DT35: 0 | DU35: =MAX(DR22:DV22) -> 0 | DV35: 0 | DW35: 0 | DX35: 1 | DY35: =IF(MAX(DT35:DW35)>DX35,1,0) -> 0
DR36: BLK | DT36: =IF(DT31>$DZ$31,1,0)+MAX(DO27:DQ27) -> 0 | DU36: =IF(DU31>$DZ$31,1,0)+MAX(DS27:DV27) -> 0 | DV36: =IF(DV31>$DZ$31,1,0)+MAX(DW27:DY27) -> 0 | DW36: =IF(DW31>$DZ$31,1,0)+MAX(DZ27:EC27) -> 0 | DY36: =SUM(DO26:EC26)+SUM(DY31:DY35) -> 0
DR37: Padded | DT37: =IF(DT31>$DX$31,1,0) -> 0 | DU37: =IF(DU31>$DX$31,1,0) -> 0 | DV37: =IF(DV31>$DX$31,1,0) -> 0 | DW37: =IF(DW31>$DX$31,1,0) -> 0
DR38: Mail | DT38: =IF(DT32>$DX$32,1,0) -> 0 | DU38: =IF(DU32>$DX$32,1,0) -> 0 | DV38: =IF(DV32>$DX$32,1,0) -> 0 | DW38: =IF(DW32>$DX$32,1,0) -> 0
DR39: ABC | DT39: =IF(OR(DT33>$DX$33,DT34>$DX$34,DT35>$DX$35),1,0) -> 0 | DU39: =IF(OR(DU33>$DX$33,DU34>$DX$34,DU35>$DX$35),1,0) -> 0 | DV39: =IF(OR(DV33>$DX$33,DV34>$DX$34,DV35>$DX$35),1,0) -> 0 | DW39: =IF(OR(DW33>$DX$33,DW34>$DX$34,DW35>$DX$35),1,0) -> 0
DR40: Total | DT40: =IF(SUM(DO26:DQ26)=0,0,1) -> 0 | DU40: =IF(SUM(DR26:DV26)=0,0,1) -> 0 | DV40: =IF(SUM(DW26:DY26)=0,0,1) -> 0 | DW40: =IF(SUM(DZ26:EC26)=0,0,1) -> 0

Sheet Item Builder
A1: Armour Item List | X1: 0.04 | Y1: 0.03 | Z1: 0.02 | AA1: 0.03 | AB1: 0.06 | AC1: 0.02 | AD1: 0.05 | AE1: 0.05 | AF1: 0.12 | AG1: 0.12 | AH1: 0.1 | AI1: 0.14 | AJ1: 0.03 | AK1: 0.12 | AL1: 0.07 | AN1: Armour Types | BG1: Layers | BV1: Prices | CK1: 0.5 | CL1: 0.5 | CM1: 0.5 | CN1: 1.5 | CO1: 1.75 | CP1: 2 | CQ1: 2 | CR1: 1.5 | CS1: 0.7 | CT1: 0.4 | CU1: 1 | CV1: 1.25 | CW1: 1.25 | CX1: 1.25 | CY1: 0.75 | CZ1: 1.5 | DA1: Rigidity | DO1: Hours | ED1: Materials Cost | ET1: Masterwork
B2: Head | E2: Arms | J2: Torso | M2: Legs | S2: 12 | X2: Head | AA2: Arms | AF2: Torso | AI2: Legs | AM2: Total | AN2: Head | AQ2: Arms | AV2: Torso | AY2: Legs | BC2: Coverage | BG2: Head | BJ2: Arms | BO2: Torso | BR2: Legs | BV2: Head | BY2: Arms | CD2: Torso | CG2: Legs | CK2: Head | CN2: Arms | CS2: Torso | CV2: Legs | CZ2: Head | DC2: Arms | DH2: Torso | DK2: Legs | DO2: Head | DR2: Arms | DW2: Torso | DZ2: Legs | ED2: Head | EG2: Arms | EL2: Torso | EO2: Legs | ET2: Head | EW2: Arms | FB2: Torso | FE2: Legs
A3: Item Name | B3: Sk | C3: Fa | D3: Nk | E3: Sh | F3: Ua | G3: El | H3: Fo | I3: Ha | J3: Tx | K3: Ab | L3: Pv | M3: Th | N3: Kn | O3: Cf | P3: Ft | Q3: Price | R3: Weight | S3: ENC | T3: PER | U3: Hours | V3: Cost | W3: MWS | X3: Sk | Y3: Fa | Z3: Nk | AA3: Sh | AB3: Ua | AC3: El | AD3: Fo | AE3: Ha | AF3: Tx | AG3: Ab | AH3: Pv | AI3: Th | AJ3: Kn | AK3: Cf | AL3: Ft | AM3: Coverage | AN3: Sk | AO3: Fa | AP3: Nk | AQ3: Sh | AR3: Ua | AS3: El | AT3: Fo | AU3: Ha | AV3: Tx | AW3: Ab | AX3: Pv | AY3: Th | AZ3: Kn | BA3: Cf | BB3: Ft | BC3: Head | BD3: Arms | BE3: Torso | BF3: Legs | BG3: Sk | BH3: Fa | BI3: Nk | BJ3: Sh | BK3: Ua | BL3: El | BM3: Fo | BN3: Ha | BO3: Tx | BP3: Ab | BQ3: Pv | BR3: Th | BS3: Kn | BT3: Cf | BU3: Ft | BV3: Sk | BW3: Fa | BX3: Nk | BY3: Sh | BZ3: Ua | CA3: El | CB3: Fo | CC3: Ha | CD3: Tx | CE3: Ab | CF3: Pv | CG3: Th | CH3: Kn | CI3: Cf | CJ3: Ft | CK3: Sk | CL3: Fa | CM3: Nk | CN3: Sh | CO3: Ua | CP3: El | CQ3: Fo | CR3: Ha | CS3: Tx | CT3: Ab | CU3: Pv | CV3: Th | CW3: Kn | CX3: Cf | CY3: Ft | CZ3: Sk | DA3: Fa | DB3: Nk | DC3: Sh | DD3: Ua | DE3: El | DF3: Fo | DG3: Ha | DH3: Tx | DI3: Ab | DJ3: Pv | DK3: Th | DL3: Kn | DM3: Cf | DN3: Ft | DO3: Sk | DP3: Fa | DQ3: Nk | DR3: Sh | DS3: Ua | DT3: El | DU3: Fo | DV3: Ha | DW3: Tx | DX3: Ab | DY3: Pv | DZ3: Th | EA3: Kn | EB3: Cf | EC3: Ft | ED3: Sk | EE3: Fa | EF3: Nk | EG3: Sh | EH3: Ua | EI3: El | EJ3: Fo | EK3: Ha | EL3: Tx | EM3: Ab | EN3: Pv | EO3: Th | EP3: Kn | EQ3: Cf | ER3: Ft | ES3: MWS | ET3: Sk | EU3: Fa | EV3: Nk | EW3: Sh | EX3: Ua | EY3: El | EZ3: Fo | FA3: Ha | FB3: Tx | FC3: Ab | FD3: Pv | FE3: Th | FF3: Kn | FG3: Cf | FH3: Ft | FJ3: Supported Materials
A4: Buckram Cap | B4: C | Q4: =SUM(BV4:CJ4)*VLOOKUP(W4,Tables!$W$3:$Z$8,4) -> 4 | R4: =SUM(CK4:CY4) -> 0.2 | S4: =ROUND(SUMPRODUCT(CK4:CY4,CZ4:DN4,$CK$1:$CY$1)/$S$2,0)*5 -> 0 | T4: =IF(OR(B4="",D4=""),0,5)+IF(C4="",0,5) -> 0 | U4: =SUM(DO4:EC4) -> 0.8 | V4: =SUM(ED4:ER4) -> 3.2 | W4: 0 | X4: =COUNTA(B4) -> 1 | Y4: =COUNTA(C4) -> 0 | Z4: =COUNTA(D4) -> 0 | AA4: =COUNTA(E4) -> 0 | AB4: =COUNTA(F4) -> 0 | AC4: =COUNTA(G4) -> 0 | AD4: =COUNTA(H4) -> 0 | AE4: =COUNTA(I4) -> 0 | ... AL4: =COUNTA(P4) -> 0 | AM4: =SUMPRODUCT(X4:AL4,$X$1:$AL$1) -> 0.04 | AN4: =LEFT(B4,1) -> C | AO4: =LEFT(C4,1) | AP4: =LEFT(D4,1) | AQ4: =LEFT(E4,1) | AR4: =LEFT(F4,1) | AS4: =LEFT(G4,1) | AT4: =LEFT(H4,1) | AU4: =LEFT(I4,1) | ... BB4: =LEFT(P4,1) | BC4: =SUMPRODUCT(X4:Z4,$X$1:$Z$1)/SUM($X$1:$Z$1) -> 0.44444444 | BD4: =SUMPRODUCT(AA4:AE4,$AA$1:$AE$1)/SUM($AA$1:$AE$1) -> 0 | BE4: =SUMPRODUCT(AF4:AH4,$AF$1:$AH$1)/SUM($AF$1:$AH$1) -> 0 | BF4: =SUMPRODUCT(AI4:AL4,$AI$1:$AL$1)/SUM($AI$1:$AL$1) -> 0 | BG4: =IF(AN4="",0,VLOOKUP(AN4,Tables!$AB$3:$AC$12,2)) -> 1 | BH4: =IF(AO4="",0,VLOOKUP(AO4,Tables!$AB$3:$AC$12,2)) -> 0 | BI4: =IF(AP4="",0,VLOOKUP(AP4,Tables!$AB$3:$AC$12,2)) -> 0 | BJ4: =IF(AQ4="",0,VLOOKUP(AQ4,Tables!$AB$3:$AC$12,2)) -> 0 | BK4: =IF(AR4="",0,VLOOKUP(AR4,Tables!$AB$3:$AC$12,2)) -> 0 | BL4: =IF(AS4="",0,VLOOKUP(AS4,Tables!$AB$3:$AC$12,2)) -> 0 | BM4: =IF(AT4="",0,VLOOKUP(AT4,Tables!$AB$3:$AC$12,2)) -> 0 | BN4: =IF(AU4="",0,VLOOKUP(AU4,Tables!$AB$3:$AC$12,2)) -> 0 | ... BU4: =IF(BB4="",0,VLOOKUP(BB4,Tables!$AB$3:$AC$12,2)) -> 0 | BV4: =IF(AN4="",0,VLOOKUP(B4,Tables!$B$3:$D$36,2,FALSE())*X$1) -> 4 | BW4: =IF(AO4="",0,VLOOKUP(C4,Tables!$B$3:$D$36,2,FALSE())*Y$1) -> 0 | BX4: =IF(AP4="",0,VLOOKUP(D4,Tables!$B$3:$D$36,2,FALSE())*Z$1) -> 0 | BY4: =IF(AQ4="",0,VLOOKUP(E4,Tables!$B$3:$D$36,2,FALSE())*AA$1) -> 0 | BZ4: =IF(AR4="",0,VLOOKUP(F4,Tables!$B$3:$D$36,2,FALSE())*AB$1) -> 0 | CA4: =IF(AS4="",0,VLOOKUP(G4,Tables!$B$3:$D$36,2,FALSE())*AC$1) -> 0 | CB4: =IF(AT4="",0,VLOOKUP(H4,Tables!$B$3:$D$36,2,FALSE())*AD$1) -> 0 | CC4: =IF(AU4="",0,VLOOKUP(I4,Tables!$B$3:$D$36,2,FALSE())*AE$1) -> 0 | ... CJ4: =IF(BB4="",0,VLOOKUP(P4,Tables!$B$3:$D$36,2,FALSE())*AL$1) -> 0 | CK4: =IF(AN4="",0,VLOOKUP(B4,Tables!$B$3:$D$36,3,FALSE())*X$1)*IF(OR(AN4="K",AN4="P"),2,1) -> 0.2 | CL4: =IF(AO4="",0,VLOOKUP(C4,Tables!$B$3:$D$36,3,FALSE())*Y$1)*IF(OR(AO4="K",AO4="P"),2,1) -> 0 | CM4: =IF(AP4="",0,VLOOKUP(D4,Tables!$B$3:$D$36,3,FALSE())*Z$1)*IF(OR(AP4="K",AP4="P"),2,1) -> 0 | CN4: =IF(AQ4="",0,VLOOKUP(E4,Tables!$B$3:$D$36,3,FALSE())*AA$1) -> 0 | CO4: =IF(AR4="",0,VLOOKUP(F4,Tables!$B$3:$D$36,3,FALSE())*AB$1) -> 0 | CP4: =IF(AS4="",0,VLOOKUP(G4,Tables!$B$3:$D$36,3,FALSE())*AC$1) -> 0 | CQ4: =IF(AT4="",0,VLOOKUP(H4,Tables!$B$3:$D$36,3,FALSE())*AD$1) -> 0 | CR4: =IF(AU4="",0,VLOOKUP(I4,Tables!$B$3:$D$36,3,FALSE())*AE$1) -> 0 | CS4: =IF(AV4="",0,VLOOKUP(J4,Tables!$B$3:$D$36,3,FALSE())*AF$1) -> 0 | CT4: =IF(AW4="",0,VLOOKUP(K4,Tables!$B$3:$D$36,3,FALSE())*AG$1) -> 0 | CU4: =IF(AX4="",0,VLOOKUP(L4,Tables!$B$3:$D$36,3,FALSE())*AH$1) -> 0 | ... CY4: =IF(BB4="",0,VLOOKUP(P4,Tables!$B$3:$D$36,3,FALSE())*AL$1) -> 0 | CZ4: =IF(B4="",0,VLOOKUP(B4,MATERIAL,10,FALSE())) -> 1 | DA4: =IF(C4="",0,VLOOKUP(C4,MATERIAL,10,FALSE())) -> 0 | DB4: =IF(D4="",0,VLOOKUP(D4,MATERIAL,10,FALSE())) -> 0 | DC4: =IF(E4="",0,VLOOKUP(E4,MATERIAL,10,FALSE())) -> 0 | DD4: =IF(F4="",0,VLOOKUP(F4,MATERIAL,10,FALSE())) -> 0 | DE4: =IF(G4="",0,VLOOKUP(G4,MATERIAL,10,FALSE())) -> 0 | DF4: =IF(H4="",0,VLOOKUP(H4,MATERIAL,10,FALSE())) -> 0 | DG4: =IF(I4="",0,VLOOKUP(I4,MATERIAL,10,FALSE())) -> 0 | ... DN4: =IF(P4="",0,VLOOKUP(P4,MATERIAL,10,FALSE())) -> 0 | DO4: =IF(AN4="",0,VLOOKUP(B4,Tables!$B$3:$M$36,11,FALSE())*X$1) -> 0.8 | DP4: =IF(AO4="",0,VLOOKUP(C4,Tables!$B$3:$M$36,11,FALSE())*Y$1) -> 0 | DQ4: =IF(AP4="",0,VLOOKUP(D4,Tables!$B$3:$M$36,11,FALSE())*Z$1) -> 0 | DR4: =IF(AQ4="",0,VLOOKUP(E4,Tables!$B$3:$M$36,11,FALSE())*AA$1) -> 0 | DS4: =IF(AR4="",0,VLOOKUP(F4,Tables!$B$3:$M$36,11,FALSE())*AB$1) -> 0 | DT4: =IF(AS4="",0,VLOOKUP(G4,Tables!$B$3:$M$36,11,FALSE())*AC$1) -> 0 | DU4: =IF(AT4="",0,VLOOKUP(H4,Tables!$B$3:$M$36,11,FALSE())*AD$1) -> 0 | DV4: =IF(AU4="",0,VLOOKUP(I4,Tables!$B$3:$M$36,11,FALSE())*AE$1) -> 0 | ... EC4: =IF(BB4="",0,VLOOKUP(P4,Tables!$B$3:$M$36,11,FALSE())*AL$1) -> 0 | ED4: =IF(AN4="",0,VLOOKUP(B4,Tables!$B$3:$M$36,12,FALSE())*X$1) -> 3.2 | EE4: =IF(AO4="",0,VLOOKUP(C4,Tables!$B$3:$M$36,12,FALSE())*Y$1) -> 0 | EF4: =IF(AP4="",0,VLOOKUP(D4,Tables!$B$3:$M$36,12,FALSE())*Z$1) -> 0 | EG4: =IF(AQ4="",0,VLOOKUP(E4,Tables!$B$3:$M$36,12,FALSE())*AA$1) -> 0 | EH4: =IF(AR4="",0,VLOOKUP(F4,Tables!$B$3:$M$36,12,FALSE())*AB$1) -> 0 | EI4: =IF(AS4="",0,VLOOKUP(G4,Tables!$B$3:$M$36,12,FALSE())*AC$1) -> 0 | EJ4: =IF(AT4="",0,VLOOKUP(H4,Tables!$B$3:$M$36,12,FALSE())*AD$1) -> 0 | EK4: =IF(AU4="",0,VLOOKUP(I4,Tables!$B$3:$M$36,12,FALSE())*AE$1) -> 0 | ... ER4: =IF(BB4="",0,VLOOKUP(P4,Tables!$B$3:$M$36,12,FALSE())*AL$1) -> 0 | ES4: =IF(MIN(ET4:FH4)=10,0,MIN(ET4:FH4)) -> 0 | ET4: =IF(AN4="",10,MIN(VLOOKUP(B4,Tables!$B$3:$N$34,13,FALSE()),'Item Builder'!$W4)) -> 0 | EU4: =IF(AO4="",10,MIN(VLOOKUP(C4,Tables!$B$3:$N$34,13,FALSE()),'Item Builder'!$W4)) -> 10 | EV4: =IF(AP4="",10,MIN(VLOOKUP(D4,Tables!$B$3:$N$34,13,FALSE()),'Item Builder'!$W4)) -> 10 | EW4: =IF(AQ4="",10,MIN(VLOOKUP(E4,Tables!$B$3:$N$34,13,FALSE()),'Item Builder'!$W4)) -> 10 | EX4: =IF(AR4="",10,MIN(VLOOKUP(F4,Tables!$B$3:$N$34,13,FALSE()),'Item Builder'!$W4)) -> 10 | EY4: =IF(AS4="",10,MIN(VLOOKUP(G4,Tables!$B$3:$N$34,13,FALSE()),'Item Builder'!$W4)) -> 10 | EZ4: =IF(AT4="",10,MIN(VLOOKUP(H4,Tables!$B$3:$N$34,13,FALSE()),'Item Builder'!$W4)) -> 10 | FA4: =IF(AU4="",10,MIN(VLOOKUP(I4,Tables!$B$3:$N$34,13,FALSE()),'Item Builder'!$W4)) -> 10 | ... FH4: =IF(BB4="",10,MIN(VLOOKUP(P4,Tables!$B$3:$N$34,13,FALSE()),'Item Builder'!$W4)) -> 10 | FJ4: Linen Homespun | FL4: Xh | FM4: Xhb | FN4: Same as for the base material, but covers only the back and attacks from behind.
A5: Buckram Cowl | B5: C | D5: C | Q5: =SUM(BV5:CJ5)*VLOOKUP(W5,Tables!$W$3:$Z$8,4) -> 6 | R5: =SUM(CK5:CY5) -> 0.3 | S5: =ROUND(SUMPRODUCT(CK5:CY5,CZ5:DN5,$CK$1:$CY$1)/$S$2,0)*5 -> 0 | T5: =IF(OR(B5="",D5=""),0,5)+IF(C5="",0,5) -> 5 | U5: =SUM(DO5:EC5) -> 1.2 | V5: =SUM(ED5:ER5) -> 4.8 | W5: 0 | X5: =COUNTA(B5) -> 1 | Y5: =COUNTA(C5) -> 0 | Z5: =COUNTA(D5) -> 1 | AA5: =COUNTA(E5) -> 0 | AB5: =COUNTA(F5) -> 0 | AC5: =COUNTA(G5) -> 0 | AD5: =COUNTA(H5) -> 0 | AE5: =COUNTA(I5) -> 0 | ... AL5: =COUNTA(P5) -> 0 | AM5: =SUMPRODUCT(X5:AL5,$X$1:$AL$1) -> 0.06 | AN5: =LEFT(B5,1) -> C | AO5: =LEFT(C5,1) | AP5: =LEFT(D5,1) -> C | AQ5: =LEFT(E5,1) | AR5: =LEFT(F5,1) | AS5: =LEFT(G5,1) | AT5: =LEFT(H5,1) | AU5: =LEFT(I5,1) | ... BB5: =LEFT(P5,1) | BC5: =SUMPRODUCT(X5:Z5,$X$1:$Z$1)/SUM($X$1:$Z$1) -> 0.66666667 | BD5: =SUMPRODUCT(AA5:AE5,$AA$1:$AE$1)/SUM($AA$1:$AE$1) -> 0 | BE5: =SUMPRODUCT(AF5:AH5,$AF$1:$AH$1)/SUM($AF$1:$AH$1) -> 0 | BF5: =SUMPRODUCT(AI5:AL5,$AI$1:$AL$1)/SUM($AI$1:$AL$1) -> 0 | BG5: =IF(AN5="",0,VLOOKUP(AN5,Tables!$AB$3:$AC$12,2)) -> 1 | BH5: =IF(AO5="",0,VLOOKUP(AO5,Tables!$AB$3:$AC$12,2)) -> 0 | BI5: =IF(AP5="",0,VLOOKUP(AP5,Tables!$AB$3:$AC$12,2)) -> 1 | BJ5: =IF(AQ5="",0,VLOOKUP(AQ5,Tables!$AB$3:$AC$12,2)) -> 0 | BK5: =IF(AR5="",0,VLOOKUP(AR5,Tables!$AB$3:$AC$12,2)) -> 0 | BL5: =IF(AS5="",0,VLOOKUP(AS5,Tables!$AB$3:$AC$12,2)) -> 0 | BM5: =IF(AT5="",0,VLOOKUP(AT5,Tables!$AB$3:$AC$12,2)) -> 0 | BN5: =IF(AU5="",0,VLOOKUP(AU5,Tables!$AB$3:$AC$12,2)) -> 0 | ... BU5: =IF(BB5="",0,VLOOKUP(BB5,Tables!$AB$3:$AC$12,2)) -> 0 | BV5: =IF(AN5="",0,VLOOKUP(B5,Tables!$B$3:$D$36,2,FALSE())*X$1) -> 4 | BW5: =IF(AO5="",0,VLOOKUP(C5,Tables!$B$3:$D$36,2,FALSE())*Y$1) -> 0 | BX5: =IF(AP5="",0,VLOOKUP(D5,Tables!$B$3:$D$36,2,FALSE())*Z$1) -> 2 | BY5: =IF(AQ5="",0,VLOOKUP(E5,Tables!$B$3:$D$36,2,FALSE())*AA$1) -> 0 | BZ5: =IF(AR5="",0,VLOOKUP(F5,Tables!$B$3:$D$36,2,FALSE())*AB$1) -> 0 | CA5: =IF(AS5="",0,VLOOKUP(G5,Tables!$B$3:$D$36,2,FALSE())*AC$1) -> 0 | CB5: =IF(AT5="",0,VLOOKUP(H5,Tables!$B$3:$D$36,2,FALSE())*AD$1) -> 0 | CC5: =IF(AU5="",0,VLOOKUP(I5,Tables!$B$3:$D$36,2,FALSE())*AE$1) -> 0 | ... CJ5: =IF(BB5="",0,VLOOKUP(P5,Tables!$B$3:$D$36,2,FALSE())*AL$1) -> 0 | CK5: =IF(AN5="",0,VLOOKUP(B5,Tables!$B$3:$D$36,3,FALSE())*X$1)*IF(OR(AN5="K",AN5="P"),2,1) -> 0.2 | CL5: =IF(AO5="",0,VLOOKUP(C5,Tables!$B$3:$D$36,3,FALSE())*Y$1)*IF(OR(AO5="K",AO5="P"),2,1) -> 0 | CM5: =IF(AP5="",0,VLOOKUP(D5,Tables!$B$3:$D$36,3,FALSE())*Z$1)*IF(OR(AP5="K",AP5="P"),2,1) -> 0.1 | CN5: =IF(AQ5="",0,VLOOKUP(E5,Tables!$B$3:$D$36,3,FALSE())*AA$1) -> 0 | CO5: =IF(AR5="",0,VLOOKUP(F5,Tables!$B$3:$D$36,3,FALSE())*AB$1) -> 0 | CP5: =IF(AS5="",0,VLOOKUP(G5,Tables!$B$3:$D$36,3,FALSE())*AC$1) -> 0 | CQ5: =IF(AT5="",0,VLOOKUP(H5,Tables!$B$3:$D$36,3,FALSE())*AD$1) -> 0 | CR5: =IF(AU5="",0,VLOOKUP(I5,Tables!$B$3:$D$36,3,FALSE())*AE$1) -> 0 | CS5: =IF(AV5="",0,VLOOKUP(J5,Tables!$B$3:$D$36,3,FALSE())*AF$1) -> 0 | CT5: =IF(AW5="",0,VLOOKUP(K5,Tables!$B$3:$D$36,3,FALSE())*AG$1) -> 0 | CU5: =IF(AX5="",0,VLOOKUP(L5,Tables!$B$3:$D$36,3,FALSE())*AH$1) -> 0 | ... CY5: =IF(BB5="",0,VLOOKUP(P5,Tables!$B$3:$D$36,3,FALSE())*AL$1) -> 0 | CZ5: =IF(B5="",0,VLOOKUP(B5,MATERIAL,10,FALSE())) -> 1 | DA5: =IF(C5="",0,VLOOKUP(C5,MATERIAL,10,FALSE())) -> 0 | DB5: =IF(D5="",0,VLOOKUP(D5,MATERIAL,10,FALSE())) -> 1 | DC5: =IF(E5="",0,VLOOKUP(E5,MATERIAL,10,FALSE())) -> 0 | DD5: =IF(F5="",0,VLOOKUP(F5,MATERIAL,10,FALSE())) -> 0 | DE5: =IF(G5="",0,VLOOKUP(G5,MATERIAL,10,FALSE())) -> 0 | DF5: =IF(H5="",0,VLOOKUP(H5,MATERIAL,10,FALSE())) -> 0 | DG5: =IF(I5="",0,VLOOKUP(I5,MATERIAL,10,FALSE())) -> 0 | ... DN5: =IF(P5="",0,VLOOKUP(P5,MATERIAL,10,FALSE())) -> 0 | DO5: =IF(AN5="",0,VLOOKUP(B5,Tables!$B$3:$M$36,11,FALSE())*X$1) -> 0.8 | DP5: =IF(AO5="",0,VLOOKUP(C5,Tables!$B$3:$M$36,11,FALSE())*Y$1) -> 0 | DQ5: =IF(AP5="",0,VLOOKUP(D5,Tables!$B$3:$M$36,11,FALSE())*Z$1) -> 0.4 | DR5: =IF(AQ5="",0,VLOOKUP(E5,Tables!$B$3:$M$36,11,FALSE())*AA$1) -> 0 | DS5: =IF(AR5="",0,VLOOKUP(F5,Tables!$B$3:$M$36,11,FALSE())*AB$1) -> 0 | DT5: =IF(AS5="",0,VLOOKUP(G5,Tables!$B$3:$M$36,11,FALSE())*AC$1) -> 0 | DU5: =IF(AT5="",0,VLOOKUP(H5,Tables!$B$3:$M$36,11,FALSE())*AD$1) -> 0 | DV5: =IF(AU5="",0,VLOOKUP(I5,Tables!$B$3:$M$36,11,FALSE())*AE$1) -> 0 | ... EC5: =IF(BB5="",0,VLOOKUP(P5,Tables!$B$3:$M$36,11,FALSE())*AL$1) -> 0 | ED5: =IF(AN5="",0,VLOOKUP(B5,Tables!$B$3:$M$36,12,FALSE())*X$1) -> 3.2 | EE5: =IF(AO5="",0,VLOOKUP(C5,Tables!$B$3:$M$36,12,FALSE())*Y$1) -> 0 | EF5: =IF(AP5="",0,VLOOKUP(D5,Tables!$B$3:$M$36,12,FALSE())*Z$1) -> 1.6 | EG5: =IF(AQ5="",0,VLOOKUP(E5,Tables!$B$3:$M$36,12,FALSE())*AA$1) -> 0 | EH5: =IF(AR5="",0,VLOOKUP(F5,Tables!$B$3:$M$36,12,FALSE())*AB$1) -> 0 | EI5: =IF(AS5="",0,VLOOKUP(G5,Tables!$B$3:$M$36,12,FALSE())*AC$1) -> 0 | EJ5: =IF(AT5="",0,VLOOKUP(H5,Tables!$B$3:$M$36,12,FALSE())*AD$1) -> 0 | EK5: =IF(AU5="",0,VLOOKUP(I5,Tables!$B$3:$M$36,12,FALSE())*AE$1) -> 0 | ... ER5: =IF(BB5="",0,VLOOKUP(P5,Tables!$B$3:$M$36,12,FALSE())*AL$1) -> 0 | ES5: =IF(MIN(ET5:FH5)=10,0,MIN(ET5:FH5)) -> 0 | ET5: =IF(AN5="",10,MIN(VLOOKUP(B5,Tables!$B$3:$N$34,13,FALSE()),'Item Builder'!$W5)) -> 0 | EU5: =IF(AO5="",10,MIN(VLOOKUP(C5,Tables!$B$3:$N$34,13,FALSE()),'Item Builder'!$W5)) -> 10 | EV5: =IF(AP5="",10,MIN(VLOOKUP(D5,Tables!$B$3:$N$34,13,FALSE()),'Item Builder'!$W5)) -> 0 | EW5: =IF(AQ5="",10,MIN(VLOOKUP(E5,Tables!$B$3:$N$34,13,FALSE()),'Item Builder'!$W5)) -> 10 | EX5: =IF(AR5="",10,MIN(VLOOKUP(F5,Tables!$B$3:$N$34,13,FALSE()),'Item Builder'!$W5)) -> 10 | EY5: =IF(AS5="",10,MIN(VLOOKUP(G5,Tables!$B$3:$N$34,13,FALSE()),'Item Builder'!$W5)) -> 10 | EZ5: =IF(AT5="",10,MIN(VLOOKUP(H5,Tables!$B$3:$N$34,13,FALSE()),'Item Builder'!$W5)) -> 10 | FA5: =IF(AU5="",10,MIN(VLOOKUP(I5,Tables!$B$3:$N$34,13,FALSE()),'Item Builder'!$W5)) -> 10 | ... FH5: =IF(BB5="",10,MIN(VLOOKUP(P5,Tables!$B$3:$N$34,13,FALSE()),'Item Builder'!$W5)) -> 10 | FJ5: Woolen Homespun | FL5: Ch | FM5: Chb
A6: Buckram Mantle | E6: C | F6: C | J6: C | Q6: =SUM(BV6:CJ6)*VLOOKUP(W6,Tables!$W$3:$Z$8,4) -> 21 | R6: =SUM(CK6:CY6) -> 1.05 | S6: =ROUND(SUMPRODUCT(CK6:CY6,CZ6:DN6,$CK$1:$CY$1)/$S$2,0)*5 -> 0 | T6: =IF(OR(B6="",D6=""),0,5)+IF(C6="",0,5) -> 0 | U6: =SUM(DO6:EC6) -> 4.2 | V6: =SUM(ED6:ER6) -> 16.8 | W6: 0 | X6: =COUNTA(B6) -> 0 | Y6: =COUNTA(C6) -> 0 | Z6: =COUNTA(D6) -> 0 | AA6: =COUNTA(E6) -> 1 | AB6: =COUNTA(F6) -> 1 | AC6: =COUNTA(G6) -> 0 | AD6: =COUNTA(H6) -> 0 | AE6: =COUNTA(I6) -> 0 | ... AL6: =COUNTA(P6) -> 0 | AM6: =SUMPRODUCT(X6:AL6,$X$1:$AL$1) -> 0.21 | AN6: =LEFT(B6,1) | AO6: =LEFT(C6,1) | AP6: =LEFT(D6,1) | AQ6: =LEFT(E6,1) -> C | AR6: =LEFT(F6,1) -> C | AS6: =LEFT(G6,1) | AT6: =LEFT(H6,1) | AU6: =LEFT(I6,1) | ... BB6: =LEFT(P6,1) | BC6: =SUMPRODUCT(X6:Z6,$X$1:$Z$1)/SUM($X$1:$Z$1) -> 0 | BD6: =SUMPRODUCT(AA6:AE6,$AA$1:$AE$1)/SUM($AA$1:$AE$1) -> 0.42857143 | BE6: =SUMPRODUCT(AF6:AH6,$AF$1:$AH$1)/SUM($AF$1:$AH$1) -> 0.35294118 | BF6: =SUMPRODUCT(AI6:AL6,$AI$1:$AL$1)/SUM($AI$1:$AL$1) -> 0 | BG6: =IF(AN6="",0,VLOOKUP(AN6,Tables!$AB$3:$AC$12,2)) -> 0 | BH6: =IF(AO6="",0,VLOOKUP(AO6,Tables!$AB$3:$AC$12,2)) -> 0 | BI6: =IF(AP6="",0,VLOOKUP(AP6,Tables!$AB$3:$AC$12,2)) -> 0 | BJ6: =IF(AQ6="",0,VLOOKUP(AQ6,Tables!$AB$3:$AC$12,2)) -> 1 | BK6: =IF(AR6="",0,VLOOKUP(AR6,Tables!$AB$3:$AC$12,2)) -> 1 | BL6: =IF(AS6="",0,VLOOKUP(AS6,Tables!$AB$3:$AC$12,2)) -> 0 | BM6: =IF(AT6="",0,VLOOKUP(AT6,Tables!$AB$3:$AC$12,2)) -> 0 | BN6: =IF(AU6="",0,VLOOKUP(AU6,Tables!$AB$3:$AC$12,2)) -> 0 | ... BU6: =IF(BB6="",0,VLOOKUP(BB6,Tables!$AB$3:$AC$12,2)) -> 0 | BV6: =IF(AN6="",0,VLOOKUP(B6,Tables!$B$3:$D$36,2,FALSE())*X$1) -> 0 | BW6: =IF(AO6="",0,VLOOKUP(C6,Tables!$B$3:$D$36,2,FALSE())*Y$1) -> 0 | BX6: =IF(AP6="",0,VLOOKUP(D6,Tables!$B$3:$D$36,2,FALSE())*Z$1) -> 0 | BY6: =IF(AQ6="",0,VLOOKUP(E6,Tables!$B$3:$D$36,2,FALSE())*AA$1) -> 3 | BZ6: =IF(AR6="",0,VLOOKUP(F6,Tables!$B$3:$D$36,2,FALSE())*AB$1) -> 6 | CA6: =IF(AS6="",0,VLOOKUP(G6,Tables!$B$3:$D$36,2,FALSE())*AC$1) -> 0 | CB6: =IF(AT6="",0,VLOOKUP(H6,Tables!$B$3:$D$36,2,FALSE())*AD$1) -> 0 | CC6: =IF(AU6="",0,VLOOKUP(I6,Tables!$B$3:$D$36,2,FALSE())*AE$1) -> 0 | ... CJ6: =IF(BB6="",0,VLOOKUP(P6,Tables!$B$3:$D$36,2,FALSE())*AL$1) -> 0 | CK6: =IF(AN6="",0,VLOOKUP(B6,Tables!$B$3:$D$36,3,FALSE())*X$1)*IF(OR(AN6="K",AN6="P"),2,1) -> 0 | CL6: =IF(AO6="",0,VLOOKUP(C6,Tables!$B$3:$D$36,3,FALSE())*Y$1)*IF(OR(AO6="K",AO6="P"),2,1) -> 0 | CM6: =IF(AP6="",0,VLOOKUP(D6,Tables!$B$3:$D$36,3,FALSE())*Z$1)*IF(OR(AP6="K",AP6="P"),2,1) -> 0 | CN6: =IF(AQ6="",0,VLOOKUP(E6,Tables!$B$3:$D$36,3,FALSE())*AA$1) -> 0.15 | CO6: =IF(AR6="",0,VLOOKUP(F6,Tables!$B$3:$D$36,3,FALSE())*AB$1) -> 0.3 | CP6: =IF(AS6="",0,VLOOKUP(G6,Tables!$B$3:$D$36,3,FALSE())*AC$1) -> 0 | CQ6: =IF(AT6="",0,VLOOKUP(H6,Tables!$B$3:$D$36,3,FALSE())*AD$1) -> 0 | CR6: =IF(AU6="",0,VLOOKUP(I6,Tables!$B$3:$D$36,3,FALSE())*AE$1) -> 0 | CS6: =IF(AV6="",0,VLOOKUP(J6,Tables!$B$3:$D$36,3,FALSE())*AF$1) -> 0.6 | CT6: =IF(AW6="",0,VLOOKUP(K6,Tables!$B$3:$D$36,3,FALSE())*AG$1) -> 0 | CU6: =IF(AX6="",0,VLOOKUP(L6,Tables!$B$3:$D$36,3,FALSE())*AH$1) -> 0 | ... CY6: =IF(BB6="",0,VLOOKUP(P6,Tables!$B$3:$D$36,3,FALSE())*AL$1) -> 0 | CZ6: =IF(B6="",0,VLOOKUP(B6,MATERIAL,10,FALSE())) -> 0 | DA6: =IF(C6="",0,VLOOKUP(C6,MATERIAL,10,FALSE())) -> 0 | DB6: =IF(D6="",0,VLOOKUP(D6,MATERIAL,10,FALSE())) -> 0 | DC6: =IF(E6="",0,VLOOKUP(E6,MATERIAL,10,FALSE())) -> 1 | DD6: =IF(F6="",0,VLOOKUP(F6,MATERIAL,10,FALSE())) -> 1 | DE6: =IF(G6="",0,VLOOKUP(G6,MATERIAL,10,FALSE())) -> 0 | DF6: =IF(H6="",0,VLOOKUP(H6,MATERIAL,10,FALSE())) -> 0 | DG6: =IF(I6="",0,VLOOKUP(I6,MATERIAL,10,FALSE())) -> 0 | ... DN6: =IF(P6="",0,VLOOKUP(P6,MATERIAL,10,FALSE())) -> 0 | DO6: =IF(AN6="",0,VLOOKUP(B6,Tables!$B$3:$M$36,11,FALSE())*X$1) -> 0 | DP6: =IF(AO6="",0,VLOOKUP(C6,Tables!$B$3:$M$36,11,FALSE())*Y$1) -> 0 | DQ6: =IF(AP6="",0,VLOOKUP(D6,Tables!$B$3:$M$36,11,FALSE())*Z$1) -> 0 | DR6: =IF(AQ6="",0,VLOOKUP(E6,Tables!$B$3:$M$36,11,FALSE())*AA$1) -> 0.6 | DS6: =IF(AR6="",0,VLOOKUP(F6,Tables!$B$3:$M$36,11,FALSE())*AB$1) -> 1.2 | DT6: =IF(AS6="",0,VLOOKUP(G6,Tables!$B$3:$M$36,11,FALSE())*AC$1) -> 0 | DU6: =IF(AT6="",0,VLOOKUP(H6,Tables!$B$3:$M$36,11,FALSE())*AD$1) -> 0 | DV6: =IF(AU6="",0,VLOOKUP(I6,Tables!$B$3:$M$36,11,FALSE())*AE$1) -> 0 | ... EC6: =IF(BB6="",0,VLOOKUP(P6,Tables!$B$3:$M$36,11,FALSE())*AL$1) -> 0 | ED6: =IF(AN6="",0,VLOOKUP(B6,Tables!$B$3:$M$36,12,FALSE())*X$1) -> 0 | EE6: =IF(AO6="",0,VLOOKUP(C6,Tables!$B$3:$M$36,12,FALSE())*Y$1) -> 0 | EF6: =IF(AP6="",0,VLOOKUP(D6,Tables!$B$3:$M$36,12,FALSE())*Z$1) -> 0 | EG6: =IF(AQ6="",0,VLOOKUP(E6,Tables!$B$3:$M$36,12,FALSE())*AA$1) -> 2.4 | EH6: =IF(AR6="",0,VLOOKUP(F6,Tables!$B$3:$M$36,12,FALSE())*AB$1) -> 4.8 | EI6: =IF(AS6="",0,VLOOKUP(G6,Tables!$B$3:$M$36,12,FALSE())*AC$1) -> 0 | EJ6: =IF(AT6="",0,VLOOKUP(H6,Tables!$B$3:$M$36,12,FALSE())*AD$1) -> 0 | EK6: =IF(AU6="",0,VLOOKUP(I6,Tables!$B$3:$M$36,12,FALSE())*AE$1) -> 0 | ... ER6: =IF(BB6="",0,VLOOKUP(P6,Tables!$B$3:$M$36,12,FALSE())*AL$1) -> 0 | ES6: =IF(MIN(ET6:FH6)=10,0,MIN(ET6:FH6)) -> 0 | ET6: =IF(AN6="",10,MIN(VLOOKUP(B6,Tables!$B$3:$N$34,13,FALSE()),'Item Builder'!$W6)) -> 10 | EU6: =IF(AO6="",10,MIN(VLOOKUP(C6,Tables!$B$3:$N$34,13,FALSE()),'Item Builder'!$W6)) -> 10 | EV6: =IF(AP6="",10,MIN(VLOOKUP(D6,Tables!$B$3:$N$34,13,FALSE()),'Item Builder'!$W6)) -> 10 | EW6: =IF(AQ6="",10,MIN(VLOOKUP(E6,Tables!$B$3:$N$34,13,FALSE()),'Item Builder'!$W6)) -> 0 | EX6: =IF(AR6="",10,MIN(VLOOKUP(F6,Tables!$B$3:$N$34,13,FALSE()),'Item Builder'!$W6)) -> 0 | EY6: =IF(AS6="",10,MIN(VLOOKUP(G6,Tables!$B$3:$N$34,13,FALSE()),'Item Builder'!$W6)) -> 10 | EZ6: =IF(AT6="",10,MIN(VLOOKUP(H6,Tables!$B$3:$N$34,13,FALSE()),'Item Builder'!$W6)) -> 10 | FA6: =IF(AU6="",10,MIN(VLOOKUP(I6,Tables!$B$3:$N$34,13,FALSE()),'Item Builder'!$W6)) -> 10 | ... FH6: =IF(BB6="",10,MIN(VLOOKUP(P6,Tables!$B$3:$N$34,13,FALSE()),'Item Builder'!$W6)) -> 10 | FJ6: Linen | FL6: Xl | FM6: Xlb
A7: Buckram Gauntlets | I7: C | Q7: =SUM(BV7:CJ7)*VLOOKUP(W7,Tables!$W$3:$Z$8,4) -> 5 | R7: =SUM(CK7:CY7) -> 0.25 | S7: =ROUND(SUMPRODUCT(CK7:CY7,CZ7:DN7,$CK$1:$CY$1)/$S$2,0)*5 -> 0 | T7: =IF(OR(B7="",D7=""),0,5)+IF(C7="",0,5) -> 0 | U7: =SUM(DO7:EC7) -> 1 | V7: =SUM(ED7:ER7) -> 4 | W7: 0 | X7: =COUNTA(B7) -> 0 | Y7: =COUNTA(C7) -> 0 | Z7: =COUNTA(D7) -> 0 | AA7: =COUNTA(E7) -> 0 | AB7: =COUNTA(F7) -> 0 | AC7: =COUNTA(G7) -> 0 | AD7: =COUNTA(H7) -> 0 | AE7: =COUNTA(I7) -> 1 | ... AL7: =COUNTA(P7) -> 0 | AM7: =SUMPRODUCT(X7:AL7,$X$1:$AL$1) -> 0.05 | AN7: =LEFT(B7,1) | AO7: =LEFT(C7,1) | AP7: =LEFT(D7,1) | AQ7: =LEFT(E7,1) | AR7: =LEFT(F7,1) | AS7: =LEFT(G7,1) | AT7: =LEFT(H7,1) | AU7: =LEFT(I7,1) -> C | ... BB7: =LEFT(P7,1) | BC7: =SUMPRODUCT(X7:Z7,$X$1:$Z$1)/SUM($X$1:$Z$1) -> 0 | BD7: =SUMPRODUCT(AA7:AE7,$AA$1:$AE$1)/SUM($AA$1:$AE$1) -> 0.23809524 | BE7: =SUMPRODUCT(AF7:AH7,$AF$1:$AH$1)/SUM($AF$1:$AH$1) -> 0 | BF7: =SUMPRODUCT(AI7:AL7,$AI$1:$AL$1)/SUM($AI$1:$AL$1) -> 0 | BG7: =IF(AN7="",0,VLOOKUP(AN7,Tables!$AB$3:$AC$12,2)) -> 0 | BH7: =IF(AO7="",0,VLOOKUP(AO7,Tables!$AB$3:$AC$12,2)) -> 0 | BI7: =IF(AP7="",0,VLOOKUP(AP7,Tables!$AB$3:$AC$12,2)) -> 0 | BJ7: =IF(AQ7="",0,VLOOKUP(AQ7,Tables!$AB$3:$AC$12,2)) -> 0 | BK7: =IF(AR7="",0,VLOOKUP(AR7,Tables!$AB$3:$AC$12,2)) -> 0 | BL7: =IF(AS7="",0,VLOOKUP(AS7,Tables!$AB$3:$AC$12,2)) -> 0 | BM7: =IF(AT7="",0,VLOOKUP(AT7,Tables!$AB$3:$AC$12,2)) -> 0 | BN7: =IF(AU7="",0,VLOOKUP(AU7,Tables!$AB$3:$AC$12,2)) -> 1 | ... BU7: =IF(BB7="",0,VLOOKUP(BB7,Tables!$AB$3:$AC$12,2)) -> 0 | BV7: =IF(AN7="",0,VLOOKUP(B7,Tables!$B$3:$D$36,2,FALSE())*X$1) -> 0 | BW7: =IF(AO7="",0,VLOOKUP(C7,Tables!$B$3:$D$36,2,FALSE())*Y$1) -> 0 | BX7: =IF(AP7="",0,VLOOKUP(D7,Tables!$B$3:$D$36,2,FALSE())*Z$1) -> 0 | BY7: =IF(AQ7="",0,VLOOKUP(E7,Tables!$B$3:$D$36,2,FALSE())*AA$1) -> 0 | BZ7: =IF(AR7="",0,VLOOKUP(F7,Tables!$B$3:$D$36,2,FALSE())*AB$1) -> 0 | CA7: =IF(AS7="",0,VLOOKUP(G7,Tables!$B$3:$D$36,2,FALSE())*AC$1) -> 0 | CB7: =IF(AT7="",0,VLOOKUP(H7,Tables!$B$3:$D$36,2,FALSE())*AD$1) -> 0 | CC7: =IF(AU7="",0,VLOOKUP(I7,Tables!$B$3:$D$36,2,FALSE())*AE$1) -> 5 | ... CJ7: =IF(BB7="",0,VLOOKUP(P7,Tables!$B$3:$D$36,2,FALSE())*AL$1) -> 0 | CK7: =IF(AN7="",0,VLOOKUP(B7,Tables!$B$3:$D$36,3,FALSE())*X$1)*IF(OR(AN7="K",AN7="P"),2,1) -> 0 | CL7: =IF(AO7="",0,VLOOKUP(C7,Tables!$B$3:$D$36,3,FALSE())*Y$1)*IF(OR(AO7="K",AO7="P"),2,1) -> 0 | CM7: =IF(AP7="",0,VLOOKUP(D7,Tables!$B$3:$D$36,3,FALSE())*Z$1)*IF(OR(AP7="K",AP7="P"),2,1) -> 0 | CN7: =IF(AQ7="",0,VLOOKUP(E7,Tables!$B$3:$D$36,3,FALSE())*AA$1) -> 0 | CO7: =IF(AR7="",0,VLOOKUP(F7,Tables!$B$3:$D$36,3,FALSE())*AB$1) -> 0 | CP7: =IF(AS7="",0,VLOOKUP(G7,Tables!$B$3:$D$36,3,FALSE())*AC$1) -> 0 | CQ7: =IF(AT7="",0,VLOOKUP(H7,Tables!$B$3:$D$36,3,FALSE())*AD$1) -> 0 | CR7: =IF(AU7="",0,VLOOKUP(I7,Tables!$B$3:$D$36,3,FALSE())*AE$1) -> 0.25 | CS7: =IF(AV7="",0,VLOOKUP(J7,Tables!$B$3:$D$36,3,FALSE())*AF$1) -> 0 | CT7: =IF(AW7="",0,VLOOKUP(K7,Tables!$B$3:$D$36,3,FALSE())*AG$1) -> 0 | CU7: =IF(AX7="",0,VLOOKUP(L7,Tables!$B$3:$D$36,3,FALSE())*AH$1) -> 0 | ... CY7: =IF(BB7="",0,VLOOKUP(P7,Tables!$B$3:$D$36,3,FALSE())*AL$1) -> 0 | CZ7: =IF(B7="",0,VLOOKUP(B7,MATERIAL,10,FALSE())) -> 0 | DA7: =IF(C7="",0,VLOOKUP(C7,MATERIAL,10,FALSE())) -> 0 | DB7: =IF(D7="",0,VLOOKUP(D7,MATERIAL,10,FALSE())) -> 0 | DC7: =IF(E7="",0,VLOOKUP(E7,MATERIAL,10,FALSE())) -> 0 | DD7: =IF(F7="",0,VLOOKUP(F7,MATERIAL,10,FALSE())) -> 0 | DE7: =IF(G7="",0,VLOOKUP(G7,MATERIAL,10,FALSE())) -> 0 | DF7: =IF(H7="",0,VLOOKUP(H7,MATERIAL,10,FALSE())) -> 0 | DG7: =IF(I7="",0,VLOOKUP(I7,MATERIAL,10,FALSE())) -> 1 | ... DN7: =IF(P7="",0,VLOOKUP(P7,MATERIAL,10,FALSE())) -> 0 | DO7: =IF(AN7="",0,VLOOKUP(B7,Tables!$B$3:$M$36,11,FALSE())*X$1) -> 0 | DP7: =IF(AO7="",0,VLOOKUP(C7,Tables!$B$3:$M$36,11,FALSE())*Y$1) -> 0 | DQ7: =IF(AP7="",0,VLOOKUP(D7,Tables!$B$3:$M$36,11,FALSE())*Z$1) -> 0 | DR7: =IF(AQ7="",0,VLOOKUP(E7,Tables!$B$3:$M$36,11,FALSE())*AA$1) -> 0 | DS7: =IF(AR7="",0,VLOOKUP(F7,Tables!$B$3:$M$36,11,FALSE())*AB$1) -> 0 | DT7: =IF(AS7="",0,VLOOKUP(G7,Tables!$B$3:$M$36,11,FALSE())*AC$1) -> 0 | DU7: =IF(AT7="",0,VLOOKUP(H7,Tables!$B$3:$M$36,11,FALSE())*AD$1) -> 0 | DV7: =IF(AU7="",0,VLOOKUP(I7,Tables!$B$3:$M$36,11,FALSE())*AE$1) -> 1 | ... EC7: =IF(BB7="",0,VLOOKUP(P7,Tables!$B$3:$M$36,11,FALSE())*AL$1) -> 0 | ED7: =IF(AN7="",0,VLOOKUP(B7,Tables!$B$3:$M$36,12,FALSE())*X$1) -> 0 | EE7: =IF(AO7="",0,VLOOKUP(C7,Tables!$B$3:$M$36,12,FALSE())*Y$1) -> 0 | EF7: =IF(AP7="",0,VLOOKUP(D7,Tables!$B$3:$M$36,12,FALSE())*Z$1) -> 0 | EG7: =IF(AQ7="",0,VLOOKUP(E7,Tables!$B$3:$M$36,12,FALSE())*AA$1) -> 0 | EH7: =IF(AR7="",0,VLOOKUP(F7,Tables!$B$3:$M$36,12,FALSE())*AB$1) -> 0 | EI7: =IF(AS7="",0,VLOOKUP(G7,Tables!$B$3:$M$36,12,FALSE())*AC$1) -> 0 | EJ7: =IF(AT7="",0,VLOOKUP(H7,Tables!$B$3:$M$36,12,FALSE())*AD$1) -> 0 | EK7: =IF(AU7="",0,VLOOKUP(I7,Tables!$B$3:$M$36,12,FALSE())*AE$1) -> 4 | ... ER7: =IF(BB7="",0,VLOOKUP(P7,Tables!$B$3:$M$36,12,FALSE())*AL$1) -> 0 | ES7: =IF(MIN(ET7:FH7)=10,0,MIN(ET7:FH7)) -> 0 | ET7: =IF(AN7="",10,MIN(VLOOKUP(B7,Tables!$B$3:$N$34,13,FALSE()),'Item Builder'!$W7)) -> 10 | EU7: =IF(AO7="",10,MIN(VLOOKUP(C7,Tables!$B$3:$N$34,13,FALSE()),'Item Builder'!$W7)) -> 10 | EV7: =IF(AP7="",10,MIN(VLOOKUP(D7,Tables!$B$3:$N$34,13,FALSE()),'Item Builder'!$W7)) -> 10 | EW7: =IF(AQ7="",10,MIN(VLOOKUP(E7,Tables!$B$3:$N$34,13,FALSE()),'Item Builder'!$W7)) -> 10 | EX7: =IF(AR7="",10,MIN(VLOOKUP(F7,Tables!$B$3:$N$34,13,FALSE()),'Item Builder'!$W7)) -> 10 | EY7: =IF(AS7="",10,MIN(VLOOKUP(G7,Tables!$B$3:$N$34,13,FALSE()),'Item Builder'!$W7)) -> 10 | EZ7: =IF(AT7="",10,MIN(VLOOKUP(H7,Tables!$B$3:$N$34,13,FALSE()),'Item Builder'!$W7)) -> 10 | FA7: =IF(AU7="",10,MIN(VLOOKUP(I7,Tables!$B$3:$N$34,13,FALSE()),'Item Builder'!$W7)) -> 0 | ... FH7: =IF(BB7="",10,MIN(VLOOKUP(P7,Tables!$B$3:$N$34,13,FALSE()),'Item Builder'!$W7)) -> 10 | FJ7: Buckram | FL7: C | FM7: Cb
A8: Buckram Vest | J8: C | K8: C | Q8: =SUM(BV8:CJ8)*VLOOKUP(W8,Tables!$W$3:$Z$8,4) -> 24 | R8: =SUM(CK8:CY8) -> 1.2 | S8: =ROUND(SUMPRODUCT(CK8:CY8,CZ8:DN8,$CK$1:$CY$1)/$S$2,0)*5 -> 0 | T8: =IF(OR(B8="",D8=""),0,5)+IF(C8="",0,5) -> 0 | U8: =SUM(DO8:EC8) -> 4.8 | V8: =SUM(ED8:ER8) -> 19.2 | W8: 0 | X8: =COUNTA(B8) -> 0 | Y8: =COUNTA(C8) -> 0 | Z8: =COUNTA(D8) -> 0 | AA8: =COUNTA(E8) -> 0 | AB8: =COUNTA(F8) -> 0 | AC8: =COUNTA(G8) -> 0 | AD8: =COUNTA(H8) -> 0 | AE8: =COUNTA(I8) -> 0 | ... AL8: =COUNTA(P8) -> 0 | AM8: =SUMPRODUCT(X8:AL8,$X$1:$AL$1) -> 0.24 | AN8: =LEFT(B8,1) | AO8: =LEFT(C8,1) | AP8: =LEFT(D8,1) | AQ8: =LEFT(E8,1) | AR8: =LEFT(F8,1) | AS8: =LEFT(G8,1) | AT8: =LEFT(H8,1) | AU8: =LEFT(I8,1) | ... BB8: =LEFT(P8,1) | BC8: =SUMPRODUCT(X8:Z8,$X$1:$Z$1)/SUM($X$1:$Z$1) -> 0 | BD8: =SUMPRODUCT(AA8:AE8,$AA$1:$AE$1)/SUM($AA$1:$AE$1) -> 0 | BE8: =SUMPRODUCT(AF8:AH8,$AF$1:$AH$1)/SUM($AF$1:$AH$1) -> 0.70588235 | BF8: =SUMPRODUCT(AI8:AL8,$AI$1:$AL$1)/SUM($AI$1:$AL$1) -> 0 | BG8: =IF(AN8="",0,VLOOKUP(AN8,Tables!$AB$3:$AC$12,2)) -> 0 | BH8: =IF(AO8="",0,VLOOKUP(AO8,Tables!$AB$3:$AC$12,2)) -> 0 | BI8: =IF(AP8="",0,VLOOKUP(AP8,Tables!$AB$3:$AC$12,2)) -> 0 | BJ8: =IF(AQ8="",0,VLOOKUP(AQ8,Tables!$AB$3:$AC$12,2)) -> 0 | BK8: =IF(AR8="",0,VLOOKUP(AR8,Tables!$AB$3:$AC$12,2)) -> 0 | BL8: =IF(AS8="",0,VLOOKUP(AS8,Tables!$AB$3:$AC$12,2)) -> 0 | BM8: =IF(AT8="",0,VLOOKUP(AT8,Tables!$AB$3:$AC$12,2)) -> 0 | BN8: =IF(AU8="",0,VLOOKUP(AU8,Tables!$AB$3:$AC$12,2)) -> 0 | ... BU8: =IF(BB8="",0,VLOOKUP(BB8,Tables!$AB$3:$AC$12,2)) -> 0 | BV8: =IF(AN8="",0,VLOOKUP(B8,Tables!$B$3:$D$36,2,FALSE())*X$1) -> 0 | BW8: =IF(AO8="",0,VLOOKUP(C8,Tables!$B$3:$D$36,2,FALSE())*Y$1) -> 0 | BX8: =IF(AP8="",0,VLOOKUP(D8,Tables!$B$3:$D$36,2,FALSE())*Z$1) -> 0 | BY8: =IF(AQ8="",0,VLOOKUP(E8,Tables!$B$3:$D$36,2,FALSE())*AA$1) -> 0 | BZ8: =IF(AR8="",0,VLOOKUP(F8,Tables!$B$3:$D$36,2,FALSE())*AB$1) -> 0 | CA8: =IF(AS8="",0,VLOOKUP(G8,Tables!$B$3:$D$36,2,FALSE())*AC$1) -> 0 | CB8: =IF(AT8="",0,VLOOKUP(H8,Tables!$B$3:$D$36,2,FALSE())*AD$1) -> 0 | CC8: =IF(AU8="",0,VLOOKUP(I8,Tables!$B$3:$D$36,2,FALSE())*AE$1) -> 0 | ... CJ8: =IF(BB8="",0,VLOOKUP(P8,Tables!$B$3:$D$36,2,FALSE())*AL$1) -> 0 | CK8: =IF(AN8="",0,VLOOKUP(B8,Tables!$B$3:$D$36,3,FALSE())*X$1)*IF(OR(AN8="K",AN8="P"),2,1) -> 0 | CL8: =IF(AO8="",0,VLOOKUP(C8,Tables!$B$3:$D$36,3,FALSE())*Y$1)*IF(OR(AO8="K",AO8="P"),2,1) -> 0 | CM8: =IF(AP8="",0,VLOOKUP(D8,Tables!$B$3:$D$36,3,FALSE())*Z$1)*IF(OR(AP8="K",AP8="P"),2,1) -> 0 | CN8: =IF(AQ8="",0,VLOOKUP(E8,Tables!$B$3:$D$36,3,FALSE())*AA$1) -> 0 | CO8: =IF(AR8="",0,VLOOKUP(F8,Tables!$B$3:$D$36,3,FALSE())*AB$1) -> 0 | CP8: =IF(AS8="",0,VLOOKUP(G8,Tables!$B$3:$D$36,3,FALSE())*AC$1) -> 0 | CQ8: =IF(AT8="",0,VLOOKUP(H8,Tables!$B$3:$D$36,3,FALSE())*AD$1) -> 0 | CR8: =IF(AU8="",0,VLOOKUP(I8,Tables!$B$3:$D$36,3,FALSE())*AE$1) -> 0 | CS8: =IF(AV8="",0,VLOOKUP(J8,Tables!$B$3:$D$36,3,FALSE())*AF$1) -> 0.6 | CT8: =IF(AW8="",0,VLOOKUP(K8,Tables!$B$3:$D$36,3,FALSE())*AG$1) -> 0.6 | CU8: =IF(AX8="",0,VLOOKUP(L8,Tables!$B$3:$D$36,3,FALSE())*AH$1) -> 0 | ... CY8: =IF(BB8="",0,VLOOKUP(P8,Tables!$B$3:$D$36,3,FALSE())*AL$1) -> 0 | CZ8: =IF(B8="",0,VLOOKUP(B8,MATERIAL,10,FALSE())) -> 0 | DA8: =IF(C8="",0,VLOOKUP(C8,MATERIAL,10,FALSE())) -> 0 | DB8: =IF(D8="",0,VLOOKUP(D8,MATERIAL,10,FALSE())) -> 0 | DC8: =IF(E8="",0,VLOOKUP(E8,MATERIAL,10,FALSE())) -> 0 | DD8: =IF(F8="",0,VLOOKUP(F8,MATERIAL,10,FALSE())) -> 0 | DE8: =IF(G8="",0,VLOOKUP(G8,MATERIAL,10,FALSE())) -> 0 | DF8: =IF(H8="",0,VLOOKUP(H8,MATERIAL,10,FALSE())) -> 0 | DG8: =IF(I8="",0,VLOOKUP(I8,MATERIAL,10,FALSE())) -> 0 | ... DN8: =IF(P8="",0,VLOOKUP(P8,MATERIAL,10,FALSE())) -> 0 | DO8: =IF(AN8="",0,VLOOKUP(B8,Tables!$B$3:$M$36,11,FALSE())*X$1) -> 0 | DP8: =IF(AO8="",0,VLOOKUP(C8,Tables!$B$3:$M$36,11,FALSE())*Y$1) -> 0 | DQ8: =IF(AP8="",0,VLOOKUP(D8,Tables!$B$3:$M$36,11,FALSE())*Z$1) -> 0 | DR8: =IF(AQ8="",0,VLOOKUP(E8,Tables!$B$3:$M$36,11,FALSE())*AA$1) -> 0 | DS8: =IF(AR8="",0,VLOOKUP(F8,Tables!$B$3:$M$36,11,FALSE())*AB$1) -> 0 | DT8: =IF(AS8="",0,VLOOKUP(G8,Tables!$B$3:$M$36,11,FALSE())*AC$1) -> 0 | DU8: =IF(AT8="",0,VLOOKUP(H8,Tables!$B$3:$M$36,11,FALSE())*AD$1) -> 0 | DV8: =IF(AU8="",0,VLOOKUP(I8,Tables!$B$3:$M$36,11,FALSE())*AE$1) -> 0 | ... EC8: =IF(BB8="",0,VLOOKUP(P8,Tables!$B$3:$M$36,11,FALSE())*AL$1) -> 0 | ED8: =IF(AN8="",0,VLOOKUP(B8,Tables!$B$3:$M$36,12,FALSE())*X$1) -> 0 | EE8: =IF(AO8="",0,VLOOKUP(C8,Tables!$B$3:$M$36,12,FALSE())*Y$1) -> 0 | EF8: =IF(AP8="",0,VLOOKUP(D8,Tables!$B$3:$M$36,12,FALSE())*Z$1) -> 0 | EG8: =IF(AQ8="",0,VLOOKUP(E8,Tables!$B$3:$M$36,12,FALSE())*AA$1) -> 0 | EH8: =IF(AR8="",0,VLOOKUP(F8,Tables!$B$3:$M$36,12,FALSE())*AB$1) -> 0 | EI8: =IF(AS8="",0,VLOOKUP(G8,Tables!$B$3:$M$36,12,FALSE())*AC$1) -> 0 | EJ8: =IF(AT8="",0,VLOOKUP(H8,Tables!$B$3:$M$36,12,FALSE())*AD$1) -> 0 | EK8: =IF(AU8="",0,VLOOKUP(I8,Tables!$B$3:$M$36,12,FALSE())*AE$1) -> 0 | ... ER8: =IF(BB8="",0,VLOOKUP(P8,Tables!$B$3:$M$36,12,FALSE())*AL$1) -> 0 | ES8: =IF(MIN(ET8:FH8)=10,0,MIN(ET8:FH8)) -> 0 | ET8: =IF(AN8="",10,MIN(VLOOKUP(B8,Tables!$B$3:$N$34,13,FALSE()),'Item Builder'!$W8)) -> 10 | EU8: =IF(AO8="",10,MIN(VLOOKUP(C8,Tables!$B$3:$N$34,13,FALSE()),'Item Builder'!$W8)) -> 10 | EV8: =IF(AP8="",10,MIN(VLOOKUP(D8,Tables!$B$3:$N$34,13,FALSE()),'Item Builder'!$W8)) -> 10 | EW8: =IF(AQ8="",10,MIN(VLOOKUP(E8,Tables!$B$3:$N$34,13,FALSE()),'Item Builder'!$W8)) -> 10 | EX8: =IF(AR8="",10,MIN(VLOOKUP(F8,Tables!$B$3:$N$34,13,FALSE()),'Item Builder'!$W8)) -> 10 | EY8: =IF(AS8="",10,MIN(VLOOKUP(G8,Tables!$B$3:$N$34,13,FALSE()),'Item Builder'!$W8)) -> 10 | EZ8: =IF(AT8="",10,MIN(VLOOKUP(H8,Tables!$B$3:$N$34,13,FALSE()),'Item Builder'!$W8)) -> 10 | FA8: =IF(AU8="",10,MIN(VLOOKUP(I8,Tables!$B$3:$N$34,13,FALSE()),'Item Builder'!$W8)) -> 10 | ... FH8: =IF(BB8="",10,MIN(VLOOKUP(P8,Tables!$B$3:$N$34,13,FALSE()),'Item Builder'!$W8)) -> 10 | FJ8: Serge | FL8: Xg | FM8: Xgb
A9: Buckram Shirt | E9: C | F9: C | J9: C | K9: C | Q9: =SUM(BV9:CJ9)*VLOOKUP(W9,Tables!$W$3:$Z$8,4) -> 33 | R9: =SUM(CK9:CY9) -> 1.65 | S9: =ROUND(SUMPRODUCT(CK9:CY9,CZ9:DN9,$CK$1:$CY$1)/$S$2,0)*5 -> 0 | T9: =IF(OR(B9="",D9=""),0,5)+IF(C9="",0,5) -> 0 | U9: =SUM(DO9:EC9) -> 6.6 | V9: =SUM(ED9:ER9) -> 26.4 | W9: 0 | X9: =COUNTA(B9) -> 0 | Y9: =COUNTA(C9) -> 0 | Z9: =COUNTA(D9) -> 0 | AA9: =COUNTA(E9) -> 1 | AB9: =COUNTA(F9) -> 1 | AC9: =COUNTA(G9) -> 0 | AD9: =COUNTA(H9) -> 0 | AE9: =COUNTA(I9) -> 0 | ... AL9: =COUNTA(P9) -> 0 | AM9: =SUMPRODUCT(X9:AL9,$X$1:$AL$1) -> 0.33 | AN9: =LEFT(B9,1) | AO9: =LEFT(C9,1) | AP9: =LEFT(D9,1) | AQ9: =LEFT(E9,1) -> C | AR9: =LEFT(F9,1) -> C | AS9: =LEFT(G9,1) | AT9: =LEFT(H9,1) | AU9: =LEFT(I9,1) | ... BB9: =LEFT(P9,1) | BC9: =SUMPRODUCT(X9:Z9,$X$1:$Z$1)/SUM($X$1:$Z$1) -> 0 | BD9: =SUMPRODUCT(AA9:AE9,$AA$1:$AE$1)/SUM($AA$1:$AE$1) -> 0.42857143 | BE9: =SUMPRODUCT(AF9:AH9,$AF$1:$AH$1)/SUM($AF$1:$AH$1) -> 0.70588235 | BF9: =SUMPRODUCT(AI9:AL9,$AI$1:$AL$1)/SUM($AI$1:$AL$1) -> 0 | BG9: =IF(AN9="",0,VLOOKUP(AN9,Tables!$AB$3:$AC$12,2)) -> 0 | BH9: =IF(AO9="",0,VLOOKUP(AO9,Tables!$AB$3:$AC$12,2)) -> 0 | BI9: =IF(AP9="",0,VLOOKUP(AP9,Tables!$AB$3:$AC$12,2)) -> 0 | BJ9: =IF(AQ9="",0,VLOOKUP(AQ9,Tables!$AB$3:$AC$12,2)) -> 1 | BK9: =IF(AR9="",0,VLOOKUP(AR9,Tables!$AB$3:$AC$12,2)) -> 1 | BL9: =IF(AS9="",0,VLOOKUP(AS9,Tables!$AB$3:$AC$12,2)) -> 0 | BM9: =IF(AT9="",0,VLOOKUP(AT9,Tables!$AB$3:$AC$12,2)) -> 0 | BN9: =IF(AU9="",0,VLOOKUP(AU9,Tables!$AB$3:$AC$12,2)) -> 0 | ... BU9: =IF(BB9="",0,VLOOKUP(BB9,Tables!$AB$3:$AC$12,2)) -> 0 | BV9: =IF(AN9="",0,VLOOKUP(B9,Tables!$B$3:$D$36,2,FALSE())*X$1) -> 0 | BW9: =IF(AO9="",0,VLOOKUP(C9,Tables!$B$3:$D$36,2,FALSE())*Y$1) -> 0 | BX9: =IF(AP9="",0,VLOOKUP(D9,Tables!$B$3:$D$36,2,FALSE())*Z$1) -> 0 | BY9: =IF(AQ9="",0,VLOOKUP(E9,Tables!$B$3:$D$36,2,FALSE())*AA$1) -> 3 | BZ9: =IF(AR9="",0,VLOOKUP(F9,Tables!$B$3:$D$36,2,FALSE())*AB$1) -> 6 | CA9: =IF(AS9="",0,VLOOKUP(G9,Tables!$B$3:$D$36,2,FALSE())*AC$1) -> 0 | CB9: =IF(AT9="",0,VLOOKUP(H9,Tables!$B$3:$D$36,2,FALSE())*AD$1) -> 0 | CC9: =IF(AU9="",0,VLOOKUP(I9,Tables!$B$3:$D$36,2,FALSE())*AE$1) -> 0 | ... CJ9: =IF(BB9="",0,VLOOKUP(P9,Tables!$B$3:$D$36,2,FALSE())*AL$1) -> 0 | CK9: =IF(AN9="",0,VLOOKUP(B9,Tables!$B$3:$D$36,3,FALSE())*X$1)*IF(OR(AN9="K",AN9="P"),2,1) -> 0 | CL9: =IF(AO9="",0,VLOOKUP(C9,Tables!$B$3:$D$36,3,FALSE())*Y$1)*IF(OR(AO9="K",AO9="P"),2,1) -> 0 | CM9: =IF(AP9="",0,VLOOKUP(D9,Tables!$B$3:$D$36,3,FALSE())*Z$1)*IF(OR(AP9="K",AP9="P"),2,1) -> 0 | CN9: =IF(AQ9="",0,VLOOKUP(E9,Tables!$B$3:$D$36,3,FALSE())*AA$1) -> 0.15 | CO9: =IF(AR9="",0,VLOOKUP(F9,Tables!$B$3:$D$36,3,FALSE())*AB$1) -> 0.3 | CP9: =IF(AS9="",0,VLOOKUP(G9,Tables!$B$3:$D$36,3,FALSE())*AC$1) -> 0 | CQ9: =IF(AT9="",0,VLOOKUP(H9,Tables!$B$3:$D$36,3,FALSE())*AD$1) -> 0 | CR9: =IF(AU9="",0,VLOOKUP(I9,Tables!$B$3:$D$36,3,FALSE())*AE$1) -> 0 | CS9: =IF(AV9="",0,VLOOKUP(J9,Tables!$B$3:$D$36,3,FALSE())*AF$1) -> 0.6 | CT9: =IF(AW9="",0,VLOOKUP(K9,Tables!$B$3:$D$36,3,FALSE())*AG$1) -> 0.6 | CU9: =IF(AX9="",0,VLOOKUP(L9,Tables!$B$3:$D$36,3,FALSE())*AH$1) -> 0 | ... CY9: =IF(BB9="",0,VLOOKUP(P9,Tables!$B$3:$D$36,3,FALSE())*AL$1) -> 0 | CZ9: =IF(B9="",0,VLOOKUP(B9,MATERIAL,10,FALSE())) -> 0 | DA9: =IF(C9="",0,VLOOKUP(C9,MATERIAL,10,FALSE())) -> 0 | DB9: =IF(D9="",0,VLOOKUP(D9,MATERIAL,10,FALSE())) -> 0 | DC9: =IF(E9="",0,VLOOKUP(E9,MATERIAL,10,FALSE())) -> 1 | DD9: =IF(F9="",0,VLOOKUP(F9,MATERIAL,10,FALSE())) -> 1 | DE9: =IF(G9="",0,VLOOKUP(G9,MATERIAL,10,FALSE())) -> 0 | DF9: =IF(H9="",0,VLOOKUP(H9,MATERIAL,10,FALSE())) -> 0 | DG9: =IF(I9="",0,VLOOKUP(I9,MATERIAL,10,FALSE())) -> 0 | ... DN9: =IF(P9="",0,VLOOKUP(P9,MATERIAL,10,FALSE())) -> 0 | DO9: =IF(AN9="",0,VLOOKUP(B9,Tables!$B$3:$M$36,11,FALSE())*X$1) -> 0 | DP9: =IF(AO9="",0,VLOOKUP(C9,Tables!$B$3:$M$36,11,FALSE())*Y$1) -> 0 | DQ9: =IF(AP9="",0,VLOOKUP(D9,Tables!$B$3:$M$36,11,FALSE())*Z$1) -> 0 | DR9: =IF(AQ9="",0,VLOOKUP(E9,Tables!$B$3:$M$36,11,FALSE())*AA$1) -> 0.6 | DS9: =IF(AR9="",0,VLOOKUP(F9,Tables!$B$3:$M$36,11,FALSE())*AB$1) -> 1.2 | DT9: =IF(AS9="",0,VLOOKUP(G9,Tables!$B$3:$M$36,11,FALSE())*AC$1) -> 0 | DU9: =IF(AT9="",0,VLOOKUP(H9,Tables!$B$3:$M$36,11,FALSE())*AD$1) -> 0 | DV9: =IF(AU9="",0,VLOOKUP(I9,Tables!$B$3:$M$36,11,FALSE())*AE$1) -> 0 | ... EC9: =IF(BB9="",0,VLOOKUP(P9,Tables!$B$3:$M$36,11,FALSE())*AL$1) -> 0 | ED9: =IF(AN9="",0,VLOOKUP(B9,Tables!$B$3:$M$36,12,FALSE())*X$1) -> 0 | EE9: =IF(AO9="",0,VLOOKUP(C9,Tables!$B$3:$M$36,12,FALSE())*Y$1) -> 0 | EF9: =IF(AP9="",0,VLOOKUP(D9,Tables!$B$3:$M$36,12,FALSE())*Z$1) -> 0 | EG9: =IF(AQ9="",0,VLOOKUP(E9,Tables!$B$3:$M$36,12,FALSE())*AA$1) -> 2.4 | EH9: =IF(AR9="",0,VLOOKUP(F9,Tables!$B$3:$M$36,12,FALSE())*AB$1) -> 4.8 | EI9: =IF(AS9="",0,VLOOKUP(G9,Tables!$B$3:$M$36,12,FALSE())*AC$1) -> 0 | EJ9: =IF(AT9="",0,VLOOKUP(H9,Tables!$B$3:$M$36,12,FALSE())*AD$1) -> 0 | EK9: =IF(AU9="",0,VLOOKUP(I9,Tables!$B$3:$M$36,12,FALSE())*AE$1) -> 0 | ... ER9: =IF(BB9="",0,VLOOKUP(P9,Tables!$B$3:$M$36,12,FALSE())*AL$1) -> 0 | ES9: =IF(MIN(ET9:FH9)=10,0,MIN(ET9:FH9)) -> 0 | ET9: =IF(AN9="",10,MIN(VLOOKUP(B9,Tables!$B$3:$N$34,13,FALSE()),'Item Builder'!$W9)) -> 10 | EU9: =IF(AO9="",10,MIN(VLOOKUP(C9,Tables!$B$3:$N$34,13,FALSE()),'Item Builder'!$W9)) -> 10 | EV9: =IF(AP9="",10,MIN(VLOOKUP(D9,Tables!$B$3:$N$34,13,FALSE()),'Item Builder'!$W9)) -> 10 | EW9: =IF(AQ9="",10,MIN(VLOOKUP(E9,Tables!$B$3:$N$34,13,FALSE()),'Item Builder'!$W9)) -> 0 | EX9: =IF(AR9="",10,MIN(VLOOKUP(F9,Tables!$B$3:$N$34,13,FALSE()),'Item Builder'!$W9)) -> 0 | EY9: =IF(AS9="",10,MIN(VLOOKUP(G9,Tables!$B$3:$N$34,13,FALSE()),'Item Builder'!$W9)) -> 10 | EZ9: =IF(AT9="",10,MIN(VLOOKUP(H9,Tables!$B$3:$N$34,13,FALSE()),'Item Builder'!$W9)) -> 10 | FA9: =IF(AU9="",10,MIN(VLOOKUP(I9,Tables!$B$3:$N$34,13,FALSE()),'Item Builder'!$W9)) -> 10 | ... FH9: =IF(BB9="",10,MIN(VLOOKUP(P9,Tables!$B$3:$N$34,13,FALSE()),'Item Builder'!$W9)) -> 10 | FJ9: Russet | FL9: Cr | FM9: Crb
